Workbook

Sheet NTFP Check
A1: Resight ID | B1: Rankings | C1: Name | D1: Changes (Name, Title, Location, Picture)
A2: IND00327 | B2: Arbitration | C2: Indranil Deshmukh | D2: *Indranil D. Deshmukh*
A3: IND00345 | B3: Arbitration | C3: Lomesh Nidumuri | D3: *Lomesh Kiran Nidumuri*
A4: IND00788 | B4: Arbitration | C4: Shankh Sengupta | D4: *Partner & Head of Dispute Practice*
A5: IND01048 | B5: Arbitration | C5: Sneha Jaisingh | D5: *Partner and Practice Lead*
A6: IND07574 | B6: Arbitration | C6: Sooraj Sharma | D6: *Founding Partner*
A7: IND02631 | B7: Arbitration | C7: Gunita Pahwa | D7: *Delhi*
A8: IND02109 | B8: Capital Markets - Debt | C8: Uttara M. Kolhatkar | D8: *Uttara M. Kolhatkar*
A9: IND00398 | B9: Capital Markets - Debt; Private Capital | C9: Subhalakshmi Naskar | D9: *Partner (Co-head - Projects (Infrastructure))*
A10: IND00271 | B10: Capital Markets - Equity | C10: Abhinav Kumar | D10: *WRONG IMAGE - uses Abhinav Maker's*
A11: IND00715 | B11: Capital Markets - Equity | C11: Bhakta Patnaik | D11: Partner and Head of Capital Markets Practice
A12: IND00323 | B12: Capital Markets - Equity | C12: Gokul Rajan | D12: Regional *Co-*head
... A33: IND00250 | B33: International Trade | C33: Udayan Choksi | D33: *Senior Partner*

Sheet RISE_lawyers
A1: Resight ID | B1: Rankings | C1: Name | D1: Position | E1: Position Check | F1: Location | G1: Column1 | H1: Organisation | I1: Bio | J1: Changes (Name, Title, Location, Picture)
A2: IND00020 | B2: Arbitration | C2: Ajay Bhargava | D2: Partner | E2: =IF(D2=(_xlfn.XLOOKUP(RISE_lawyers!$A2, All!$A$2:$A$158,All!H$2:H$158)), TRUE, FALSE) -> TRUE | F2: Delhi | G2: =IF(F2=(_xlfn.XLOOKUP(RISE_lawyers!$A2, All!$A$2:$A$158,All!G$2:G$158)), TRUE, FALSE) -> TRUE | H2: Khaitan & Co | J2: X
A3: IND07515 | B3: Arbitration | C3: Ashim Sood | D3: Principal | E3: =IF(D3=(_xlfn.XLOOKUP(RISE_lawyers!$A3, All!$A$2:$A$158,All!H$2:H$158)), TRUE, FALSE) -> TRUE | F3: Delhi | G3: =IF(F3=(_xlfn.XLOOKUP(RISE_lawyers!$A3, All!$A$2:$A$158,All!G$2:G$158)), TRUE, FALSE) -> TRUE | H3: Ashim Sood Law Offices | J3: X
A4: IND00712 | B4: Arbitration | C4: Ashish Bhan | D4: Partner | E4: =IF(D4=(_xlfn.XLOOKUP(RISE_lawyers!$A4, All!$A$2:$A$158,All!H$2:H$158)), TRUE, FALSE) -> TRUE | F4: Delhi | G4: =IF(F4=(_xlfn.XLOOKUP(RISE_lawyers!$A4, All!$A$2:$A$158,All!G$2:G$158)), TRUE, FALSE) -> TRUE | H4: Trilegal | J4: X
A5: IND00439 | B5: Arbitration | C5: Binsy Susan | D5: Partner | E5: =IF(D5=(_xlfn.XLOOKUP(RISE_lawyers!$A5, All!$A$2:$A$158,All!H$2:H$158)), TRUE, FALSE) -> TRUE | F5: Delhi | G5: =IF(F5=(_xlfn.XLOOKUP(RISE_lawyers!$A5, All!$A$2:$A$158,All!G$2:G$158)), TRUE, FALSE) -> TRUE | H5: Shardul Amarchand Mangaldas & Co | J5: X
A6: IND00064 | B6: Arbitration | C6: Chakrapani Misra | D6: Senior Partner | E6: =IF(D6=(_xlfn.XLOOKUP(RISE_lawyers!$A6, All!$A$2:$A$158,All!H$2:H$158)), TRUE, FALSE) -> TRUE | F6: Mumbai | G6: =IF(F6=(_xlfn.XLOOKUP(RISE_lawyers!$A6, All!$A$2:$A$158,All!G$2:G$158)), TRUE, FALSE) -> TRUE | H6: Khaitan & Co | J6: X
A7: IND01936 | B7: Arbitration | C7: Dheeraj Nair | D7: Partner | E7: =IF(D7=(_xlfn.XLOOKUP(RISE_lawyers!$A7, All!$A$2:$A$158,All!H$2:H$158)), TRUE, FALSE) -> TRUE | F7: Delhi | G7: =IF(F7=(_xlfn.XLOOKUP(RISE_lawyers!$A7, All!$A$2:$A$158,All!G$2:G$158)), TRUE, FALSE) -> TRUE | H7: JSA Advocates & Solicitors | J7: X
A8: IND00456 | B8: Arbitration | C8: Ila Kapoor | D8: Partner | E8: =IF(D8=(_xlfn.XLOOKUP(RISE_lawyers!$A8, All!$A$2:$A$158,All!H$2:H$158)), TRUE, FALSE) -> TRUE | F8: Delhi | G8: =IF(F8=(_xlfn.XLOOKUP(RISE_lawyers!$A8, All!$A$2:$A$158,All!G$2:G$158)), TRUE, FALSE) -> TRUE | H8: Shardul Amarchand Mangaldas & Co | J8: X
A9: IND00327 | B9: Arbitration | C9: Indranil Deshmukh | D9: Partner & Head of Disputes | E9: =IF(D9=(_xlfn.XLOOKUP(RISE_lawyers!$A9, All!$A$2:$A$158,All!H$2:H$158)), TRUE, FALSE) -> TRUE | F9: Mumbai | G9: =IF(F9=(_xlfn.XLOOKUP(RISE_lawyers!$A9, All!$A$2:$A$158,All!G$2:G$158)), TRUE, FALSE) -> TRUE | H9: Cyril Amarchand Mangaldas | J9: *Indranil D. Deshmukh*
A10: IND00337 | B10: Arbitration | C10: Kapil Arora | D10: Partner | E10: =IF(D10=(_xlfn.XLOOKUP(RISE_lawyers!$A10, All!$A$2:$A$158,All!H$2:H$158)), TRUE, FALSE) -> TRUE | F10: Delhi | G10: =IF(F10=(_xlfn.XLOOKUP(RISE_lawyers!$A10, All!$A$2:$A$158,All!G$2:G$158)), TRUE, FALSE) -> TRUE | H10: Cyril Amarchand Mangaldas | J10: X
A11: IND00739 | B11: Arbitration | C11: Ketan Gaur | D11: Partner | E11: =IF(D11=(_xlfn.XLOOKUP(RISE_lawyers!$A11, All!$A$2:$A$158,All!H$2:H$158)), TRUE, FALSE) -> TRUE | F11: Delhi | G11: =IF(F11=(_xlfn.XLOOKUP(RISE_lawyers!$A11, All!$A$2:$A$158,All!G$2:G$158)), TRUE, FALSE) -> TRUE | H11: Trilegal | J11: X
A12: IND00112 | B12: Arbitration | C12: Kingshuk Banerjee | D12: Partner | E12: =IF(D12=(_xlfn.XLOOKUP(RISE_lawyers!$A12, All!$A$2:$A$158,All!H$2:H$158)), TRUE, FALSE) -> TRUE | F12: Mumbai | G12: =IF(F12=(_xlfn.XLOOKUP(RISE_lawyers!$A12, All!$A$2:$A$158,All!G$2:G$158)), TRUE, FALSE) -> TRUE | H12: Khaitan & Co | J12: X
A13: IND00345 | B13: Arbitration | C13: Lomesh Nidumuri | D13: Partner (Head - Disputes, South India) | E13: =IF(D13=(_xlfn.XLOOKUP(RISE_lawyers!$A13, All!$A$2:$A$158,All!H$2:H$158)), TRUE, FALSE) -> TRUE | F13: Bengaluru | G13: =IF(F13=(_xlfn.XLOOKUP(RISE_lawyers!$A13, All!$A$2:$A$158,All!G$2:G$158)), TRUE, FALSE) -> TRUE | H13: Cyril Amarchand Mangaldas | J13: *Lomesh Kiran Nidumuri*
... A19: IND00589 | B19: Arbitration | C19: Rajendra Barot | D19: Senior Partner | E19: =IF(D19=(_xlfn.XLOOKUP(RISE_lawyers!$A19, All!$A$2:$A$158,All!H$2:H$158)), TRUE, FALSE) -> TRUE | F19: Mumbai | G19: =IF(F19=(_xlfn.XLOOKUP(RISE_lawyers!$A19, All!$A$2:$A$158,All!G$2:G$158)), TRUE, FALSE) -> TRUE | H19: AZB & Partners | J19: X
A20: IND00929 | B20: Arbitration | C20: Sameer Tapia | D20: Founder & Senior Partner | E20: =IF(D20=(_xlfn.XLOOKUP(RISE_lawyers!$A20, All!$A$2:$A$158,All!H$2:H$158)), TRUE, FALSE) -> TRUE | F20: Mumbai | G20: =IF(F20=(_xlfn.XLOOKUP(RISE_lawyers!$A20, All!$A$2:$A$158,All!G$2:G$158)), TRUE, FALSE) -> TRUE | H20: ALMT Legal | J20: X | K20: *Instruction Scores look off*
A21: IND00197 | B21: Arbitration | C21: Sanjeev K Kapoor | D21: Partner | E21: =IF(D21=(_xlfn.XLOOKUP(RISE_lawyers!$A21, All!$A$2:$A$158,All!H$2:H$158)), TRUE, FALSE) -> TRUE | F21: Delhi | G21: =IF(F21=(_xlfn.XLOOKUP(RISE_lawyers!$A21, All!$A$2:$A$158,All!G$2:G$158)), TRUE, FALSE) -> TRUE | H21: Khaitan & Co | J21: X
A22: IND00386 | B22: Arbitration | C22: Shaneen Parikh | D22: Partner (Head - International Arbitration) | E22: =IF(D22=(_xlfn.XLOOKUP(RISE_lawyers!$A22, All!$A$2:$A$158,All!H$2:H$158)), TRUE, FALSE) -> TRUE | F22: Mumbai | G22: =IF(F22=(_xlfn.XLOOKUP(RISE_lawyers!$A22, All!$A$2:$A$158,All!G$2:G$158)), TRUE, FALSE) -> TRUE | H22: Cyril Amarchand Mangaldas | J22: X
A23: IND00788 | B23: Arbitration | C23: Shankh Sengupta | D23: Partner | E23: =IF(D23=(_xlfn.XLOOKUP(RISE_lawyers!$A23, All!$A$2:$A$158,All!H$2:H$158)), TRUE, FALSE) -> TRUE | F23: Delhi | G23: =IF(F23=(_xlfn.XLOOKUP(RISE_lawyers!$A23, All!$A$2:$A$158,All!G$2:G$158)), TRUE, FALSE) -> TRUE | H23: Trilegal | J23: *Partner & Head of Dispute Practice*
A24: IND00540 | B24: Arbitration | C24: Smarika Singh | D24: Partner | E24: =IF(D24=(_xlfn.XLOOKUP(RISE_lawyers!$A24, All!$A$2:$A$158,All!H$2:H$158)), TRUE, FALSE) -> TRUE | F24: Delhi | G24: =IF(F24=(_xlfn.XLOOKUP(RISE_lawyers!$A24, All!$A$2:$A$158,All!G$2:G$158)), TRUE, FALSE) -> TRUE | H24: Shardul Amarchand Mangaldas & Co | J24: X
A25: IND01048 | B25: Arbitration | C25: Sneha Jaisingh | D25: Partner | E25: =IF(D25=(_xlfn.XLOOKUP(RISE_lawyers!$A25, All!$A$2:$A$158,All!H$2:H$158)), TRUE, FALSE) -> TRUE | F25: Mumbai | G25: =IF(F25=(_xlfn.XLOOKUP(RISE_lawyers!$A25, All!$A$2:$A$158,All!G$2:G$158)), TRUE, FALSE) -> TRUE | H25: Bharucha & Partners | J25: *Partner and Practice Lead*
A26: IND07574 | B26: Arbitration | C26: Sooraj Sharma | D26: Partner | E26: =IF(D26=(_xlfn.XLOOKUP(RISE_lawyers!$A26, All!$A$2:$A$158,All!H$2:H$158)), TRUE, FALSE) -> TRUE | F26: Delhi | G26: =IF(F26=(_xlfn.XLOOKUP(RISE_lawyers!$A26, All!$A$2:$A$158,All!G$2:G$158)), TRUE, FALSE) -> TRUE | H26: Clavius Legal | J26: *Founding Partner*
A27: IND02569 | B27: Arbitration | C27: Suvigya Awasthy | D27: Partner | E27: =IF(D27=(_xlfn.XLOOKUP(RISE_lawyers!$A27, All!$A$2:$A$158,All!H$2:H$158)), TRUE, FALSE) -> TRUE | F27: Delhi | G27: =IF(F27=(_xlfn.XLOOKUP(RISE_lawyers!$A27, All!$A$2:$A$158,All!G$2:G$158)), TRUE, FALSE) -> TRUE | H27: PSL Advocates & Solicitors | J27: X
A28: IND00801 | B28: Arbitration | C28: Tine Abraham | D28: Partner | E28: =IF(D28=(_xlfn.XLOOKUP(RISE_lawyers!$A28, All!$A$2:$A$158,All!H$2:H$158)), TRUE, FALSE) -> TRUE | F28: Delhi | G28: =IF(F28=(_xlfn.XLOOKUP(RISE_lawyers!$A28, All!$A$2:$A$158,All!G$2:G$158)), TRUE, FALSE) -> TRUE | H28: Trilegal | J28: X
A29: IND00602 | B29: Arbitration | C29: Vijayendra Pratap Singh | D29: Senior Partner | E29: =IF(D29=(_xlfn.XLOOKUP(RISE_lawyers!$A29, All!$A$2:$A$158,All!H$2:H$158)), TRUE, FALSE) -> TRUE | F29: Delhi | G29: =IF(F29=(_xlfn.XLOOKUP(RISE_lawyers!$A29, All!$A$2:$A$158,All!G$2:G$158)), TRUE, FALSE) -> TRUE | H29: AZB & Partners | J29: X
A30: IND02504 | B30: Arbitration | C30: Vyapak Desai | D30: Counsel | E30: =IF(D30=(_xlfn.XLOOKUP(RISE_lawyers!$A30, All!$A$2:$A$158,All!H$2:H$158)), TRUE, FALSE) -> TRUE | F30: Mumbai | G30: =IF(F30=(_xlfn.XLOOKUP(RISE_lawyers!$A30, All!$A$2:$A$158,All!G$2:G$158)), TRUE, FALSE) -> TRUE | H30: Vyapak Desai Law Chambers | J30: X
A31: IND02631 | B31: Arbitration | C31: Gunita Pahwa | D31: Joint Managing Partner | E31: =IF(D31=(_xlfn.XLOOKUP(RISE_lawyers!$A31, All!$A$2:$A$158,All!H$2:H$158)), TRUE, FALSE) -> TRUE | F31: Delhi | G31: =IF(F31=(_xlfn.XLOOKUP(RISE_lawyers!$A31, All!$A$2:$A$158,All!G$2:G$158)), TRUE, FALSE) -> TRUE | H31: S&A Law Offices | J31: *Delhi*
A32: IND02534 | B32: Capital Markets - Debt | C32: Aditya Bhargava | D32: Partner | E32: =IF(D32=(_xlfn.XLOOKUP(RISE_lawyers!$A32, All!$A$2:$A$158,All!H$2:H$158)), TRUE, FALSE) -> TRUE | F32: Mumbai | G32: =IF(F32=(_xlfn.XLOOKUP(RISE_lawyers!$A32, All!$A$2:$A$158,All!G$2:G$158)), TRUE, FALSE) -> TRUE | H32: Trilegal | J32: X
... A121: IND01511 | B121: Competition; International Trade | C121: Parthsarathi Jha | D121: Partner | E121: =IF(D121=(_xlfn.XLOOKUP(RISE_lawyers!$A121, All!$A$2:$A$158,All!H$2:H$158)), TRUE, FALSE) -> TRUE | F121: Delhi | G121: =IF(F121=(_xlfn.XLOOKUP(RISE_lawyers!$A121, All!$A$2:$A$158,All!G$2:G$158)), TRUE, FALSE) -> TRUE | H121: Economic Laws Practice | J121: X
A122: IND05097 | B122: Cyber | C122: Aadya Misra | D122: Counsel | E122: =IF(D122=(_xlfn.XLOOKUP(RISE_lawyers!$A122, All!$A$2:$A$158,All!H$2:H$158)), TRUE, FALSE) -> TRUE | F122: Bengaluru | G122: =IF(F122=(_xlfn.XLOOKUP(RISE_lawyers!$A122, All!$A$2:$A$158,All!G$2:G$158)), TRUE, FALSE) -> TRUE | H122: Spice Route Legal
A123: IND04874 | B123: Cyber | C123: Akash Karmakar | D123: Partner | E123: =IF(D123=(_xlfn.XLOOKUP(RISE_lawyers!$A123, All!$A$2:$A$158,All!H$2:H$158)), TRUE, FALSE) -> TRUE | F123: Delhi | G123: =IF(F123=(_xlfn.XLOOKUP(RISE_lawyers!$A123, All!$A$2:$A$158,All!G$2:G$158)), TRUE, FALSE) -> TRUE | H123: Panag & Babu
A124: IND00291 | B124: Cyber | C124: Anirban Mohapatra | D124: Partner | E124: =IF(D124=(_xlfn.XLOOKUP(RISE_lawyers!$A124, All!$A$2:$A$158,All!H$2:H$158)), TRUE, FALSE) -> TRUE | F124: Bengaluru | G124: =IF(F124=(_xlfn.XLOOKUP(RISE_lawyers!$A124, All!$A$2:$A$158,All!G$2:G$158)), TRUE, FALSE) -> TRUE | H124: Cyril Amarchand Mangaldas
A125: IND00298 | B125: Cyber | C125: Arun Prabhu | D125: Partner (Co-head - Technology & Telecommunications) | E125: =IF(D125=(_xlfn.XLOOKUP(RISE_lawyers!$A125, All!$A$2:$A$158,All!H$2:H$158)), TRUE, FALSE) -> TRUE | F125: Bengaluru | G125: =IF(F125=(_xlfn.XLOOKUP(RISE_lawyers!$A125, All!$A$2:$A$158,All!G$2:G$158)), TRUE, FALSE) -> TRUE | H125: Cyril Amarchand Mangaldas | J125: *Arun S. Prabhu*
A126: IND00095 | B126: Cyber | C126: Harsh Walia | D126: Partner | E126: =IF(D126=(_xlfn.XLOOKUP(RISE_lawyers!$A126, All!$A$2:$A$158,All!H$2:H$158)), TRUE, FALSE) -> TRUE | F126: Delhi | G126: =IF(F126=(_xlfn.XLOOKUP(RISE_lawyers!$A126, All!$A$2:$A$158,All!G$2:G$158)), TRUE, FALSE) -> TRUE | H126: Khaitan & Co
A127: IND00455 | B127: Cyber | C127: Hemant Krishna | D127: Partner | E127: =IF(D127=(_xlfn.XLOOKUP(RISE_lawyers!$A127, All!$A$2:$A$158,All!H$2:H$158)), TRUE, FALSE) -> TRUE | F127: Bengaluru | G127: =IF(F127=(_xlfn.XLOOKUP(RISE_lawyers!$A127, All!$A$2:$A$158,All!G$2:G$158)), TRUE, FALSE) -> TRUE | H127: Shardul Amarchand Mangaldas & Co
A128: IND00732 | B128: Cyber | C128: Jaideep Reddy | D128: Partner | E128: =IF(D128=(_xlfn.XLOOKUP(RISE_lawyers!$A128, All!$A$2:$A$158,All!H$2:H$158)), TRUE, FALSE) -> TRUE | F128: Bengaluru | G128: =IF(F128=(_xlfn.XLOOKUP(RISE_lawyers!$A128, All!$A$2:$A$158,All!G$2:G$158)), TRUE, FALSE) -> TRUE | H128: Trilegal
A129: IND00734 | B129: Cyber | C129: Jyotsna Jayaram | D129: Partner | E129: =IF(D129=(_xlfn.XLOOKUP(RISE_lawyers!$A129, All!$A$2:$A$158,All!H$2:H$158)), TRUE, FALSE) -> TRUE | F129: Bengaluru | G129: =IF(F129=(_xlfn.XLOOKUP(RISE_lawyers!$A129, All!$A$2:$A$158,All!G$2:G$158)), TRUE, FALSE) -> TRUE | H129: Trilegal
A130: IND03226 | B130: Cyber | C130: Mathew Chacko | D130: Founding Partner | E130: =IF(D130=(_xlfn.XLOOKUP(RISE_lawyers!$A130, All!$A$2:$A$158,All!H$2:H$158)), TRUE, FALSE) -> TRUE | F130: Bengaluru | G130: =IF(F130=(_xlfn.XLOOKUP(RISE_lawyers!$A130, All!$A$2:$A$158,All!G$2:G$158)), TRUE, FALSE) -> TRUE | H130: Spice Route Legal
A131: IND01738 | B131: Cyber | C131: Namita Viswanath | D131: Partner | E131: =IF(D131=(_xlfn.XLOOKUP(RISE_lawyers!$A131, All!$A$2:$A$158,All!H$2:H$158)), TRUE, FALSE) -> TRUE | F131: Bengaluru | G131: =IF(F131=(_xlfn.XLOOKUP(RISE_lawyers!$A131, All!$A$2:$A$158,All!G$2:G$158)), TRUE, FALSE) -> TRUE | H131: CMS INDUSLAW
A132: IND07527 | B132: Cyber | C132: Nehaa Chaudhari | D132: Partner | E132: =IF(D132=(_xlfn.XLOOKUP(RISE_lawyers!$A132, All!$A$2:$A$158,All!H$2:H$158)), TRUE, FALSE) -> TRUE | F132: Bengaluru | G132: =IF(F132=(_xlfn.XLOOKUP(RISE_lawyers!$A132, All!$A$2:$A$158,All!G$2:G$158)), TRUE, FALSE) -> TRUE | H132: Ikigai Law
A133: IND00757 | B133: Cyber | C133: Nikhil Narendran | D133: Partner | E133: =IF(D133=(_xlfn.XLOOKUP(RISE_lawyers!$A133, All!$A$2:$A$158,All!H$2:H$158)), TRUE, FALSE) -> TRUE | F133: Bengaluru | G133: =IF(F133=(_xlfn.XLOOKUP(RISE_lawyers!$A133, All!$A$2:$A$158,All!G$2:G$158)), TRUE, FALSE) -> TRUE | H133: Trilegal
A134: IND02023 | B134: Cyber | C134: Probir Roy Chowdhury | D134: Partner | E134: =IF(D134=(_xlfn.XLOOKUP(RISE_lawyers!$A134, All!$A$2:$A$158,All!H$2:H$158)), TRUE, FALSE) -> TRUE | F134: Bengaluru | G134: =IF(F134=(_xlfn.XLOOKUP(RISE_lawyers!$A134, All!$A$2:$A$158,All!G$2:G$158)), TRUE, FALSE) -> TRUE | H134: JSA Advocates & Solicitors
A135: IND01749 | B135: Cyber | C135: Ranjana Adhikari | D135: Partner | E135: =IF(D135=(_xlfn.XLOOKUP(RISE_lawyers!$A135, All!$A$2:$A$158,All!H$2:H$158)), TRUE, FALSE) -> TRUE | F135: Mumbai | G135: =IF(F135=(_xlfn.XLOOKUP(RISE_lawyers!$A135, All!$A$2:$A$158,All!G$2:G$158)), TRUE, FALSE) -> TRUE | H135: Shardul Amarchand Mangaldas & Co
A136: IND04894 | B136: Cyber | C136: Rishi Anand | D136: Partner | E136: =IF(D136=(_xlfn.XLOOKUP(RISE_lawyers!$A136, All!$A$2:$A$158,All!H$2:H$158)), TRUE, FALSE) -> TRUE | F136: Delhi | G136: =IF(F136=(_xlfn.XLOOKUP(RISE_lawyers!$A136, All!$A$2:$A$158,All!G$2:G$158)), TRUE, FALSE) -> TRUE | H136: DSK Legal
A137: IND02052 | B137: Cyber | C137: Sajai Singh | D137: Partner | E137: =IF(D137=(_xlfn.XLOOKUP(RISE_lawyers!$A137, All!$A$2:$A$158,All!H$2:H$158)), TRUE, FALSE) -> TRUE | F137: Bengaluru | G137: =IF(F137=(_xlfn.XLOOKUP(RISE_lawyers!$A137, All!$A$2:$A$158,All!G$2:G$158)), TRUE, FALSE) -> TRUE | H137: JSA Advocates & Solicitors
... A145: IND01267 | B145: International Trade | C145: Ashish Chandra | D145: Partner | E145: =IF(D145=(_xlfn.XLOOKUP(RISE_lawyers!$A145, All!$A$2:$A$158,All!H$2:H$158)), TRUE, FALSE) -> TRUE | F145: Delhi | G145: =IF(F145=(_xlfn.XLOOKUP(RISE_lawyers!$A145, All!$A$2:$A$158,All!G$2:G$158)), TRUE, FALSE) -> TRUE | H145: DSK Legal
A146: IND07689 | B146: International Trade | C146: Atul Sharma | D146: Partner | E146: =IF(D146=(_xlfn.XLOOKUP(RISE_lawyers!$A146, All!$A$2:$A$158,All!H$2:H$158)), TRUE, FALSE) -> TRUE | F146: Delhi | G146: =IF(F146=(_xlfn.XLOOKUP(RISE_lawyers!$A146, All!$A$2:$A$158,All!G$2:G$158)), TRUE, FALSE) -> TRUE | H146: Sarvada Legal | J146: *Co-Founder and Partner*
A147: IND00059 | B147: International Trade | C147: Ayush Mehrotra | D147: Partner | E147: =IF(D147=(_xlfn.XLOOKUP(RISE_lawyers!$A147, All!$A$2:$A$158,All!H$2:H$158)), TRUE, FALSE) -> TRUE | F147: Delhi | G147: =IF(F147=(_xlfn.XLOOKUP(RISE_lawyers!$A147, All!$A$2:$A$158,All!G$2:G$158)), TRUE, FALSE) -> TRUE | H147: Khaitan & Co
A148: IND02203 | B148: International Trade | C148: Devinder Bagia | D148: Partner | E148: =IF(D148=(_xlfn.XLOOKUP(RISE_lawyers!$A148, All!$A$2:$A$158,All!H$2:H$158)), TRUE, FALSE) -> TRUE | F148: Delhi | G148: =IF(F148=(_xlfn.XLOOKUP(RISE_lawyers!$A148, All!$A$2:$A$158,All!G$2:G$158)), TRUE, FALSE) -> TRUE | H148: Lakshmikumaran & Sridharan | J148: *Executive Partner*
A149: IND00723 | B149: International Trade | C149: Dhruv Gupta | D149: Partner | E149: =IF(D149=(_xlfn.XLOOKUP(RISE_lawyers!$A149, All!$A$2:$A$158,All!H$2:H$158)), TRUE, FALSE) -> TRUE | F149: Delhi | G149: =IF(F149=(_xlfn.XLOOKUP(RISE_lawyers!$A149, All!$A$2:$A$158,All!G$2:G$158)), TRUE, FALSE) -> TRUE | H149: Trilegal
A150: IND00121 | B150: International Trade | C150: Mayank Jain | D150: Partner | E150: =IF(D150=(_xlfn.XLOOKUP(RISE_lawyers!$A150, All!$A$2:$A$158,All!H$2:H$158)), TRUE, FALSE) -> TRUE | F150: Mumbai | G150: =IF(F150=(_xlfn.XLOOKUP(RISE_lawyers!$A150, All!$A$2:$A$158,All!G$2:G$158)), TRUE, FALSE) -> TRUE | H150: Khaitan & Co
A151: IND02989 | B151: International Trade | C151: Rajat Agarwal | D151: Partner | E151: =IF(D151=(_xlfn.XLOOKUP(RISE_lawyers!$A151, All!$A$2:$A$158,All!H$2:H$158)), TRUE, FALSE) -> TRUE | F151: Mumbai | G151: =IF(F151=(_xlfn.XLOOKUP(RISE_lawyers!$A151, All!$A$2:$A$158,All!G$2:G$158)), TRUE, FALSE) -> TRUE | H151: VERTICES PARTNERS | J151: *Equity Partner*
A152: IND07621 | B152: International Trade | C152: Reena Khair | D152: Senior Partner | E152: =IF(D152=(_xlfn.XLOOKUP(RISE_lawyers!$A152, All!$A$2:$A$158,All!H$2:H$158)), TRUE, FALSE) -> TRUE | F152: Delhi | G152: =IF(F152=(_xlfn.XLOOKUP(RISE_lawyers!$A152, All!$A$2:$A$158,All!G$2:G$158)), TRUE, FALSE) -> TRUE | H152: Kochhar & Co
A153: IND01522 | B153: International Trade | C153: Sanjay Notani | D153: Partner | E153: =IF(D153=(_xlfn.XLOOKUP(RISE_lawyers!$A153, All!$A$2:$A$158,All!H$2:H$158)), TRUE, FALSE) -> TRUE | F153: Mumbai | G153: =IF(F153=(_xlfn.XLOOKUP(RISE_lawyers!$A153, All!$A$2:$A$158,All!G$2:G$158)), TRUE, FALSE) -> TRUE | H153: Economic Laws Practice | J153: *Partner and Co-head (International Trade & Customs)*
A154: IND07657 | B154: International Trade | C154: Seetharaman Sampath | D154: Founder | E154: =IF(D154=(_xlfn.XLOOKUP(RISE_lawyers!$A154, All!$A$2:$A$158,All!H$2:H$158)), TRUE, FALSE) -> TRUE | F154: Delhi | G154: =IF(F154=(_xlfn.XLOOKUP(RISE_lawyers!$A154, All!$A$2:$A$158,All!G$2:G$158)), TRUE, FALSE) -> TRUE | H154: Sarvada Legal | J154: *Co-Founder and Advocate*
A155: IND00250 | B155: International Trade | C155: Udayan Choksi | D155: Partner | E155: =IF(D155=(_xlfn.XLOOKUP(RISE_lawyers!$A155, All!$A$2:$A$158,All!H$2:H$158)), TRUE, FALSE) -> TRUE | F155: Mumbai | G155: =IF(F155=(_xlfn.XLOOKUP(RISE_lawyers!$A155, All!$A$2:$A$158,All!G$2:G$158)), TRUE, FALSE) -> TRUE | H155: Veritas Legal | J155: *Senior Partner*
A156: IND02274 | B156: International Trade | C156: V. Lakshmikumaran | D156: Founder & Managing Partner | E156: =IF(D156=(_xlfn.XLOOKUP(RISE_lawyers!$A156, All!$A$2:$A$158,All!H$2:H$158)), TRUE, FALSE) -> TRUE | F156: Delhi | G156: =IF(F156=(_xlfn.XLOOKUP(RISE_lawyers!$A156, All!$A$2:$A$158,All!G$2:G$158)), TRUE, FALSE) -> TRUE | H156: Lakshmikumaran & Sridharan
A157: IND02976 | B157: Private Capital | C157: Abhijit Joshi | D157: Founding & Managing Partner | E157: =IF(D157=(_xlfn.XLOOKUP(RISE_lawyers!$A157, 'Private Capital'!$A$2:$A$51,'Private Capital'!G$2:G$51)), TRUE, FALSE) -> TRUE | F157: Mumbai | G157: =IF(F157=(_xlfn.XLOOKUP(RISE_lawyers!$A157, 'Private Capital'!$A$2:$A$51,'Private Capital'!F$2:F$51)), TRUE, FALSE) -> TRUE | H157: Veritas Legal | I157: Abhijit Joshi is the founder and managing partner of Veritas Legal and maintains a top-quality private equity practice. Abhijit has built expertiseÂ in e-commerce, chemicals and pharmaceuticals, sectors where regulatory complexity intersects with commercial sophistication. _x000D_ _x000D_ Placed in the Top 10 for instructions, Abhijitâ€™s client relationships include some of the market's most sophisticated institutions, including KKR, Brookfield Asset Management,Â KedaaraÂ Capital, Partners Group and 360 One. The quality of his client bases gives him one of the tops scores in the market against this metric. _x000D_ _x000D_ Abhijit has a strong reputation featuring frequently in the media and in directory rankings. _x000D_ _x000D_ What distinguishes Abhijit's practice is his appetite for highly complex deals, gravitating towards transactions that demand intricate structuring and deep technical expertise regardless of size.Â
A158: IND00696 | B158: Private Capital | C158: Aditya Jha | D158: Partner | E158: =IF(D158=(_xlfn.XLOOKUP(RISE_lawyers!$A158, 'Private Capital'!$A$2:$A$51,'Private Capital'!G$2:G$51)), TRUE, FALSE) -> TRUE | F158: Mumbai | G158: =IF(F158=(_xlfn.XLOOKUP(RISE_lawyers!$A158, 'Private Capital'!$A$2:$A$51,'Private Capital'!F$2:F$51)), TRUE, FALSE) -> TRUE | H158: Trilegal | I158: Aditya Jha advises leading domestic and global sponsors on private equity and fund formation matters, including repeat mandates for Edelweiss, A91 Partners, IFC, ICICI and Morgan Stanley. Adityaâ€™s instruction score is above the market average, having completed a high number of deals during the research period. His portfolio also reflects experience supporting sponsors through high-value exits and secondary monetisation._x000D_ _x000D_ His approach is highly execution-focused, balancing investor negotiation with regulatory accuracy. He integrates automation tools, market data and blended pricing to provide greater cost predictability. Trilegal is advanced in its attitude to technology, andÂ is experimenting with deployingÂ leaner teams augmented by AI. Aditya receives a top score for his use of deal data and analytics in his practice.
A159: IND00701 | B159: Private Capital | C159: Amit Khansaheb | D159: Partner | E159: =IF(D159=(_xlfn.XLOOKUP(RISE_lawyers!$A159, 'Private Capital'!$A$2:$A$51,'Private Capital'!G$2:G$51)), TRUE, FALSE) -> TRUE | F159: Gurugram | G159: =IF(F159=(_xlfn.XLOOKUP(RISE_lawyers!$A159, 'Private Capital'!$A$2:$A$51,'Private Capital'!F$2:F$51)), TRUE, FALSE) -> TRUE | H159: Trilegal | I159: Amit Khansaheb advises sponsors including TA Associates, Lightrock, Lightspeed, Faering Capital and Greater Pacific Capital across both growth capital and control investments. His practice spans healthcare, consumer, technology and renewable industries. Repeat engagements reflect client confidence._x000D_ _x000D_ He shapes governance and investor protections to match business maturity, keeping negotiations commercial without losing sight of risk. Amit co-ordinates institutional knowledge across his mandates, ensuring consistent execution on key terms such as indemnity structuring and regulatory touchpoints._x000D_ _x000D_ Directory recognition and co-lead roles on significant mandates like A91 Partners Fund III underscore Amit'sÂ strong market profile. His growing status as an adviser for sponsors operating in competitive deal environments is driving more demand for his advice.
A160: IND00566 | B160: Private Capital | C160: Anil Kasturi | D160: Senior Partner | E160: =IF(D160=(_xlfn.XLOOKUP(RISE_lawyers!$A160, 'Private Capital'!$A$2:$A$51,'Private Capital'!G$2:G$51)), TRUE, FALSE) -> TRUE | F160: Delhi | G160: =IF(F160=(_xlfn.XLOOKUP(RISE_lawyers!$A160, 'Private Capital'!$A$2:$A$51,'Private Capital'!F$2:F$51)), TRUE, FALSE) -> TRUE | H160: AZB & Partners | I160: Anil Kasturi, a senior partner at AZB & Partners, has developed a broad private equity, venture capital and private credit practice. With one of the best reputations in the market, Anil is placed in the Top 10, with particularly strong recognition in legal directories._x000D_ _x000D_ His client relationships include Everstone Capital and Warburg Pincus, amongst other top investment houses. His philosophy towards legal advice emphasises providing a holistic perspective beyond pure technical analysis and ensuring availability to clients. _x000D_ _x000D_ The firm platform at AZB provides an opportunity to service complex, high-value private equity mandates.
A161: IND00569 | B161: Private Capital | C161: Ashwath Rau | D161: Senior Partner | E161: =IF(D161=(_xlfn.XLOOKUP(RISE_lawyers!$A161, 'Private Capital'!$A$2:$A$51,'Private Capital'!G$2:G$51)), TRUE, FALSE) -> TRUE | F161: Mumbai | G161: =IF(F161=(_xlfn.XLOOKUP(RISE_lawyers!$A161, 'Private Capital'!$A$2:$A$51,'Private Capital'!F$2:F$51)), TRUE, FALSE) -> TRUE | H161: AZB & Partners | I161: Ashwath Rau has the highest reputationÂ in India's private capital market, receiving the most client recommendations and peer mentions of any lawyer. His blue-chip client base includes KKR, Bain, Carlyle, BlackRock and PAG._x000D_ _x000D_ Clients commend his strategic thinking and ability to navigate complex legal and commercial problems with clarity. Working closely with firm managing partner Zia Mody, he plays a central role in shaping AZB's growth and strategic direction._x000D_ _x000D_ Clients describe his approach as deliberate, combining regulatory expertise with commercial judgment on consequential transactions. He brings technical mastery to deals involving intricate structures and high-stakes negotiations._x000D_ _x000D_ Ashwath's ranking reflects a practice built on institutional trust and market-leading deal flow. He is viewed as a senior figure whose judgment shapes outcomes on India's most significant private capital mandates.
A162: IND00060 | B162: Private Capital | C162: Bharat Anand | D162: Partner | E162: =IF(D162=(_xlfn.XLOOKUP(RISE_lawyers!$A162, 'Private Capital'!$A$2:$A$51,'Private Capital'!G$2:G$51)), TRUE, FALSE) -> TRUE | F162: Delhi | G162: =IF(F162=(_xlfn.XLOOKUP(RISE_lawyers!$A162, 'Private Capital'!$A$2:$A$51,'Private Capital'!F$2:F$51)), TRUE, FALSE) -> TRUE | H162: Khaitan & Co | I162: Bharat Anand places first in the market for practice sophistication, with top scores in technology, data-driven practice and pricing models. He employs AI for drafting and summarisation, uses bots to produce due diligence notes, and runs data analytics to support client work. His clients increasingly request these AI capabilities as adoption moves mainstream._x000D_ _x000D_ Bharat has good instruction scores for clients and deal volume. Clients include Lightspeed, Peak XV Partners andÂ ChrysCapital, and he has done significant work in the pharma and healthcare sector._x000D_ _x000D_ Clients gave strong scores for Bharatâ€™s strategy and leadership, important to sustaining the high-volume institutional relationships that define his practice.
A163: IND00573 | B163: Private Capital | C163: Darshika Kothari | D163: Senior Partner | E163: =IF(D163=(_xlfn.XLOOKUP(RISE_lawyers!$A163, 'Private Capital'!$A$2:$A$51,'Private Capital'!G$2:G$51)), TRUE, FALSE) -> TRUE | F163: Mumbai | G163: =IF(F163=(_xlfn.XLOOKUP(RISE_lawyers!$A163, 'Private Capital'!$A$2:$A$51,'Private Capital'!F$2:F$51)), TRUE, FALSE) -> TRUE | H163: AZB & Partners | I163: Darshika Kothari's client roster includes KKR, TA Associates, Fairfax and New Mountain Capital, and approximately 70% of her work is on cross-border transactions. _x000D_ _x000D_ At AZB & Partners, her practice model emphasises lean teams and operational efficiency. She champions technology adoption and has helped develop a proprietary database that tracks client negotiating positions across transactions, enabling her team to mine historical deal data._x000D_ _x000D_ Darshika's practice combines high-value execution with one of the most data-enabled practices in the market. She has a high media profile in the private capital field and received strong client experience scores across all indicators.
A164: IND00066 | B164: Private Capital | C164: Deepak Jodhani | D164: Partner | E164: =IF(D164=(_xlfn.XLOOKUP(RISE_lawyers!$A164, 'Private Capital'!$A$2:$A$51,'Private Capital'!G$2:G$51)), TRUE, FALSE) -> TRUE | F164: Mumbai | G164: =IF(F164=(_xlfn.XLOOKUP(RISE_lawyers!$A164, 'Private Capital'!$A$2:$A$51,'Private Capital'!F$2:F$51)), TRUE, FALSE) -> TRUE | H164: Khaitan & Co | I164: Deepak Jodhani receives high scores for service, commerciality, strategy and emotional intelligence. In the past 12 months, he has acted on complex, high-value transactions, including advising Blackstone on its $366mn acquisition of Kolkata's South City Mall, one of eastern India's largest private equity real estate deals._x000D_ _x000D_ Sophistication indicators reflect active use of AI-driven drafting, analytics and post-deal feedback data, distinguishing his practice from traditional models._x000D_ _x000D_ Clients value Deepak'sÂ technical capability on significant real estate transactions.
A165: IND00074 | B165: Private Capital | C165: Divaspathi Singh | D165: Partner | E165: =IF(D165=(_xlfn.XLOOKUP(RISE_lawyers!$A165, 'Private Capital'!$A$2:$A$51,'Private Capital'!G$2:G$51)), TRUE, FALSE) -> TRUE | F165: Mumbai | G165: =IF(F165=(_xlfn.XLOOKUP(RISE_lawyers!$A165, 'Private Capital'!$A$2:$A$51,'Private Capital'!F$2:F$51)), TRUE, FALSE) -> TRUE | H165: Khaitan & Co | I165: Divaspati Singh has built a strong market position in India-focused private capital fund formation, particularly across AIFs and GIFT City structures. His mandates include work for TPG, Edelweiss, IFC, Kotak and White Oak, reflecting trust from institutional clients who repeatedly engage him for multi-fund platforms. A standout matter is his role on Kedaara Capital's fourth fund, which closed at around $1.73bnÂ and ranks among the largest India-focused private equity funds raised by a domestic manager._x000D_ _x000D_ Strong points include his navigation of regulatory frameworks, his negotiation on investor terms and a commercial approach that prioritises clarity and deal execution. HeÂ uses firm-wide data, automation tools and flexible pricing models to provide predictable, market-aligned advice._x000D_ _x000D_ Divaspati's combination of complex fund mandates, recurring institutional clients, leading use of technology and data, and strong qualitative feedback places him in this ranking of top private capital lawyers in India.
A166: IND00724 | B166: Private Capital | C166: Ganesh Rao | D166: Partner | E166: =IF(D166=(_xlfn.XLOOKUP(RISE_lawyers!$A166, 'Private Capital'!$A$2:$A$51,'Private Capital'!G$2:G$51)), TRUE, FALSE) -> TRUE | F166: Mumbai | G166: =IF(F166=(_xlfn.XLOOKUP(RISE_lawyers!$A166, 'Private Capital'!$A$2:$A$51,'Private Capital'!F$2:F$51)), TRUE, FALSE) -> TRUE | H166: Trilegal | I166: Ganesh Rao is a private equity and private credit partner at Trilegal with a strong client base of leading global sponsors and firms active in the private credit space. His client list includes Ares, Blackstone, Edelweiss, Morgan Stanley, Apollo, Goldman Sachs, ICICI Venture and PAG._x000D_ _x000D_ His practice spans sponsor-led financings, private equity investments and structured credit, anchored by repeat work from international institutions deploying capital into India. Instruction metrics indicate both a high volume of deals and instruction on complex and high-value mandates._x000D_ _x000D_ The breadth of top tier institutional relationships and the consistency of Ganesh's portfolio point to a practitioner with growing influence across private equity and private credit transactions.
A167: IND02949 | B167: Private Capital | C167: Gautam Saha | D167: Joint Managing Partner | E167: =IF(D167=(_xlfn.XLOOKUP(RISE_lawyers!$A167, 'Private Capital'!$A$2:$A$51,'Private Capital'!G$2:G$51)), TRUE, FALSE) -> TRUE | F167: Delhi | G167: =IF(F167=(_xlfn.XLOOKUP(RISE_lawyers!$A167, 'Private Capital'!$A$2:$A$51,'Private Capital'!F$2:F$51)), TRUE, FALSE) -> TRUE | H167: TT&A | I167: Gautam Saha's Top 10 reputation ranking stems from exceptional peer recognition, comprehensive directory acknowledgement, and extensive media profile across India's private capital market. His joint managing partner role at TT&A Advocates positions him at the intersection of private equity, venture capital and private credit, where his strategic oversight combines with technical excellence._x000D_ _x000D_ His instruction volume demonstrates consistent mandates from premier institutional clients. While he has acted for many leading private capital investors over the years, in the 12-month period analysed, Gautam's client list was more limited.Â It includedÂ Setu AIF Trust, IFC and DFC. Gautam is known for the high-value, technically complex nature of his internationally-focused practice spanning M&A and structured financing._x000D_ _x000D_ Gautam's practice stands out for a strongÂ client relationship focus. His pragmatic negotiation skills, understanding of client objectives and strategic thinking distinguish his approach.
A168: IND01232 | B168: Private Capital | C168: Gunjan Shah | D168: Partner | E168: =IF(D168=(_xlfn.XLOOKUP(RISE_lawyers!$A168, 'Private Capital'!$A$2:$A$51,'Private Capital'!G$2:G$51)), TRUE, FALSE) -> TRUE | F168: Mumbai | G168: =IF(F168=(_xlfn.XLOOKUP(RISE_lawyers!$A168, 'Private Capital'!$A$2:$A$51,'Private Capital'!F$2:F$51)), TRUE, FALSE) -> TRUE | H168: Shardul Amarchand Mangaldas & Co. | I168: Gunjan Shahâ€™s acts for leading investors including ChrysCapital, TPG, Bain Capital Credit, Apollo Global Management, CVC Capital Partners, Think Investments andÂ Alphawave. Her work for ChrysCapital, one of India's largest domestic investors, demonstrates the trust placed in her by home-grown institutional capital._x000D_ _x000D_ Considered a senior and leading practitioner in the private equity space, Gunjan had a lower profile in 12 month period of the research than usual. She advises on both public and private deals, specialising in structured products that go beyond straight equity, including debt-like and semi-equity instruments. Her practice encompasses minority investments, buyouts and investments in stressed assets._x000D_ _x000D_ Gunjan's ability to innovate with new financial products positions her as a creative problem-solver for funds seeking sophisticated structuring. Crucially, she combinesÂ technical mastery of complex capital structures with knowledgeÂ of how to deploy these tools to achieve commercial objectives in India's dynamic private capital market.
... A193: IND00391 | B193: Private Capital | C193: Shishir Jose Vayttaden | D193: Partner | E193: =IF(D193=(_xlfn.XLOOKUP(RISE_lawyers!$A193, 'Private Capital'!$A$2:$A$51,'Private Capital'!G$2:G$51)), TRUE, FALSE) -> TRUE | F193: Mumbai | G193: =IF(F193=(_xlfn.XLOOKUP(RISE_lawyers!$A193, 'Private Capital'!$A$2:$A$51,'Private Capital'!F$2:F$51)), TRUE, FALSE) -> TRUE | H193: Khaitan & Co | I193: Shishir Jose Vayttaden is one of Khaitan & Co.â€™s leading private equity practitioners, having joined from Cyril Amarchand Mangaldas in 2024. His reputation is anchored in strong peer recognition, with fellow practitioners frequently citing his judgement and execution strength. His key client relationships include Blackstone, Warburg Pincus and Multiples, who value the continuity and quality of his counsel on major transactions._x000D_ _x000D_ Institutional investors commend his ability to manage complex, large-scale mandates with consistency and precision, reflected in a sophistication score in the top half of the market. Their sustained confidence in his technical execution and strategic judgement supports long-term relationships and reinforces his position as a trusted adviser within Indiaâ€™s private capital ecosystem.
A194: IND01585 | B194: Private Capital | C194: Shuva Mandal | D194: Founder & Managing Partner | E194: =IF(D194=(_xlfn.XLOOKUP(RISE_lawyers!$A194, 'Private Capital'!$A$2:$A$51,'Private Capital'!G$2:G$51)), TRUE, FALSE) -> TRUE | F194: Mumbai | G194: =IF(F194=(_xlfn.XLOOKUP(RISE_lawyers!$A194, 'Private Capital'!$A$2:$A$51,'Private Capital'!F$2:F$51)), TRUE, FALSE) -> TRUE | H194: Anagram Partners | I194: Shuva Mandalâ€™s instruction metrics are anchored in high-value mandates for prominent private equity investors such as CVC, Goldman Sachs and Valiant Capital. His client mix reflects continued engagement from both Indian and international funds, signalling trust in his judgment on significant deployment decisions. _x000D_ _x000D_ Shuva founded Anagram Partners in 2021, and working within a smaller firm and team, handled a lower total value and volume of work in our research over the past 12 months than peers at the largest five firms. _x000D_ _x000D_ What distinguishes him within this group is his depth in governance and longer-term strategic input on buyouts, supported by his experience as group general counsel at Tata and reinforced by longstanding institutional relationships across varied transaction types. _x000D_ _x000D_ Shuva was also an early mover in adopting AI. The firm has developed AI-tools and workflows to support their transactional work, positioning them alongside or ahead of larger law firms on this metric of practice sophistication. | J194: *Just describes himself as 'Partner'*
A195: IND00218 | B195: Private Capital | C195: Siddarth Shah | D195: Partner | E195: =IF(D195=(_xlfn.XLOOKUP(RISE_lawyers!$A195, 'Private Capital'!$A$2:$A$51,'Private Capital'!G$2:G$51)), TRUE, FALSE) -> TRUE | F195: Mumbai | G195: =IF(F195=(_xlfn.XLOOKUP(RISE_lawyers!$A195, 'Private Capital'!$A$2:$A$51,'Private Capital'!F$2:F$51)), TRUE, FALSE) -> TRUE | H195: Khaitan & Co | I195: Siddarth Shah operates across the full spectrum of private capital at Khaitan & Co - private equity, venture capital and private credit. His practice spans fund formation and deployment for institutional investors, including advising Kedaara Capital on one of Indiaâ€™s largest domestically-sponsored funds -Â its $1.73bn fourth fund in GIFT City._x000D_ _x000D_ Client relationships span premier international and domestic firms, including Brookfield, ChrysCapital and Kotak Alternatives, alongside sovereign wealth funds and government investors. _x000D_ _x000D_ His top 25 reputation draws on particularly high directory and media profile scores._x000D_ _x000D_ Siddarth also receives a high sophistication of practice score, particularly in the data-driven practice metric. He receives a top score in this area for deployment of proprietary deal analytics, leveraging Khaitan's accumulated transaction data to enhance efficiency and provide clients with market trend intelligence.
A196: IND03027 | B196: Private Capital | C196: Siddhart Srivastava | D196: Partner | E196: =IF(D196=(_xlfn.XLOOKUP(RISE_lawyers!$A196, 'Private Capital'!$A$2:$A$51,'Private Capital'!G$2:G$51)), TRUE, FALSE) -> TRUE | F196: Delhi | G196: =IF(F196=(_xlfn.XLOOKUP(RISE_lawyers!$A196, 'Private Capital'!$A$2:$A$51,'Private Capital'!F$2:F$51)), TRUE, FALSE) -> TRUE | H196: Khaitan & Co | I196: Siddhart Srivastava's instruction metrics demonstrate steady deal activity in private credit at Khaitan & Co., built on relationships with institutional investors including Oaktree, Cerberus and Baring. _x000D_ _x000D_ Siddhart receives the equal second highest score for sophistication of practice. He has strong technology skills and is also keen to share his knowhow. Siddharth presents key deal featuresÂ internally after completed transactions, using AI to capture and shareÂ learning. His focus on building institutional memory through technology positions him well as private credit work continues to expand in India._x000D_ _x000D_ Though he scores highly on multiple experience indicators, theÂ smaller overall scoreÂ reflects theÂ low number of client ratings received during the research period.
A197: IND02081 | B197: Private Capital | C197: Siddharth Mody | D197: Partner | E197: =IF(D197=(_xlfn.XLOOKUP(RISE_lawyers!$A197, 'Private Capital'!$A$2:$A$51,'Private Capital'!G$2:G$51)), TRUE, FALSE) -> TRUE | F197: Mumbai | G197: =IF(F197=(_xlfn.XLOOKUP(RISE_lawyers!$A197, 'Private Capital'!$A$2:$A$51,'Private Capital'!F$2:F$51)), TRUE, FALSE) -> TRUE | H197: J. Sagar Associates | I197: Siddharth Mody is a private equity and venture capital partner at JSA, advising sponsors and asset managers across growth- and control-focused transactions. His client base includes ChrysCapital, General Atlantic, 360 ONE and other leading domestic and global investors active in Indiaâ€™s mid-market._x000D_ _x000D_ His work spans minority and growth investments, platform build-outs and portfolio support, with activity concentrated in sectors attracting sustained sponsor interest. A strong media profiles contributes to Siddharthâ€™s reputation score.
A198: IND02937 | B198: Private Capital | C198: Sonali Mahapatra | D198: Partner | E198: =IF(D198=(_xlfn.XLOOKUP(RISE_lawyers!$A198, 'Private Capital'!$A$2:$A$51,'Private Capital'!G$2:G$51)), TRUE, FALSE) -> TRUE | F198: Mumbai | G198: =IF(F198=(_xlfn.XLOOKUP(RISE_lawyers!$A198, 'Private Capital'!$A$2:$A$51,'Private Capital'!F$2:F$51)), TRUE, FALSE) -> TRUE | H198: TT&A | I198: Sonali Mahapatra has a private credit practice at TT&A, focusing on alternative credit structures in India's expanding credit market. Sonaliâ€™s reputation as one Indiaâ€™s leading private credit practitioners is reflected in her high number of peer mentions and strong directory presence._x000D_ _x000D_ Her instruction base includes leading private capital firms such as Ares Management, Brookfield, TPG, Farallon Capital, BlackRock, Davidson Kempner, PAG, Kotak, Hillhouse and Allianz. This client portfolio gives Sonali a top ten score for clients. Near-perfect client ratings across all evaluation metrics underscore both service excellence and technical competence._x000D_ _x000D_ At TT&A, Sonali leads a private credit practice that handles structured transactions involving multiple funding entities and layered capital arrangements. Clients engage Sonali for matters involving both technical structuring and regulatory compliance considerations.
A199: IND00596 | B199: Private Capital | C199: Srinath Dasari | D199: Senior Partner | E199: =IF(D199=(_xlfn.XLOOKUP(RISE_lawyers!$A199, 'Private Capital'!$A$2:$A$51,'Private Capital'!G$2:G$51)), TRUE, FALSE) -> TRUE | F199: Bengaluru | G199: =IF(F199=(_xlfn.XLOOKUP(RISE_lawyers!$A199, 'Private Capital'!$A$2:$A$51,'Private Capital'!F$2:F$51)), TRUE, FALSE) -> TRUE | H199: AZB & Partners | I199: Srinath Dasariâ€™s practice at AZB & Partners covers both private equity and venture capital clients on work at different phases of the corporate life- cycle. He ranks in the Top 25 for reputation and for the sophistication of his practice. _x000D_ _x000D_ Srinathâ€™s deals include repeat mandates for Tiger Global Management and Vitruvian Partners over the research period. _x000D_ _x000D_ The AZB & Partners platform supports cross-border co-ordination and process discipline, enabling execution on compressed timelines._x000D_ _x000D_ Srinath's approach prioritises execution certainty and documentation-led risk management, with clients valuing his ability to maintain clarity under pressure. He receives strong client reviews, but from a relatively small number of clients over the research period.
A200: IND00600 | B200: Private Capital | C200: Vaidhyanadhan Iyer | D200: Senior Partner | E200: =IF(D200=(_xlfn.XLOOKUP(RISE_lawyers!$A200, 'Private Capital'!$A$2:$A$51,'Private Capital'!G$2:G$51)), TRUE, FALSE) -> TRUE | F200: Mumbai | G200: =IF(F200=(_xlfn.XLOOKUP(RISE_lawyers!$A200, 'Private Capital'!$A$2:$A$51,'Private Capital'!F$2:F$51)), TRUE, FALSE) -> TRUE | H200: AZB & Partners | I200: A senior partner at AZB & Partners, Vaidhyanadhan Iyer ranks second in the market for aggregate deal value over the RISE research period. Coupled with a high volume of transactions, Vaidhyanadhan has a reputation within the firm for handling more private equity deals than any other lawyer. His client roster includes Warburg Pincus, Advent, TPG and Footpath, with Warburg relying on him as a trusted adviser across its most significant mandates._x000D_ _x000D_ Beyond execution, Vaidhyanadhan integrates data-driven and technology-enhanced approaches into his practice. He personallyÂ championed AZBâ€™s adoption of Harvey and built a private-equity-specific data vault containing granular deal intelligence, which he uses to strengthen analysis and accelerate decision-making in live transactions. His tech and data savvy has placed him in the Top 10 private capital lawyers in India.Â
A201: IND02118 | B201: Private Capital | C201: Vikram Raghani | D201: Partner | E201: =IF(D201=(_xlfn.XLOOKUP(RISE_lawyers!$A201, 'Private Capital'!$A$2:$A$51,'Private Capital'!G$2:G$51)), TRUE, FALSE) -> TRUE | F201: Mumbai | G201: =IF(F201=(_xlfn.XLOOKUP(RISE_lawyers!$A201, 'Private Capital'!$A$2:$A$51,'Private Capital'!F$2:F$51)), TRUE, FALSE) -> TRUE | H201: J. Sagar Associates | I201: Vikram Raghani is one of JSA Advocates & Solicitorsâ€™ leading private equity specialists, recognised across the market for his focused practice and trusted by major institutional investors. He maintains longstanding relationships with EQT and Temasek, who consistently return to him for high-value and strategically complex transactions. Over the past year, he has been busiest with financial services and consumer mandates, with manufacturing and real estate forming the remainder of his deal flow._x000D_ _x000D_ In a market where many peers divide their time between M&A and private equity, Vikram stands out as one of Indiaâ€™s most traditional, pure private equity lawyers. His inclusion in the top 10 of Indiaâ€™s Private Capital RISE Lawyers underscores the respect he commands among senior peers and reflects his reputation as a â€œpractical dealmakerâ€ known for timely, effective execution.
A202: IND00261 | B202: Private Capital | C202: Vivek Mamani | D202: Partner | E202: =IF(D202=(_xlfn.XLOOKUP(RISE_lawyers!$A202, 'Private Capital'!$A$2:$A$51,'Private Capital'!G$2:G$51)), TRUE, FALSE) -> TRUE | F202: Mumbai | G202: =IF(F202=(_xlfn.XLOOKUP(RISE_lawyers!$A202, 'Private Capital'!$A$2:$A$51,'Private Capital'!F$2:F$51)), TRUE, FALSE) -> TRUE | H202: Khaitan & Co | I202: Vivek Mimani is a partner at Khaitan & Co. with a practice concentrated on private equity and venture capital fund formation. He advises managers across early-stage, growth and pre-IPO strategies, with recent mandates for Stellaris Ventures, Trust Capital, Rukam Capital and Axis AMC._x000D_ _x000D_ His work spans structuring India-focused AIFs, establishing investment platforms and guiding clients through SEBI approvals and regulatory requirements tied to PE and VC fund launches._x000D_ _x000D_ Vivek receives the third highest sophistication of practice score in the market. He incorporates technology into fund-formation workflows, using automated tools to streamline documentation and regulatory processes, supporting efficient launch cycles for PE and VC managers operating in a fast-developing market.
A203: IND01707 | B203: Private Capital | C203: Winnie Sherkhar | D203: Partner | E203: =IF(D203=(_xlfn.XLOOKUP(RISE_lawyers!$A203, 'Private Capital'!$A$2:$A$51,'Private Capital'!G$2:G$51)), TRUE, FALSE) -> TRUE | F203: Bengaluru | G203: =IF(F203=(_xlfn.XLOOKUP(RISE_lawyers!$A203, 'Private Capital'!$A$2:$A$51,'Private Capital'!F$2:F$51)), TRUE, FALSE) -> TRUE | H203: IndusLaw | I203: Winnie Shekhar is a venture capital and private equity practitioner at CMS IndusLaw, whose broad sectoral knowhow includes expertise in flip and flip-back transactions across theÂ technology, healthcare and defence industries._x000D_ _x000D_ Winnie was exceptionally active during the research period, with the top deal volume score driven by repeat clients including General Catalyst, Elevation Capital, Nexus Venture and LightRock on small-to-medium-ticket transactions._x000D_ _x000D_ With a focus on venture capital work, her profile amongst peers working across the private capital space was lower. However, she is highly rated in directories for her VC practice, and receives excellent client ratings from a large number of clients. Her experience score puts her in the top 10 in the market.
A204: IND00813 | B204: Private Capital | C204: Yogesh Singh | D204: Partner | E204: =IF(D204=(_xlfn.XLOOKUP(RISE_lawyers!$A204, 'Private Capital'!$A$2:$A$51,'Private Capital'!G$2:G$51)), TRUE, FALSE) -> TRUE | F204: Gurugram | G204: =IF(F204=(_xlfn.XLOOKUP(RISE_lawyers!$A204, 'Private Capital'!$A$2:$A$51,'Private Capital'!F$2:F$51)), TRUE, FALSE) -> TRUE | H204: Trilegal | I204: Yogesh Singh is a private equity and private credit partner at Trilegal. The firm has invested heavily in technology and data systems, building a database of more than 500 deals since markets resurged after Covid.Â Yogesh integrates these tools into his practice to produce trend reports, identify key findings and run detailed deal-trench analyses for clients._x000D_ _x000D_ Recent mandates include work for Brookfield Asset Management and Goldman Sachs, reflecting engagement from leading institutional investors. Yogesh receives strong instructions scores across all metrics, with a good client base and high deal values and volumes over the research period. _x000D_ _x000D_ Yogesh places in the top 10 for client experience. Clients rated him highly across all indicators and he received a large number of client reviews.

Sheet All
A1: Resight ID | B1: New Resight ID | C1: Ranking | D1: @Image path | E1: Name | F1: Bio | G1: Location | H1: Position | I1: Organisation | J1: Total | K1: Badge | L1: Rank | M1: Reputation score | N1: Reputation score Median | O1: Reputation rank badge | P1: R Peers | Q1: R Peers Median | R1: R Directories | S1: R Directories Median | T1: R News media | U1: R News media Median | V1: R Social media | W1: R Social media Median | X1: Instructions score | Y1: Instructions score Median | Z1: Instructions rank badge | AA1: I Volume | AB1: I Volume Median | AC1: I Value | AD1: I Value Median | AE1: I Clients | AF1: I Clients Median | AG1: I Complexity | AH1: I Complexity Median | AI1: Sophistication score | AJ1: Sophistication score Median | AK1: Sophistication rank badge | AL1: S Tech and data | AM1: S Tech and data Median | AN1: S Pricing | AO1: S Pricing Median | AP1: S Talent development | AQ1: S Talent development Median | AR1: Experience score | AS1: Experience score Median | AT1: Experience rank badge | AU1: E Service | AV1: E Service Median | AW1: E Expertise | AX1: E Expertise Median | AY1: E Commerciality | AZ1: E Commerciality Median | BA1: E Communication | BB1: E Communication Median | BC1: E EQ | BD1: E EQ Median | BE1: E Strategy | BF1: E Strategy Median | BG1: E Network | BH1: E Network Median | BI1: E Leadership | BJ1: E Leadership Median
A2: IND05097 | B2: IND05097 | C2: Cyber | D2: Aadya-Misra.webp | E2: Aadya Misra | F2: Aadya Misra receives an excellent RISE client experience score, with a number of client recommendations and particularly high ratings for service, commerciality and EQ (emotional quotient and ability to empathise and walk in the client's shoes). Misra is also included in the list on the basis of a strong RISE instruction score. Misra has a purely data protection and cyber focused practice, one of the few in this cohort that does not sit within a broader TMT or corporate department. Her clients include domestic Indian companies expanding into the EU, Southeast Asia, the Middle East, and the US, where cross-border data transfer and localisation requirements drive most of the complexity. Her work includes data governance structures, cybersecurity, and data architecture compliance across Indian and foreign jurisdictions. Misra also makes use of a client-facing data hub offering compliance tools and an interactive comparative map of data and cyber laws, reflected in her sophistication of practice RISE score. Her EnRoute programme offers 100 hours of free legal service to small companies and also provides a structured training ground for junior lawyers building advisory confidence under supervision. | G2: Bengaluru | H2: Counsel | I2: Spice Route Legal | J2: 5.3 | L2: 16 | M2: 3.3 | N2: 3.75 | P2: 0 | Q2: 0 | R2: 6 | S2: 7.1 | T2: 8.5 | U2: 8 | V2: 8.3 | W2: 8.3 | X2: 7.1 | Y2: 8 | AA2: 7.8 | AB2: 7.6 | AC2: - | AD2: 0 | AE2: 4.8 | AF2: 8.8 | AG2: 8 | AH2: 7.5 | AI2: 5.7 | AJ2: 6.7 | AL2: 3.3 | AM2: 6.7 | AN2: 6 | AO2: 7 | AP2: 8 | AQ2: 6 | AR2: 9.8 | AS2: 8.5 | AT2: Ranked 1st | AU2: 10 | AV2: 10 | AW2: 9.6 | AX2: 10 | AY2: 10 | AZ2: 10 | BA2: 9.6 | BB2: 10 | BC2: 10 | BD2: 10 | BE2: 9.6 | BF2: 10 | BG2: 9.6 | BH2: 10 | BI2: 9.6 | BJ2: 10
A3: IND06252 | B3: IND06252 | C3: Capital Markets - Equity | D3: Photos/Aashima-Johur.png | E3: Aashima Johur | F3: Aashima Johur at Cyril Amarchand Mangaldas has built her practice around new-age, technology-focused, asset-light companies, working almost exclusively as issuer counsel, a positioning that gives her deeper insight into non-traditional capital structures, employee incentive schemes, and promoter arrangements than a bank-side practice typically produces. Instruction scores are her strongest RISE metric, but she also scores well on some sophistication sub-indicators such as pricing flexibility, and she switches between fixed fees and hourly rates in ways appropriate to client and matter. For pre-IPO advisory work—where the firm entrenches itself with potential issuers up to a year before the formal process begins to assess IPO readiness and identify areas requiring "cleaning up"—the firm tends to work on an hourly basis. Johur also scores strongly on the complexity of her mandates in line with her focus on new age companies. Her matters have received a lot of media attention. For example, the Lenskart IPO generated significant social media discussion about valuation and promoter incentives, requiring the team to address public perception and justify the commercial arrangements. | G3: Delhi | H3: Partner | I3: Cyril Amarchand Mangaldas | J3: 5.7 | L3: 24 | M3: 2.4 | N3: 4.9 | P3: 0 | Q3: 3.2 | R3: 2.9 | S3: 6 | T3: 6.7 | U3: 6.8 | V3: 8.4 | W3: 8.5 | X3: 8.1 | Y3: 8.2 | AA3: 7.4 | AB3: 7.3 | AC3: 8.6 | AD3: 8.6 | AE3: 6.3 | AF3: 9.4 | AG3: 8.8 | AH3: 8.2 | AI3: 7.7 | AJ3: 7.1 | AK3: Top 10 | AL3: 7.3 | AM3: 7.3 | AN3: 8 | AO3: 7 | AP3: 8 | AQ3: 8 | AR3: 8.5 | AS3: 8.5 | AU3: 10 | AV3: 10 | AW3: 10 | AX3: 10 | AY3: 10 | AZ3: 10 | BA3: 10 | BB3: 10 | BC3: 10 | BD3: 10 | BE3: 10 | BF3: 10 | BG3: 10 | BH3: 10 | BI3: 10 | BJ3: 10
A4: IND00004 | B4: IND00004 | C4: Capital Markets - Equity | D4: Photos/Ayush Mohata - ECM.png | E4: Aayush Mohata | F4: Aayush Mohata combines strong AI and sophistication scores with a deliberate focus on quality over quantity, building a practice around fewer and larger mandates rather than volume. He uses the firm's KAI platform across a wide range of tasks including preparing diligence checklists, benchmarking disclosures against recent regulatory precedents, and identifying consent triggers in financing documents. Mohata also invests heavily in structured training, running tailored, annual programmes for junior lawyers and bespoke sessions for new joiners. One of his most prominent recent matters is Knowledge Realty Trust’s IPO, India's largest REIT and Asia's second largest, sponsored by Blackstone alongside Sattva Developers. | G4: Mumbai | H4: Partner | I4: Khaitan & Co | J4: 4.2 | L4: 39 | M4: 2.4 | N4: 4.9 | P4: 0 | Q4: 3.2 | R4: 2.9 | S4: 6 | T4: 6.2 | U4: 6.8 | V4: 9 | W4: 8.5 | X4: 4 | Y4: 8.2 | AA4: 6.7 | AB4: 7.3 | AC4: 0 | AD4: 8.6 | AE4: 4.7 | AF4: 9.4 | AG4: 6.5 | AH4: 8.2 | AI4: 8.3 | AJ4: 7.1 | AK4: Top 5 | AL4: 8.7 | AM4: 7.3 | AN4: 8 | AO4: 7 | AP4: 8 | AQ4: 8 | AR4: 8.3 | AS4: 8.5 | AU4: 10 | AV4: 10 | AW4: 10 | AX4: 10 | AY4: 10 | AZ4: 10 | BA4: 10 | BB4: 10 | BC4: 10 | BD4: 10 | BE4: 8 | BF4: 10 | BG4: 10 | BH4: 10 | BI4: 10 | BJ4: 10
A5: IND01474 | B5: IND01474 | C5: Competition | D5: Photos/Mr-Abhay-Joshi.jpg | E5: Abhay Joshi | F5: Abhay Joshi’s strongest RISE metric is Instructions, driven by the exceptional complexity of mandates he handles for a high-quality client roster. His portfolio includes IREL India, Bridgestone India, SKF India, Ecozen Solutions, Corteva Agriscience, and United Breweries. His practice is defined by these layered enforcement matters rather than routine market-share analysis, reflecting a deep institutional understanding of Indian competition law. Joshi differentiates himself through his "quiet achiever" status; while his Reputation score is more minimal, his work on sophisticated regulatory intersections is notable. He recently defended IREL in a monopoly abuse case, arguing that strategic policy context justifies market position. His work for United Breweries involved navigating a highly regulated industry to address complex business issues regarding the sharing of commercially sensitive pricing and production data. Having transitioned from a background in M&A and private equity, Joshi also leverages a growing strand of data privacy work. He believes this forward-facing approach, treating privacy as a non-price parameter in competition analysis, is essential for modern market power mandates. | G5: Delhi | H5: Partner | I5: Economic Laws Practice | J5: 5.2 | L5: 38 | M5: 2.8 | N5: 5.6 | P5: 0 | Q5: 4.1 | R5: 7.1 | S5: 7.5 | T5: 3.6 | U5: 5.9 | V5: 8.4 | W5: 8.3 | X5: 7.5 | Y5: 8.4 | AA5: 4.8 | AB5: 7.4 | AC5: - | AD5: 0 | AE5: 8.2 | AF5: 9.5 | AG5: 8.5 | AH5: 8.5 | AI5: 5.5 | AJ5: 6.7 | AL5: 5.3 | AM5: 6.7 | AN5: 5 | AO5: 7 | AP5: 6 | AQ5: 7.5 | AR5: - | AS5: 8.5 | AU5: - | AV5: 10 | AW5: - | AX5: 10 | AY5: - | AZ5: 10 | BA5: - | BB5: 10 | BC5: - | BD5: 10 | BE5: - | BF5: 10 | BG5: - | BH5: 10 | BI5: - | BJ5: 10
A6: IND00005 | B6: IND00005 | C6: Capital Markets - Equity | D6: Photos/Abhimanyu-Bhattacharya.png | E6: Abhimanyu Bhattacharya | F6: Abhimanyu Bhattacharya works across the full public markets ecosystem, advising financial sponsors on IPO exits and issuers on listings, with clients including Apollo Global, Blackstone, TPG, and SoftBank. His highest RISE score is for the reputation indicator, where he draws solid peer recommendations, and a visible presence legal directory presence. His mandates consistently involve sponsor-heavy transactions with large, complex cap tables. Meesho's IPO is a good example: a reverse-flipped issuer with a novel business model where the core challenge was aligning numerous financial sponsors and renegotiating pre-IPO documentation to get the transaction ready for market. | G6: Mumbai | H6: Partner | I6: Khaitan & Co | J6: 7.9 | K6: Top 10 | L6: 8 | M6: 8 | N6: 4.9 | O6: Top 10 | P6: 7.7 | Q6: 3.2 | R6: 9.3 | S6: 6 | T6: 7 | U6: 6.8 | V6: 8.5 | W6: 8.5 | X6: 7.9 | Y6: 8.2 | AA6: 6.1 | AB6: 7.3 | AC6: 8.5 | AD6: 8.6 | AE6: 6.5 | AF6: 9.4 | AG6: 8.5 | AH6: 8.2 | AI6: 7.5 | AJ6: 7.1 | AK6: Top 10 | AL6: 7.3 | AM6: 7.3 | AN6: 7 | AO6: 7 | AP6: 8 | AQ6: 8 | AR6: - | AS6: 8.5 | AU6: - | AV6: 10 | AW6: - | AX6: 10 | AY6: - | AZ6: 10 | BA6: - | BB6: 10 | BC6: - | BD6: 10 | BE6: - | BF6: 10 | BG6: - | BH6: 10 | BI6: - | BJ6: 10
A7: IND03708 | B7: IND03708 | C7: Capital Markets - Equity | D7: Photos/Abhinav Maver - ECM.png | E7: Abhinav Maker | F7: Abhinav Maker's instruction and sophistication scores at Trilegal are underpinned by a practice that treats regulatory engagement as a client service rather than a compliance obligation. Maker works directly with SEBI on consultation papers and uses client interviews to shape how his team tracks and communicates regulatory change. AI and data usage is a strong sub-indicator. Maker also prioritises training for his team, which includes mandatory biweekly sessions and knowledge sharing to keep the team current. He has worked on some novel transactions such as the Bluestone IPO, which required creating new structural mechanisms to meet shareholding rules that a series of funding rounds had made impossible to satisfy in the conventional way, and Dam Capital that became India's first investment bank to go public. He works in the BFSI, manufacturing, infrastructure, and new-age technology sectors. | G7: Delhi | H7: Partner | I7: Trilegal | J7: 5.7 | L7: 27 | M7: 2.3 | N7: 4.9 | P7: 0 | Q7: 3.2 | R7: 2.9 | S7: 6 | T7: 6 | U7: 6.8 | V7: 8.4 | W7: 8.5 | X7: 8.2 | Y7: 8.2 | AA7: 7.8 | AB7: 7.3 | AC7: 8 | AD7: 8.6 | AE7: 8.9 | AF7: 9.4 | AG7: 8.2 | AH7: 8.2 | AI7: 7.4 | AJ7: 7.1 | AL7: 8 | AM7: 7.3 | AN7: 7 | AO7: 7 | AP7: - | AQ7: 8 | AR7: - | AS7: 8.5 | AU7: - | AV7: 10 | AW7: - | AX7: 10 | AY7: - | AZ7: 10 | BA7: - | BB7: 10 | BC7: - | BD7: 10 | BE7: - | BF7: 10 | BG7: - | BH7: 10 | BI7: - | BJ7: 10
A8: IND00406 | B8: IND00406 | C8: Capital Markets - Equity | D8: Photos/Abhiroop-Amitava-Datta- ECM.png | E8: Abhiroop Datta | F8: Abhiroop Datta at Shardul Amarchand Mangaldas & Co scores most strongly on RISE sophistication metrics, with technology usage and talent development the standout sub-indicators. He connects Outlook to Harvey to pull and summarise all correspondence relating to a transaction, replacing manual inbox management, and stores transaction data in structured archives to run analyses without risk. His practice spans large regulated-sector IPOs and technology listings, including matters using SEBI's confidential filing route, with experience across a wide range of promoter profiles and investor types from family-led Indian businesses to international corporate and financial sponsors. He regularly advises on public regulatory compliance issues where multiple regulators or large syndicates are involved. A personal background spanning three countries and ten cities has given him an ability to engage comfortably across socio-economic and cultural contexts, from traditional Indian promoters to sophisticated international clients. | G8: Delhi | H8: Partner | I8: Shardul Amarchand Mangaldas & Co | J8: 5.3 | L8: 36 | M8: 2.4 | N8: 4.9 | P8: 0 | Q8: 3.2 | R8: 2.9 | S8: 6 | T8: 7 | U8: 6.8 | V8: 8.1 | W8: 8.5 | X8: 7 | Y8: 8.2 | AA8: 5.1 | AB8: 7.3 | AC8: 8.1 | AD8: 8.6 | AE8: 7.1 | AF8: 9.4 | AG8: 7 | AH8: 8.2 | AI8: 7.6 | AJ8: 7.1 | AK8: Top 10 | AL8: 8 | AM8: 7.3 | AN8: 6 | AO8: 7 | AP8: 8 | AQ8: 8 | AR8: - | AS8: 8.5 | AU8: - | AV8: 10 | AW8: - | AX8: 10 | AY8: - | AZ8: 10 | BA8: - | BB8: 10 | BC8: - | BD8: 10 | BE8: - | BF8: 10 | BG8: - | BH8: 10 | BI8: - | BJ8: 10
A9: IND07656 | B9: IND08613 | C9: Competition | D9: Photos/abir-roy-neww.png | E9: Abir Roy | F9: Abir Roy at Sarvada Legal occupies an unusual position in the Indian competition market: an enforcement-led practice running approximately 80% contentious work, with a distinct concentration on the complainant side in big tech platform cases at a time when most comparable complexity sits within larger full-service firms. Sophistication and Experience are also rated highly, with technology and value the standout sub-indicators within each. Abir's work on Google, Apple and app ecosystem matters involves technical arguments around platform economics, data flows and jurisdictional overlap with data protection, with data accumulation treated as a source of dominance rather than a separate regulatory question. A notable feature is his representation of app developer communities acting collectively against dominant platforms, requiring coordination of multi-party complainant strategies across long-running, multi-forum disputes. He argues his own matters and maintains full file ownership throughout, a model that suits the litigation-control and forum-strategy dimension of enforcement work but operates from a smaller platform than the full-service practices handling comparable complexity. | G9: Delhi | H9: Co-founder & Partner | I9: Sarvada Legal | J9: 6.1 | L9: 28 | M9: 5.3 | N9: 5.6 | P9: 4.1 | Q9: 4.1 | R9: 7.5 | S9: 7.5 | T9: 4.2 | U9: 5.9 | V9: 9.2 | W9: 8.3 | X9: 6.5 | Y9: 8.4 | AA9: 10 | AB9: 7.4 | AC9: - | AD9: 0 | AE9: 0 | AF9: 9.5 | AG9: 9 | AH9: 8.5 | AI9: 6.6 | AJ9: 6.7 | AL9: 6 | AM9: 6.7 | AN9: 7 | AO9: 7 | AP9: 7 | AQ9: 7.5 | AR9: - | AS9: 8.5 | AU9: - | AV9: 10 | AW9: - | AX9: 10 | AY9: - | AZ9: 10 | BA9: - | BB9: 10 | BC9: - | BD9: 10 | BE9: - | BF9: 10 | BG9: - | BH9: 10 | BI9: - | BJ9: 10
A10: IND00016 | B10: IND00016 | C10: Capital Markets - Equity | D10: Photos/Aditya Cheriyan.png | E10: Aditya George Cheriyan | F10: Aditya George Cheriyan's is a modern-day of practitioner. His highest RISE scores come under 'Sophistication' of practice, essentially in the business of law. His role in developing his team is his standout sub-indicator. His associate training covers legal expertise, financial literacy, negotiation, and client communication, Associates are assessed regularly and developed through workshops and partner-led mentoring. Cheriyan teaches externally at Gujarat National Law University, which doubles as a talent pipeline and has contributed to less attrition in his team compared to peers. Clients include Travel Food Services, Sai Life Sciences, and Meesho, each involving novel equity arrangements, regulatory challenges, or cross-border structuring. His team systematically tracks what is market across transactions even where the firm is not instructed. | G10: Mumbai | H10: Partner | I10: Khaitan & Co | J10: 7.1 | L10: 14 | M10: 5.9 | N10: 4.9 | P10: 6.2 | Q10: 3.2 | R10: 2.9 | S10: 6 | T10: 7.6 | U10: 6.8 | V10: 8.3 | W10: 8.5 | X10: 7.5 | Y10: 8.2 | AA10: 6.7 | AB10: 7.3 | AC10: 8.2 | AD10: 8.6 | AE10: 6.8 | AF10: 9.4 | AG10: 7.8 | AH10: 8.2 | AI10: 8.6 | AJ10: 7.1 | AK10: Ranked 2nd | AL10: 8 | AM10: 7.3 | AN10: 7 | AO10: 7 | AP10: 10 | AQ10: 8 | AR10: 7.8 | AS10: 8.5 | AU10: 10 | AV10: 10 | AW10: 10 | AX10: 10 | AY10: 8 | AZ10: 10 | BA10: 10 | BB10: 10 | BC10: 6 | BD10: 10 | BE10: 8 | BF10: 10 | BG10: 10 | BH10: 10 | BI10: 10 | BJ10: 10
A11: IND00020 | B11: IND00020 | C11: Arbitration | D11: Photos/Ajay Bhargava_0.png | E11: Ajay Bhargava | F11: Ajay Bhargava runs a high-volume practice for Indian conglomerates, multinationals, and government bodies, with instructions from Aditya Birla Group, Adani Group, L&T, Siemens, Hyundai, Panacea and INOX. Complexity is among his strongest RISE indicators, with matters regularly involving multiple jurisdictions, public sector counterparties, and points of law with no settled precedent. A standout recent matter is Antrix Corporation, the first case in India to establish a doctrine of fraud in arbitration, with enforcement proceedings running in parallel across the Netherlands, Germany, France, and the US. His RISE sophistication score is anchored in talent development, working directly on matters alongside junior lawyers and having mentored around 15 lawyers to partnership over his career. | G11: Delhi | H11: Partner | I11: Khaitan & Co | J11: 6.8 | K11: Top 10 | L11: 10 | M11: 5.1 | N11: 3.6 | P11: 3.1 | Q11: 1 | R11: 7.5 | S11: 7.1 | T11: 6.4 | U11: 6.3 | V11: 9.8 | W11: 8.9 | X11: 8.3 | Y11: 7.8 | Z11: Top 10 | AA11: 9.5 | AB11: 7.6 | AC11: 7.6 | AD11: 7.5 | AE11: 7.4 | AF11: 7.4 | AG11: 8.7 | AH11: 8.7 | AI11: 7.2 | AJ11: 7.1 | AL11: 6 | AM11: 6.7 | AN11: 6 | AO11: 6 | AP11: 9 | AQ11: 7.5 | AR11: - | AS11: 8.3 | AU11: - | AV11: 10 | AW11: - | AX11: 10 | AY11: - | AZ11: 10 | BA11: - | BB11: 10 | BC11: - | BD11: 10 | BE11: - | BF11: 10 | BG11: - | BH11: 10 | BI11: - | BJ11: 10
A12: IND02646 | B12: IND02646 | C12: International Trade | D12: Photos/Ajinkya Gunjan Mishra.jpg | E12: Ajinkya Gunjan Mishra | F12: Ajinkya Gunjan Mishra carries some of the highest news and social media scores in this cohort, writing throughout 2025 on topics including the effects of US tariffs and opportunities for India's defence sector. His instruction record in the same year includes a rare disputed benefits case under the India-Japan CEPA, one of India's most active trade corridors in Asia-Pacific. Appearances for Mishra relating to trade remedies are largely concentrated in Indian forums across all levels, including the Supreme Court, primarily for multinationals, whom he also acts for on an advisory basis. An MBA from the Indian Institute of Foreign Trade, taken thirteen years ago when that combination was uncommon for a mid-career trade lawyer, signals a commercial orientation that has shaped how he has approached mandates since. | G12: Delhi | H12: Partner | I12: S&R Associates | J12: 5.3 | L12: 15 | M12: 2.4 | N12: 3.35 | P12: 0 | Q12: 0 | R12: 0 | S12: 7.1 | T12: 9.4 | U12: 7.1 | V12: 10 | W12: 8.9 | X12: 7.6 | Y12: 8.6 | AA12: 8.6 | AB12: 8.6 | AC12: - | AD12: 0 | AE12: 8.3 | AF12: 8.9 | AG12: 7 | AH12: 8.7 | AI12: 6.5 | AJ12: 6.4 | AK12: Top 10 | AL12: 6.7 | AM12: 5.3 | AN12: 7 | AO12: 7 | AP12: 6 | AQ12: 7.5 | AR12: 8.5 | AS12: 8.3 | AT12: Top 10 | AU12: 10 | AV12: 10 | AW12: 10 | AX12: 10 | AY12: 10 | AZ12: 10 | BA12: 10 | BB12: 10 | BC12: 10 | BD12: 10 | BE12: 10 | BF12: 10 | BG12: 10 | BH12: 10 | BI12: 10 | BJ12: 10
A13: IND02656 | B13: IND02656 | C13: Competition | D13: Photos/Akshat-Kulshrestha-GS.jpg | E13: Akshat Kulshrestha | F13: Akshat Kulshrestha at S&R Associates scores most strongly on RISE instruction metrics, driven by technically demanding merger control work and growing enforcement exposure rather than filing volume alone. His Client base is the standout sub-indicator, spanning infrastructure, private equity, and logistics, alongside cartel defence and High Court litigation for a top global express courier company. RISE sophistication scores are the second strongest signal. AI usage is notable, with the team building a competition-specific repository of CCI precedents segmented by conduct type, penalty range, and market definition using Lucio. | G13: Delhi | H13: Partner | I13: S&R Associates | J13: 5.1 | L13: 40 | M13: 2.3 | N13: 5.6 | P13: 0 | Q13: 4.1 | R13: 5.8 | S13: 7.5 | T13: 2.6 | U13: 5.9 | V13: 7.5 | W13: 8.3 | X13: 7.2 | Y13: 8.4 | AA13: 5.3 | AB13: 7.4 | AC13: - | AD13: 0 | AE13: 9.2 | AF13: 9.5 | AG13: 7 | AH13: 8.5 | AI13: 6.7 | AJ13: 6.7 | AL13: 6.7 | AM13: 6.7 | AN13: 8 | AO13: 7 | AP13: 6 | AQ13: 7.5 | AR13: - | AS13: 8.5 | AU13: - | AV13: 10 | AW13: - | AX13: 10 | AY13: - | AZ13: 10 | BA13: - | BB13: 10 | BC13: - | BD13: 10 | BE13: - | BF13: 10 | BG13: - | BH13: 10 | BI13: - | BJ13: 10
A14: IND00698 | B14: IND00698 | C14: Capital Markets - Equity | D14: Photos/Albin-Thomas-1.png | E14: Albin Thomas | F14: Albin Thomas's instruction scores are his strongest RISE metric, built on a practice that spans both ECM and DCM and a track record of first-of-their-kind transactions that generates repeat work. The Mahindra Finance rights issue, one of the first executed under the new streamlined SEBI regime, and the ROADIS high-yield bond, the first tollway high-yield bond in India, are good illustrations of his work. Thomas' AI and data usage is the sophistication standout: his team captures SEBI observations on filed offer documents into a structured database, creating ready-made prompts for drafting teams on what the regulator has been scrutinising in the past six months. Clients include Mahindra Group, IIFL Capital, and Jefferies. | G14: Mumbai | H14: Partner | I14: Trilegal | J14: 5.9 | L14: 23 | M14: 2.4 | N14: 4.9 | P14: 0 | Q14: 3.2 | R14: 2.9 | S14: 6 | T14: 6.2 | U14: 6.8 | V14: 9.5 | W14: 8.5 | X14: 8.8 | Y14: 8.2 | Z14: Top 10 | AA14: 8.4 | AB14: 7.3 | AC14: 8.6 | AD14: 8.6 | AE14: 9.9 | AF14: 9.4 | AG14: 8.5 | AH14: 8.2 | AI14: 7.1 | AJ14: 7.1 | AL14: 8.7 | AM14: 7.3 | AN14: 6 | AO14: 7 | AP14: 6 | AQ14: 8 | AR14: - | AS14: 8.5 | AU14: - | AV14: 10 | AW14: - | AX14: 10 | AY14: - | AZ14: 10 | BA14: - | BB14: 10 | BC14: - | BD14: 10 | BE14: - | BF14: 10 | BG14: - | BH14: 10 | BI14: - | BJ14: 10
A15: IND00291 | B15: IND00291 | C15: Cyber | D15: Anirban Mohapatra.jpg | E15: Anirban Mohapatra | F15: Anirban Mohapatra receives a high RISE client experience score. Clients rated his service, commerciality, EQ and network particularly highly. Mohapatra's score on the RISE instruction metric reflects a cross-sector practice spanning large technology companies, domestic and global banks, insurance companies, and platforms. His cyber advisory practice sits within the firm's new Digital Plus practice, a unified team that covers transactions, advisory, and incident response for clients. A strong score on the RISE sophistication metric is also is based on an advanced use of technology and approach to talent development. Mohapatra's training philosophy requires junior lawyers to understand technology architecture before advising on it. The firm uses legal AI tool Legora, and his team has built a proprietary prompt library refined in weekly sessions, with AI now deployed on transaction checklists, drafting, summarisation, and first-response analysis across data-heavy matters. He also authored a public cybersecurity handbook drawing on global precedent and client experience. | G15: Bengaluru | H15: Partner | I15: Cyril Amarchand Mangaldas | J15: 5.3 | L15: 17 | M15: 2 | N15: 3.75 | P15: 0 | Q15: 0 | R15: 6 | S15: 7.1 | T15: 0 | U15: 8 | V15: 7.9 | W15: 8.3 | X15: 7.6 | Y15: 8 | AA15: 6.5 | AB15: 7.6 | AC15: - | AD15: 0 | AE15: 8.9 | AF15: 8.8 | AG15: 7.5 | AH15: 7.5 | AI15: 7.4 | AJ15: 6.7 | AK15: Top 5 | AL15: 8 | AM15: 6.7 | AN15: 7 | AO15: 7 | AP15: 7 | AQ15: 6 | AR15: 9 | AS15: 8.5 | AT15: Top 5 | AU15: 10 | AV15: 10 | AW15: 9 | AX15: 10 | AY15: 10 | AZ15: 10 | BA15: 9 | BB15: 10 | BC15: 10 | BD15: 10 | BE15: 8 | BF15: 10 | BG15: 10 | BH15: 10 | BI15: 9 | BJ15: 10
A16: IND02193 | B16: IND02193 | C16: International Trade | D16: Photos/Ankur Sharma.jpg | E16: Ankur Sharma | F16: Ankur Sharma at Lakshmikumaran & Sridharan has established a leading position in sanctions and carbon border adjustment mechanism advisory, two of the fastest-moving sub-practice areas in international trade, at a moment when most practitioners are still developing their footing in both. Sharma scores in the top 5 for the RISE instructions metric as a result of his expertise in these frontier specialisms. Sharma's talent development for junior lawyers is also strong, with training structured around emerging laws paired with business development strategy. A background in engineering rather than the accountancy qualifications more common among trade lawyers gives him a mathematical foundation that he applies directly to the economic analysis that CBAM work demands. | G16: Delhi | H16: Partner | I16: Lakshmikumaran & Sridharan | J16: 6.2 | K16: Top 10 | L16: 10 | M16: 3.3 | N16: 3.35 | O16: Top 10 | P16: 0 | Q16: 0 | R16: 7.1 | S16: 7.1 | T16: 6.5 | U16: 7.1 | V16: 8.8 | W16: 8.9 | X16: 9.2 | Y16: 8.6 | Z16: Top 5 | AA16: 8.4 | AB16: 8.6 | AC16: - | AD16: 0 | AE16: 9.6 | AF16: 8.9 | AG16: 9.3 | AH16: 8.7 | AI16: 6 | AJ16: 6.4 | AL16: 4 | AM16: 5.3 | AN16: 6 | AO16: 7 | AP16: 8 | AQ16: 7.5 | AR16: 6.8 | AS16: 8.3 | AU16: 6 | AV16: 10 | AW16: 8 | AX16: 10 | AY16: 8 | AZ16: 10 | BA16: 8 | BB16: 10 | BC16: 8 | BD16: 10 | BE16: 8 | BF16: 10 | BG16: 8 | BH16: 10 | BI16: 8 | BJ16: 10
A17: IND00038 | B17: IND00038 | C17: Competition | D17: Photos/Anshuman Sakle 2025 web_0.png | E17: Anshuman Sakle | F17: Anshuman Sakle ranks eighth in the RISE competition standings, supported by a near-equal balance between his reputation and instruction scores. His reputation is defined by exceptional visibility; he is one of the most frequently quoted practitioners in the legal press and maintains an excellent profile across international legal directories and peer mentions. His Instructions score is equally robust, reflecting a high-volume, high-complexity practice that handled 17 major transactions in 2025 for a prestigious client roster including Torrent Pharmaceuticals, Mahindra & Mahindra, Haldiram Snack Foods, Interpublic Group (IPG), Wilmar International, and American Axle & Manufacturing. Based in Mumbai, Sakle’s practice typically splits 75% toward merger control and 25% toward enforcement, though he notes this ratio fluctuates with the Commission’s investigative cycles. He differentiates himself through a culture of team continuity; by giving associates early client-facing responsibility, he maintains notably low attrition rates. This stability, combined with his long-standing engagement with the CCI, provides clients with reliable regulatory navigation across diverse sectors such as pharma, financial services, and oil and gas. His profile marks him as a highly visible market leader who remains deeply embedded in the execution of complex, sector-spanning mandates. | G17: Mumbai | H17: Partner | I17: Khaitan & Co | J17: 7.9 | K17: Top 10 | L17: 8 | M17: 8.1 | N17: 5.6 | O17: Top 10 | P17: 6.9 | Q17: 4.1 | R17: 9.2 | S17: 7.5 | T17: 10 | U17: 5.9 | V17: 9.3 | W17: 8.3 | X17: 8.3 | Y17: 8.4 | AA17: 7.5 | AB17: 7.4 | AC17: - | AD17: 0 | AE17: 9.4 | AF17: 9.5 | AG17: 8 | AH17: 8.5 | AI17: 6.9 | AJ17: 6.7 | AL17: 6.7 | AM17: 6.7 | AN17: 7 | AO17: 7 | AP17: 7 | AQ17: 7.5 | AR17: 8.5 | AS17: 8.5 | AT17: Top 10 | AU17: 10 | AV17: 10 | AW17: 10 | AX17: 10 | AY17: 10 | AZ17: 10 | BA17: 10 | BB17: 10 | BC17: 10 | BD17: 10 | BE17: 10 | BF17: 10 | BG17: 10 | BH17: 10 | BI17: 10 | BJ17: 10
A18: IND00968 | B18: IND00968 | C18: Competition | D18: Photos/Anu Monga.jpg | E18: Anu Monga | F18: Anu Monga achieves the second-highest experience score in her cohort, rated particularly strongly by clients for her expertise, commerciality, and communication. Instruction scores are her second strongest RISE metric, driven by advisory work for multiple Indian ministries on policy and by representing the Government of India before foreign authorities including in the US, Canada and China. She co-leads the youngest firm in this ranking of top international trade lawyers, formed only in 2020. Perhaps partly from the agility of being a smaller, younger firm, AnantLaw is the only Indian firm using the global legal research platform VLex. It is also a signal of the practice's orientation toward international standards. Complementary specialisations across international trade, competition law, and disputes, combined with deep government advisory work, produce a practice that is as politically attuned as it is technically grounded. | G18: Delhi | H18: Partner | I18: AnantLaw | J18: 5.7 | L18: 32 | M18: 2.7 | N18: 5.6 | P18: 0 | Q18: 4.1 | R18: 5.1 | S18: 7.5 | T18: 5.9 | U18: 5.9 | V18: 7.7 | W18: 8.3 | X18: 8.9 | Y18: 8.4 | AA18: 6.4 | AB18: 7.4 | AC18: - | AD18: 0 | AE18: 6.6 | AF18: 9.5 | AG18: 10 | AH18: 8.5 | AI18: 5.4 | AJ18: 6.7 | AL18: 4 | AM18: 6.7 | AN18: 7 | AO18: 7 | AP18: 6 | AQ18: 7.5 | AR18: 9 | AS18: 8.5 | AT18: Top 10 | AU18: 9 | AV18: 10 | AW18: 10 | AX18: 10 | AY18: 10 | AZ18: 10 | BA18: 10 | BB18: 10 | BC18: 9 | BD18: 10 | BE18: 9 | BF18: 10 | BG18: 9 | BH18: 10 | BI18: 9 | BJ18: 10
A19: IND00968 | B19: IND00968 | C19: International Trade | D19: Photos/Anu Monga.jpg | E19: Anu Monga | F19: Anu Monga achieves the second-highest experience score in her cohort, rated particularly strongly by clients for her expertise, commerciality, and communication. Instruction scores are her second strongest RISE metric, driven by advisory work for multiple Indian ministries on policy and by representing the Government of India before foreign authorities including in the US, Canada and China. She co-leads the youngest firm in this ranking of top international trade lawyers, formed only in 2020. Perhaps partly from the agility of being a smaller, younger firm, AnantLaw is the only Indian firm using the global legal research platform VLex. It is also a signal of the practice's orientation toward international standards. Complementary specialisations across international trade, competition law, and disputes, combined with deep government advisory work, produce a practice that is as politically attuned as it is technically grounded. | G19: Delhi | H19: Partner | I19: AnantLaw | J19: 5.3 | L19: 13 | M19: 2.1 | N19: 3.35 | P19: 0 | Q19: 0 | R19: 0 | S19: 7.1 | T19: 8 | U19: 7.1 | V19: 8.7 | W19: 8.9 | X19: 8.6 | Y19: 8.6 | Z19: Top 10 | AA19: 8.6 | AB19: 8.6 | AC19: - | AD19: 0 | AE19: 8.7 | AF19: 8.9 | AG19: 8.5 | AH19: 8.7 | AI19: 5.4 | AJ19: 6.4 | AL19: 4 | AM19: 5.3 | AN19: 7 | AO19: 7 | AP19: 6 | AQ19: 7.5 | AR19: 9 | AS19: 8.3 | AT19: Ranked 2nd | AU19: 9 | AV19: 10 | AW19: 10 | AX19: 10 | AY19: 10 | AZ19: 10 | BA19: 10 | BB19: 10 | BC19: 9 | BD19: 10 | BE19: 9 | BF19: 10 | BG19: 9 | BH19: 10 | BI19: 9 | BJ19: 10
A20: IND07570 | B20: IND08621 | C20: International Trade | D20: Photos/Anuradha R V.jpg | E20: Anuradha RV | F20: Anuradha RV at Clarus Law Associates has built a practice on policy and high-level advisory rather than the anti-dumping foundation more common for a trade lawyer. Her work is focused more on services and sustainability commitments as well as investment commitments in bilateral investment treaties, and her clientele includes government bodies and industry associations. She consults with the International Trade Center in Geneva, supporting countries on trade policy development and WTO accession, a mandate profile that operates at a different level of the market to most practitioners here. She is a prolific writer and teacher alongside her practice, co-authoring articles with economists on India's trade policies for publications including the Hindustan Times and Mint, a combination that reinforces both her external profile and technical proficiency in emerging sub-practice areas of trade law. Talent development is a strong sub-indicator, with associates rotated across trade, investment, and policy to broaden exposure and match availability to workflow. | G20: Delhi | H20: Partner | I20: Clarus Law Associates | J20: 6.1 | K20: Top 10 | L20: 9 | M20: 3.4 | N20: 3.35 | O20: Top 10 | P20: 0 | Q20: 0 | R20: 7.5 | S20: 7.1 | T20: 10 | U20: 7.1 | V20: 9.1 | W20: 8.9 | X20: 8.9 | Y20: 8.6 | Z20: Top 10 | AA20: 8.9 | AB20: 8.6 | AC20: - | AD20: 0 | AE20: 9 | AF20: 8.9 | AG20: 8.8 | AH20: 8.7 | AI20: 6 | AJ20: 6.4 | AK20: Top 10 | AL20: 2.7 | AM20: 5.3 | AN20: - | AO20: 7 | AP20: 9 | AQ20: 7.5 | AR20: - | AS20: 8.3 | AU20: - | AV20: 10 | AW20: - | AX20: 10 | AY20: - | AZ20: 10 | BA20: - | BB20: 10 | BC20: - | BD20: 10 | BE20: - | BF20: 10 | BG20: - | BH20: 10 | BI20: - | BJ20: 10
A21: IND00428 | B21: IND00428 | C21: Competition | D21: Photos/Aparna Mehra.png | E21: Aparna Mehra | F21: Aparna Mehra ranks within the top 20 of the RISE Competition list, with her strongest metric being Reputation. This standing is driven by consistent recognition across legal directories and a notable social media presence, alongside a solid profile among her peers. Her Instructions score is also robust; while she maintains an understated profile, she remains a trusted advisor for high-caliber clients including ArcelorMittal, Bain Capital Investors, Jindal Steel & Power, Rolls-Royce India, and Vedanta Limited. As one of the first generation of Indian competition specialists with two decades of experience, Mehra’s practice has a distinct cross-border character. She is frequently sought out as local counsel by firms in Japan, Brussels, London, and New York for specialist mandates. She believes her practice is valued for its reliability and deep system-level understanding of Indian merger control. This expertise is evident in her analysis of deal value thresholds and evolving green channel filing behaviors, reflecting a sophisticated grasp of the regulatory landscape that transcends individual mandates. | G21: Delhi | H21: Partner | I21: Trilegal | J21: 7 | L21: 18 | M21: 7.5 | N21: 5.6 | O21: Top 10 | P21: 7.2 | Q21: 4.1 | R21: 7.8 | S21: 7.5 | T21: 7.5 | U21: 5.9 | V21: 8.3 | W21: 8.3 | X21: 6.8 | Y21: 8.4 | AA21: 7.2 | AB21: 7.4 | AC21: - | AD21: 0 | AE21: 7.6 | AF21: 9.5 | AG21: 6 | AH21: 8.5 | AI21: 6.5 | AJ21: 6.7 | AL21: - | AM21: 6.7 | AN21: 6 | AO21: 7 | AP21: - | AQ21: 7.5 | AR21: - | AS21: 8.5 | AU21: - | AV21: 10 | AW21: - | AX21: 10 | AY21: - | AZ21: 10 | BA21: - | BB21: 10 | BC21: - | BD21: 10 | BE21: - | BF21: 10 | BG21: - | BH21: 10 | BI21: - | BJ21: 10
A22: IND01915 | B22: IND01915 | C22: Capital Markets - Equity | D22: Photos/Arka-Mookerjee-Profile-Picture.jpg | E22: Arka Mookerjee | F22: Around 90 per cent of Arka Mookerjee's work at J. Sagar Associates is independently generated, a figure that is unusual at his level and reflected by his instruction scores in the RISE rating. His client roster spans Temasek, for whom he handles all Indian exits, alongside Axis, Kotak, Citi, and JPMorgan. A significant portion of his practice covers government infrastructure mandates. The Raajmarg Infra Investment Trust, the first government-sponsored InvIT in the roads sector, required an entirely new structure to monetise completed road assets outside a standard disinvestment framework, a transaction that illustrates both the complexity and the novelty of his practice. | G22: Mumbai | H22: Partner | I22: JSA Advocates & Solicitors | J22: 7.4 | L22: 11 | M22: 6.5 | N22: 4.9 | P22: 4.5 | Q22: 3.2 | R22: 9 | S22: 6 | T22: 8.5 | U22: 6.8 | V22: 9.3 | W22: 8.5 | X22: 9 | Y22: 8.2 | Z22: Top 10 | AA22: 9.2 | AB22: 7.3 | AC22: 9 | AD22: 8.6 | AE22: 9.9 | AF22: 9.4 | AG22: 8.5 | AH22: 8.2 | AI22: 6.2 | AJ22: 7.1 | AL22: 4 | AM22: 7.3 | AN22: 7 | AO22: 7 | AP22: 8 | AQ22: 8 | AR22: 7.9 | AS22: 8.5 | AU22: 10 | AV22: 10 | AW22: 10 | AX22: 10 | AY22: 10 | AZ22: 10 | BA22: 8 | BB22: 10 | BC22: 10 | BD22: 10 | BE22: 8 | BF22: 10 | BG22: 8 | BH22: 10 | BI22: 10 | BJ22: 10
A23: IND00298 | B23: IND00298 | C23: Cyber | D23: Arun-S.-Prabhu-1.png | E23: Arun Prabhu | F23: Arun Prabhu has developed a leading cyber practice at the firm over the past two decades, and is frequently quoted in the press as a thought leader on data protection and technology law and policy. This is shown in his leading score for the RISE news media metric, and strong overall reputation rating. He acts for many global tech giants, but his transactional and advisory work cuts across sectors as organisations look to implement new compliance measures to meet India's new data protection requirements. A high score on the RISE instructions metrics draws on a profile client bases as well as handling a large number , and high complexity of cyber matters in the past year. Prabhu is closely engaged with the Indian regulators and helps client anticipate changes in India's rapidly changing regulatory environment. Amongst the tech-savvy cyber practitioners, he also scores highly on the RISE sophistication metrics. He uses a range of AI tools for document review, red teaming, and client-specific tasks, and to help more accurately predict client fees. | G23: Bengaluru | H23: Partner (Co-Head - Technology & Telecommunications) | I23: Cyril Amarchand Mangaldas | J23: 7.2 | K23: Top 5 | L23: 5 | M23: 7.2 | N23: 3.75 | O23: Top 5 | P23: 6 | Q23: 0 | R23: 7.5 | S23: 7.1 | T23: 10 | U23: 8 | V23: 8.5 | W23: 8.3 | X23: 7.5 | Y23: 8 | AA23: 8 | AB23: 7.6 | AC23: - | AD23: 0 | AE23: 8.2 | AF23: 8.8 | AG23: 7 | AH23: 7.5 | AI23: 6.8 | AJ23: 6.7 | AK23: Top 10 | AL23: 8 | AM23: 6.7 | AN23: 10 | AO23: 7 | AP23: 4 | AQ23: 6 | AR23: - | AS23: 8.5 | AU23: - | AV23: 10 | AW23: - | AX23: 10 | AY23: - | AZ23: 10 | BA23: - | BB23: 10 | BC23: - | BD23: 10 | BE23: - | BF23: 10 | BG23: - | BH23: 10 | BI23: - | BJ23: 10
A24: IND07515 | B24: IND08609 | C24: Arbitration | D24: Photos/Ashim Sood.jpg | E24: Ashim Sood | F24: Ashim Sood runs a deliberately constrained practice built around depth rather than volume, concentrating on a small number of matters at a time. Direct senior involvement is the product rather than an occasional feature. His RISE instruction scores reflect this: the work he takes on is typically complex in legal rather than financial terms, gravitating toward jurisdictional questions, corporate veil arguments, and cases where the applicable framework is genuinely unsettled. His sophistication score is anchored in how he deploys technology. He uses AI primarily as a verification layer to identify contradictions across documents and cross-check witness statements against correspondence, and is building a knowledge management system to retrieve prior research systematically across matters. | G24: Delhi | H24: Principal | I24: Ashim Sood Law Offices | J24: 5.2 | L24: 28 | M24: 2.8 | N24: 3.6 | P24: 1 | Q24: 1 | R24: 6.6 | S24: 7.1 | T24: 0 | U24: 6.3 | V24: 9.2 | W24: 8.9 | X24: 7.7 | Y24: 7.8 | AA24: 7.1 | AB24: 7.6 | AC24: 9.1 | AD24: 7.5 | AE24: 7.1 | AF24: 7.4 | AG24: 7.3 | AH24: 8.7 | AI24: 5.2 | AJ24: 7.1 | AL24: 6 | AM24: 6.7 | AN24: 6 | AO24: 6 | AP24: 4 | AQ24: 7.5 | AR24: - | AS24: 8.3 | AU24: - | AV24: 10 | AW24: - | AX24: 10 | AY24: - | AZ24: 10 | BA24: - | BB24: 10 | BC24: - | BD24: 10 | BE24: - | BF24: 10 | BG24: - | BH24: 10 | BI24: - | BJ24: 10
A25: IND00712 | B25: IND00712 | C25: Arbitration | D25: Photos/ashish-bhan.png | E25: Ashish Bhan | F25: Ashish Bhan has been at Trilegal since 2010 and leads a team of 25 to 30 lawyers, with arbitration accounting for around 45 to 50% of his personal practice. AI usage drives his strong RISE sophistication score. Running searches across Trilegal's 25-year database via Lucio, his team recently identified eight recurring risk areas in a defence tender in days rather than the two days of manual file review previously required. Defence and aviation manufacturers form the core of his client base, with a practice specialising in procurement arbitrations involving G2G contracts, geopolitical sensitivities, and strategic decisions about which claims to press and which to concede to preserve government relationships across jurisdictions. | G25: Delhi | H25: Partner | I25: Trilegal | J25: 5.9 | L25: 16 | M25: 3 | N25: 3.6 | P25: 1 | Q25: 1 | R25: 7.8 | S25: 7.1 | T25: 0 | U25: 6.3 | V25: 9.2 | W25: 8.9 | X25: 7.8 | Y25: 7.8 | AA25: 5.5 | AB25: 7.6 | AC25: 8.1 | AD25: 7.5 | AE25: 6.8 | AF25: 7.4 | AG25: 8.7 | AH25: 8.7 | AI25: 7.9 | AJ25: 7.1 | AK25: Ranked 1st | AL25: 9.3 | AM25: 6.7 | AN25: - | AO25: 6 | AP25: - | AQ25: 7.5 | AR25: 7.9 | AS25: 8.3 | AU25: 10 | AV25: 10 | AW25: 10 | AX25: 10 | AY25: 10 | AZ25: 10 | BA25: 8 | BB25: 10 | BC25: 10 | BD25: 10 | BE25: 8 | BF25: 10 | BG25: 8 | BH25: 10 | BI25: 10 | BJ25: 10
A26: IND01267 | B26: IND01267 | C26: International Trade | D26: Photos/Ashish-Chandra.jpg | E26: Ashish Chandra | F26: Ashish Chandra at DSK Legal is one of a small number of Indian trade lawyers with direct WTO litigation experience, and with the appellate system now near non-functioning, he has redirected that expertise into trade disputes before domestic high courts. This, in part, earns him a place in the top 10 of scores for the RISE instructions metric. Additionally to WTO and trade disputes, Chandra is involved in trade remedies, customs, export controls and sanctions. He advised the Government of Korea until 2024 in Indian trade remedy investigations, a mandate that sits alongside a full-service trade practice spanning the complete range of matters. | G26: Delhi | H26: Partner | I26: DSK Legal | J26: 5.8 | L26: 11 | M26: 3.2 | N26: 3.35 | P26: 0 | Q26: 0 | R26: 8.7 | S26: 7.1 | T26: 3.8 | U26: 7.1 | V26: 8.9 | W26: 8.9 | X26: 8.6 | Y26: 8.6 | Z26: Top 10 | AA26: 8.8 | AB26: 8.6 | AC26: - | AD26: 0 | AE26: 8.5 | AF26: 8.9 | AG26: 8.6 | AH26: 8.7 | AI26: 5.2 | AJ26: 6.4 | AL26: 4 | AM26: 5.3 | AN26: 4 | AO26: 7 | AP26: 7 | AQ26: 7.5 | AR26: 8.1 | AS26: 8.3 | AT26: Top 10 | AU26: 10 | AV26: 10 | AW26: 10 | AX26: 10 | AY26: 10 | AZ26: 10 | BA26: 10 | BB26: 10 | BC26: 8 | BD26: 10 | BE26: 10 | BF26: 10 | BG26: 8 | BH26: 10 | BI26: 10 | BJ26: 10
A27: IND07689 | B27: IND08618 | C27: International Trade | D27: Photos/Atul Sharma.png | E27: Atul Sharma | F27: Atul Sharma at Sarvada is the strongest-performing practitioner from a boutique in this cohort, driven by peer recommendations and a mandate profile that includes acting as lead counsel for the Government of India in active WTO disputes and representing a Saudi Arabian chemical corporation before the US Department of Commerce in third-country trade remedy proceedings unrelated to India. His score for the pricing RISE metric is the highest, underpinned by structured scoping systems and deferred payment arrangements aligned to client billing cycles, a commercial flexibility that larger firms rarely offer. A practical differentiator in his client service is working directly through clients' SAP and Oracle systems to extract and reconcile raw data for filings, reducing the burden on client teams and improving the accuracy of submissions. | G27: Delhi | H27: Partner | I27: Sarvada Legal | J27: 7.2 | K27: Top 10 | L27: 6 | M27: 6 | N27: 3.35 | O27: Top 10 | P27: 3.8 | Q27: 0 | R27: 7.5 | S27: 7.1 | T27: 9.5 | U27: 7.1 | V27: 9.3 | W27: 8.9 | X27: 9.1 | Y27: 8.6 | Z27: Top 10 | AA27: 8.2 | AB27: 8.6 | AC27: - | AD27: 0 | AE27: 9.4 | AF27: 8.9 | AG27: 9.3 | AH27: 8.7 | AI27: 5.7 | AJ27: 6.4 | AL27: 5.3 | AM27: 5.3 | AN27: 8 | AO27: 7 | AP27: 5 | AQ27: 7.5 | AR27: - | AS27: 8.3 | AU27: - | AV27: 10 | AW27: - | AX27: 10 | AY27: - | AZ27: 10 | BA27: - | BB27: 10 | BC27: - | BD27: 10 | BE27: - | BF27: 10 | BG27: - | BH27: 10 | BI27: - | BJ27: 10
A28: IND00301 | B28: IND00301 | C28: Competition | D28: Photos/avantika kakkar.jpg | E28: Avaantika Kakkar | F28: Avaantika Kakkar’s strongest RISE metrics are Reputation and Instructions, with high scores driven by consistent peer recognition, strong directory presence and sustained demand from sophisticated clients. Her practice spans the Commission, appellate forums, High Courts and the Supreme Court, a breadth of forum coverage within a single practice that differentiates her in a market where many competition partners operate more narrowly. She is focused on complex, data-heavy merger control work across healthcare, infrastructure and industrial sectors, where market definition and competitive effects are actively contested. She operates a lean staffing model, giving associates and partners greater ownership of matters. On the enforcement side, she has been involved in a number of the regulator’s most significant dawn raids, including instructions from clients outside the firm’s existing base, reflecting trust in high-pressure situations. | G28: Mumbai | H28: Partner (Head - Competition Law) | I28: Cyril Amarchand Mangaldas | J28: 8.7 | K28: Ranked 3rd | L28: 3 | M28: 9 | N28: 5.6 | O28: Ranked 3rd | P28: 8.7 | Q28: 4.1 | R28: 10 | S28: 7.5 | T28: 8.7 | U28: 5.9 | V28: 9.1 | W28: 8.3 | X28: 9.2 | Y28: 8.4 | Z28: Top 5 | AA28: 8.9 | AB28: 7.4 | AC28: - | AD28: 0 | AE28: 9.9 | AF28: 9.5 | AG28: 9 | AH28: 8.5 | AI28: 7.2 | AJ28: 6.7 | AL28: 6 | AM28: 6.7 | AN28: 8 | AO28: 7 | AP28: 8 | AQ28: 7.5 | AR28: 9.1 | AS28: 8.5 | AT28: Top 10 | AU28: 10 | AV28: 10 | AW28: 10 | AX28: 10 | AY28: 10 | AZ28: 10 | BA28: 9 | BB28: 10 | BC28: 10 | BD28: 10 | BE28: 10 | BF28: 10 | BG28: 8 | BH28: 10 | BI28: 9 | BJ28: 10
A29: IND01150 | B29: IND01150 | C29: Competition | D29: Photos/Avinash Amarnath.jpg | E29: Avinash Amarnath | F29: Avinash Amarnath's scores highest in Instructions, and is particularly strong for its complexity, followed by client quality and volume metrics. Amarnath's practice has a greater emphasis on complex enforcement work and litigation mandates, for a client mix that includes Google, Intel and major participants in the Amazon and Flipkart investigations, alongside significant corporate groups and media distribution clients. Around half the practice is international, with working relationships spanning Allen Overy Shearman, Freshfields, Linklaters, Davis Polk, and Stibbe. His work sits at the intersection of competition law, administrative law and sector regulation, with a particular concentration in digital markets, telecom-media disputes, leniency and cartel defence.Notable matters include acting on what is understood to be India's first commitments application under the new settlements framework, the Asianet Digital jurisdictional dispute requiring analysis of competing regulatory regimes at the Supreme Court level, and the seller-side challenge in the Amazon and Flipkart investigations raising fundamental questions of CCI procedure and due process. | G29: Hyderabad | H29: Partner & Head of Competition and Disputes | I29: Chandhiok & Mahajan | J29: 5.9 | L29: 31 | M29: 2.5 | N29: 5.6 | P29: 0 | Q29: 4.1 | R29: 5.8 | S29: 7.5 | T29: 3.6 | U29: 5.9 | V29: 8.3 | W29: 8.3 | X29: 8.6 | Y29: 8.4 | AA29: 7.4 | AB29: 7.4 | AC29: - | AD29: 0 | AE29: 8.3 | AF29: 9.5 | AG29: 9.5 | AH29: 8.5 | AI29: 7.1 | AJ29: 6.7 | AL29: 6.7 | AM29: 6.7 | AN29: 6 | AO29: 7 | AP29: 8 | AQ29: 7.5 | AR29: 8.1 | AS29: 8.5 | AU29: 10 | AV29: 10 | AW29: 10 | AX29: 10 | AY29: 10 | AZ29: 10 | BA29: 10 | BB29: 10 | BC29: 10 | BD29: 10 | BE29: 8 | BF29: 10 | BG29: 8 | BH29: 10 | BI29: 10 | BJ29: 10
A30: IND00059 | B30: IND00059 | C30: International Trade | D30: Photos/Ayush A Mehrotra.png | E30: Ayush Mehrotra | F30: Ayush Mehrotra at Khaitan & Co scores highest in the cohort for technology and data use, leveraging the firm's ask.Kai tool across legal research, drafting, and large-scale data processing, with efficiency gains reportedly applied directly to competitive pricing and faster turnaround for clients. He is a partner in one of the larger indirect tax practices within a full-service Indian firm, integrating customs, GST, excise, and WTO-linked advisory into a practice that also covers sanctions-driven supply chain restructuring for Indian entities affected by US designations across multiple jurisdictions. A standout recent matter saw Mehrotra secure a reduction of an ASEAN FTA-related demand from over $1.2bn to approximately Rs 11bn, with High Court proceedings ongoing. | G30: Delhi | H30: Partner | I30: Khaitan & Co | J30: 5.7 | L30: 14 | M30: 1.9 | N30: 3.35 | P30: 0 | Q30: 0 | R30: 0 | S30: 7.1 | T30: 6 | U30: 7.1 | V30: 9.8 | W30: 8.9 | X30: 8.4 | Y30: 8.6 | AA30: 7.6 | AB30: 8.6 | AC30: - | AD30: 0 | AE30: 8.6 | AF30: 8.9 | AG30: 8.6 | AH30: 8.7 | AI30: 8 | AJ30: 6.4 | AK30: Ranked 1st | AL30: 8.7 | AM30: 5.3 | AN30: - | AO30: 7 | AP30: 8 | AQ30: 7.5 | AR30: 8.3 | AS30: 8.3 | AT30: Top 10 | AU30: 10 | AV30: 10 | AW30: 10 | AX30: 10 | AY30: 10 | AZ30: 10 | BA30: 10 | BB30: 10 | BC30: 10 | BD30: 10 | BE30: 10 | BF30: 10 | BG30: 8 | BH30: 10 | BI30: 10 | BJ30: 10
A31: IND00371 | B31: IND00371 | C31: Capital Markets - Equity | D31: Photos/Reuben Chacko - ECM.jpg | E31: Reuben Chacko | F31: Based in Bangalore, Reuben Chacko leads CAM's South Capital markets team. Chacko is a very forward thinking lawyer and heavy AI user. He is also actively involved in recruitment and now assesses law students for their AI familiarity and proficiency. Other external roles include doing guest lectures in law schools (capital markets / securities law) a few times per year. In the RISE rating, his highest scores are in the Instruction and Sophistication set of indicators. Instructions and sophistications. His standout sub indicator is his usage of AI and data, where he is a keen experimenter. One of his use cases was to use AI to identify lender consent requirements (change of shareholding/management/control) across hundreds of bulky financing agreements (common for NBFC/MFI issuers). He predicts it has saved ~60–70% of time versus manual review. Chacko also scores very strongly on work complexity: he works in highly regulated sectors such as pharma and healthcare where IPOs/QIPs are challenging, and due diligence involves extensive operational approvals and compliance review. Recent deals include Anthem Biosciences IPO (Bangalore-based pharma); IndiQube (co-working / flexible workspace company) that he took public; Biocon Limited — advised on a QIP (earlier this year): Brigade Hospitality / Brigade Hotel Ventures IPOs. | G31: Bengaluru | H31: Partner - Regional Co-head Markets Practice (South) | I31: Cyril Amarchand Mangaldas | J31: 5.7 | L31: 26 | M31: 3 | N31: 4.9 | P31: 5 | Q31: 3.2 | R31: 1 | S31: 6 | T31: 0 | U31: 6.8 | V31: 0 | W31: 8.5 | X31: 7.6 | Y31: 8.2 | AA31: 7.5 | AB31: 7.3 | AC31: 8.3 | AD31: 8.6 | AE31: 4.7 | AF31: 9.4 | AG31: 10 | AH31: 8.2 | AI31: 7.6 | AJ31: 7.1 | AK31: Top 10 | AL31: 8.7 | AM31: 7.3 | AN31: - | AO31: 7 | AP31: - | AQ31: 8 | AR31: - | AS31: 8.5 | AU31: - | AV31: 10 | AW31: - | AX31: 10 | AY31: - | AZ31: 10 | BA31: - | BB31: 10 | BC31: - | BD31: 10 | BE31: - | BF31: 10 | BG31: - | BH31: 10 | BI31: - | BJ31: 10
A32: IND00451 | B32: IND00451 | C32: Competition | D32: Photos/Gauri-Chhabra.png | E32: Gauri Chhabra | F32: Based in Mumbai, Gauri Chhabra occupies a unique position in the Indian competition market as a senior partner deeply embedded in the city’s private equity and strategic M&A ecosystem. Her highest RISE metric is sophistication, driven by her exceptional commitment to talent development. She differentiates herself through her leadership of a close-knit, eight-associate team that has remained with her since their graduation, moving as a unit from her previous firm. Chhabra fosters this institutional depth through biweekly meetings and by encouraging her team to engage in deep research and thought leadership. Her instructions score is equally strong, characterized by high-complexity mandates for a prestigious client roster despite a more focused volume of work. She acts for major PE and sponsor-led clients, including Blackstone, WestBridge, and the Ontario Teachers’ Pension Plan, and has represented Petronas and JSW. Her practice, which is approximately 65% merger control, is noted for its responsiveness. This was recently evidenced in the Carlisle and Roop-Highway matter, where her team secured clearance in an unusually compressed timeframe despite managing over 50 product overlaps. | G32: Mumbai | H32: Partner | I32: Trilegal | J32: 6.2 | L32: 27 | M32: 3.7 | N32: 5.6 | P32: 4.1 | Q32: 4.1 | R32: 0 | S32: 7.5 | T32: 4.6 | U32: 5.9 | V32: 7.6 | W32: 8.3 | X32: 7.4 | Y32: 8.4 | AA32: 5.8 | AB32: 7.4 | AC32: - | AD32: 0 | AE32: 9.5 | AF32: 9.5 | AG32: 7 | AH32: 8.5 | AI32: 8.5 | AJ32: 6.7 | AK32: Ranked 2nd | AL32: 8.7 | AM32: 6.7 | AN32: 7 | AO32: 7 | AP32: 9 | AQ32: 7.5 | AR32: - | AS32: 8.5 | AU32: - | AV32: 10 | AW32: - | AX32: 10 | AY32: - | AZ32: 10 | BA32: - | BB32: 10 | BC32: - | BD32: 10 | BE32: - | BF32: 10 | BG32: - | BH32: 10 | BI32: - | BJ32: 10
A33: IND04713 | B33: IND04713 | C33: Competition | D33: Photos/Kirthi-Srinivas-Website-1.jpg | E33: Kirthi Srinivas | F33: Based in Mumbai, Kirthi Srinivas maintains a very high instructions score, placing him among the top tier for this metric. This standing is driven by a high volume of work and a prestigious client roster that leans toward private equity heavyweights like KKR, Bain, and Premji Invest, alongside corporate mandates for JSW Steel, Cube Highways, and Jumbotail. His Experience score is equally robust, reflecting a practice focused on complex, regulator-facing transactions rather than routine filings. Srinivas’s practice runs approximately 70/30 in favor of merger control over enforcement. A standout mandate is the KKR and Singtel data center transaction, which he notes as the first CCI review of the data center market to have conditions imposed. He believes his value lies in navigating the CCI’s internal dynamics and review style, especially during technically complicated filings and compressed timelines. While he is a "quiet achiever" with a more measured Reputation score across peer mentions and legal directories, his profile is anchored by consistent execution and the sheer scale of the portfolios he manages. | G33: Mumbai | H33: Partner | I33: AZB & Partners | J33: 6.7 | L33: 24 | M33: 4.4 | N33: 5.6 | P33: 3 | Q33: 4.1 | R33: 5.1 | S33: 7.5 | T33: 6.5 | U33: 5.9 | V33: 8.2 | W33: 8.3 | X33: 9.1 | Y33: 8.4 | Z33: Top 10 | AA33: 9.1 | AB33: 7.4 | AC33: - | AD33: 0 | AE33: 9.8 | AF33: 9.5 | AG33: 8.5 | AH33: 8.5 | AI33: 6.5 | AJ33: 6.7 | AL33: 6.7 | AM33: 6.7 | AN33: 7 | AO33: 7 | AP33: 6 | AQ33: 7.5 | AR33: 8.5 | AS33: 8.5 | AU33: 10 | AV33: 10 | AW33: 10 | AX33: 10 | AY33: 10 | AZ33: 10 | BA33: 10 | BB33: 10 | BC33: 10 | BD33: 10 | BE33: 10 | BF33: 10 | BG33: 10 | BH33: 10 | BI33: 10 | BJ33: 10
A34: IND00715 | B34: IND00715 | C34: Capital Markets - Equity | D34: Photos/bhakta-patnaik-1.png | E34: Bhakta Patnaik | F34: Bhakta Patnaik at Trilegal built the firm's capital markets practice from scratch a decade ago, growing it into a team of close to 100 lawyers that handled 52 listings last year. His instruction scores are his strongest RISE metric, underpinned by a client base that includes issues, banks and investors such as Blackstone, GIC, ICICI Securities, Bank of America Merrill Lynch, Citigroup, Kedaara Capital and Piramal Group. He is regularly brought in where little precedent exists. Arcil's IPO is a good illustration: the first ever by an asset reconstruction company in India, with a trust-based structure that triggered complex disclosure requirements with no comparable transaction to emulate. | G34: Mumbai | H34: Partner | I34: Trilegal | J34: 8 | K34: Top 10 | L34: 7 | M34: 7 | N34: 4.9 | O34: Top 10 | P34: 6.5 | Q34: 3.2 | R34: 8.6 | S34: 6 | T34: 6.7 | U34: 6.8 | V34: 7.5 | W34: 8.5 | X34: 9.1 | Y34: 8.2 | Z34: Ranked 3rd | AA34: 8.8 | AB34: 7.3 | AC34: 8.6 | AD34: 8.6 | AE34: 10 | AF34: 9.4 | AG34: 9.2 | AH34: 8.2 | AI34: 7.7 | AJ34: 7.1 | AK34: Top 5 | AL34: 7.3 | AM34: 7.3 | AN34: 6 | AO34: 7 | AP34: 9 | AQ34: 8 | AR34: 8.5 | AS34: 8.5 | AT34: Top 10 | AU34: 10 | AV34: 10 | AW34: 10 | AX34: 10 | AY34: 10 | AZ34: 10 | BA34: 10 | BB34: 10 | BC34: 10 | BD34: 10 | BE34: 10 | BF34: 10 | BG34: 10 | BH34: 10 | BI34: 10 | BJ34: 10
A35: IND00628 | B35: IND00628 | C35: Competition | D35: Photos/Bharat-Budholia-e1637655967207.png | E35: Bharat Budholia | F35: Bharat Budholia ranks 10th in the rise competition rating, with instructions serving as his strongest metric. This standing is driven by a prestigious client roster and a near-equal balance between high volume and technical complexity. Based in Mumbai, Budholia is structurally positioned at the center of the city's private equity deal flow, representing heavyweights such as KKR and TPG, alongside Mankind Pharma, Citibank, Siemens, Qube Cinema, the BCCI, and the IATA. His reputation is exceptionally high, supported by strong peer recommendations and a consistent profile across legal directories and the legal press. Approximately 60% of his work focuses on merger control, where he differentiates himself by rejecting template-driven filings in favor of bespoke, sector-specific narratives. Within the sophistication category, his use of technology is a practical marker of quality; he has developed searchable databases of past advisory case law and sector-specific notes to ensure institutional consistency. | G35: Mumbai | H35: Partner | I35: AZB & Partners | J35: 7.9 | K35: Top 10 | L35: 10 | M35: 7.8 | N35: 5.6 | O35: Top 10 | P35: 7.2 | Q35: 4.1 | R35: 9 | S35: 7.5 | T35: 7.4 | U35: 5.9 | V35: 8.7 | W35: 8.3 | X35: 8.8 | Y35: 8.4 | AA35: 8.5 | AB35: 7.4 | AC35: - | AD35: 0 | AE35: 9.6 | AF35: 9.5 | AG35: 8.5 | AH35: 8.5 | AI35: 6.1 | AJ35: 6.7 | AL35: 9.6 | AM35: 6.7 | AN35: 5 | AO35: 7 | AP35: 6 | AQ35: 7.5 | AR35: 7.9 | AS35: 8.5 | AU35: 10 | AV35: 10 | AW35: 10 | AX35: 10 | AY35: 8 | AZ35: 10 | BA35: 10 | BB35: 10 | BC35: 10 | BD35: 10 | BE35: 8 | BF35: 10 | BG35: 8 | BH35: 10 | BI35: 10 | BJ35: 10
A36: IND00439 | B36: IND00439 | C36: Arbitration | D36: Photos/Binsy Susan.png | E36: Binsy Susan | F36: Binsy Susan's RISE instruction scores are her strongest metric, built on a genuinely multi-jurisdictional practice spanning SIAC, ICC, AAA, and CAM CCBC, with matters seated across Singapore, Brazil, the US, and India. Few India-based practitioners can match that breadth. Reputation scores are solid, underpinned by consistent directory recognition and a social media presence that keeps her visible beyond the immediate legal market. Her instruction base is distinctive in sector range, spanning technology, construction, oil and gas, energy, infrastructure, and telecoms alongside the more typical M&A, JV and shareholder disputes. | G36: Delhi | H36: Partner | I36: Shardul Amarchand Mangaldas & Co | J36: 7.3 | K36: Top 10 | L36: 8 | M36: 7.1 | N36: 3.6 | O36: Top 10 | P36: 6.8 | Q36: 1 | R36: 6.6 | S36: 7.1 | T36: 7.7 | U36: 6.3 | V36: 8.2 | W36: 8.9 | X36: 7.8 | Y36: 7.8 | AA36: 5.7 | AB36: 7.6 | AC36: 8.9 | AD36: 7.5 | AE36: 6.1 | AF36: 7.4 | AG36: 8.6 | AH36: 8.7 | AI36: 6.7 | AJ36: 7.1 | AL36: 8.7 | AM36: 6.7 | AN36: 6 | AO36: 6 | AP36: 5 | AQ36: 7.5 | AR36: 7 | AS36: 8.3 | AU36: 8 | AV36: 10 | AW36: 8 | AX36: 10 | AY36: 8 | AZ36: 10 | BA36: 8 | BB36: 10 | BC36: 8 | BD36: 10 | BE36: 8 | BF36: 10 | BG36: 8 | BH36: 10 | BI36: 8 | BJ36: 10
A37: IND00716 | B37: IND00716 | C37: Capital Markets - Equity | D37: Photos/Brajendu-bhaskar.png | E37: Brajendu Bhaskar | F37: Brajendu Bhaskar's client list at Trilegal is his standout sub-indicator among strong instruction and sophistication scores. Client relationships include ICICI Securities, JM Financial, JPMorgan, and Kotak among others. The Lenskart IPO is a good illustration of Bhaskar's work standard: a new-age tech company returning market confidence after the post-Paytm lull, with complexity driven by sophisticated investors, a dense cap table, and commercially sensitive negotiations where shareholder rights survive the listing. Earlier time at A&O in London gives him useful perspective on international markets that he brings to domestic clients. His team are growing in their AI skills, for example, analysing international offering documents to find comparisons for Indian deals where no domestic precedent exists. | G37: Mumbai | H37: Partner | I37: Trilegal | J37: 5.4 | L37: 35 | M37: 2.3 | N37: 4.9 | P37: 0 | Q37: 3.2 | R37: 2.9 | S37: 6 | T37: 6.5 | U37: 6.8 | V37: 7.4 | W37: 8.5 | X37: 7.8 | Y37: 8.2 | AA37: 6.7 | AB37: 7.3 | AC37: 7.6 | AD37: 8.6 | AE37: 10 | AF37: 9.4 | AG37: 7.5 | AH37: 8.2 | AI37: 6.9 | AJ37: 7.1 | AL37: 7.3 | AM37: 7.3 | AN37: 6 | AO37: 7 | AP37: - | AQ37: 8 | AR37: - | AS37: 8.5 | AU37: - | AV37: 10 | AW37: - | AX37: 10 | AY37: - | AZ37: 10 | BA37: - | BB37: 10 | BC37: - | BD37: 10 | BE37: - | BF37: 10 | BG37: - | BH37: 10 | BI37: - | BJ37: 10
A38: IND00064 | B38: IND00064 | C38: Arbitration | D38: Photos/Chakrapani Mishra 2025 web.png | E38: Chakrapani Misra | F38: Chakrapani Misra has practised arbitration for over 33 years, beginning under the 1940 Act before the current framework existed. His RISE reputation score is his most prominent metric, built through sustained directory recognition and a strong social media profile. His instruction base reflects a predominantly domestic practice of high legal complexity. Standout recent matters include a procedurally challenging ropeway project arbitration for a major Mumbai temple and an ICC cross-border money claim for a Mauritius-based company against an Indian multinational subsidiary. | G38: Mumbai | H38: Senior Partner | I38: Khaitan & Co | J38: 5.2 | L38: 30 | M38: 4.4 | N38: 3.6 | P38: 1 | Q38: 1 | R38: 9.2 | S38: 7.1 | T38: 7.2 | U38: 6.3 | V38: 9.1 | W38: 8.9 | X38: 5.5 | Y38: 7.8 | AA38: 5.7 | AB38: 7.6 | AC38: 4.2 | AD38: 7.5 | AE38: 0 | AF38: 7.4 | AG38: 8 | AH38: 8.7 | AI38: 6.2 | AJ38: 7.1 | AL38: 6 | AM38: 6.7 | AN38: 7 | AO38: 6 | AP38: 6 | AQ38: 7.5 | AR38: - | AS38: 8.3 | AU38: - | AV38: 10 | AW38: - | AX38: 10 | AY38: - | AZ38: 10 | BA38: - | BB38: 10 | BC38: - | BD38: 10 | BE38: - | BF38: 10 | BG38: - | BH38: 10 | BI38: - | BJ38: 10
A39: IND00118 | B39: IND00118 | C39: Competition | D39: Photos/Manas Kumar Chaudhuri.png | E39: Manas Kumar Chaudhuri | F39: Chaudhuri's strongest RISE metric is instructions, placing him at the top of the cohort for this indicator, driven by the quality of his clients and the complexity of his mandates. Experience scores are also notable, with clients reporting high satisfaction with his advisory style. His reputation score is moderated by fewer peer mentions relative to his instruction volume, though directory recognition remains strong. He holds the position of global Co-Chair of the IPBA Competition Law Committee and has served as a Non-Governmental Adviser to the CCI for the ICN and BRICS, reflecting an international profile that extends well beyond domestic practice. An old hand in the field, his experience spans the pre-CCI era to the current regime, with a specialism in enforcement cases and dawn raids where he adopts a restrained, risk-weighted approach, starting with forensic damage assessment rather than promising specific outcomes. His sophistication score reflects a heavy investment in talent development, training juniors in courtroom instincts and research methodology to pass on his institutional understanding of how Indian competition law has been constitutionally embedded over time. He has also been a visiting guest faculty on competition law of various National Law Schools of India for over a decade now. | G39: Delhi | H39: Partner | I39: Khaitan & Co | J39: 7.5 | L39: 13 | M39: 5.9 | N39: 5.6 | P39: 4.1 | Q39: 4.1 | R39: 10 | S39: 7.5 | T39: 5.6 | U39: 5.9 | V39: 7.9 | W39: 8.3 | X39: 9.1 | Y39: 8.4 | Z39: Top 10 | AA39: 8.3 | AB39: 7.4 | AC39: - | AD39: 0 | AE39: 9 | AF39: 9.5 | AG39: 9.5 | AH39: 8.5 | AI39: 7.7 | AJ39: 6.7 | AK39: Top 10 | AL39: 6.7 | AM39: 6.7 | AN39: 7 | AO39: 7 | AP39: 9 | AQ39: 7.5 | AR39: 8.5 | AS39: 8.5 | AT39: Top 10 | AU39: 10 | AV39: 10 | AW39: 10 | AX39: 10 | AY39: 10 | AZ39: 10 | BA39: 10 | BB39: 10 | BC39: 10 | BD39: 10 | BE39: 10 | BF39: 10 | BG39: 10 | BH39: 10 | BI39: 10 | BJ39: 10
A40: IND01161 | B40: IND01161 | C40: Competition | D40: Photos/Deeksha manchanda.jpg | E40: Deeksha Manchanda | F40: Deeksha Manchanda at Chandhiok & Mahajan scores most strongly on RISE instruction and sophistication metrics, with volume and technology the standout indicators. This is an unusual pairing that points to a practitioner embedded in technically demanding, long-running enforcement matters rather than one whose profile is driven by market pull or transaction flow. Her practice runs 60/40 in favour of behavioural, advisory, and enforcement work over merger control. Google is the clearest centrepiece, with multiple overlapping matters since 2020, a coordinated appeals strategy, and a substantial penalty reduction among the outcomes. JCB, Michelin, and Coca-Cola feature alongside, several on matters stretching across years rather than single mandates. That sticking power on complex, regulator-facing disputes is the most distinctive feature of the practice. She integrates AI tools actively into her workflow and takes a hands-on approach to team development and internal culture-building. | G40: Delhi | H40: Partner - Competition and Data Privacy | I40: Chandhiok & Mahajan | J40: 7 | L40: 20 | M40: 4.9 | N40: 5.6 | P40: 3 | Q40: 4.1 | R40: 8.3 | S40: 7.5 | T40: 4.6 | U40: 5.9 | V40: 8.8 | W40: 8.3 | X40: 8.8 | Y40: 8.4 | AA40: 6.7 | AB40: 7.4 | AC40: - | AD40: 0 | AE40: 9.5 | AF40: 9.5 | AG40: 9.5 | AH40: 8.5 | AI40: 7.5 | AJ40: 6.7 | AL40: 7.3 | AM40: 6.7 | AN40: 7 | AO40: 7 | AP40: 8 | AQ40: 7.5 | AR40: - | AS40: 8.5 | AU40: - | AV40: 10 | AW40: - | AX40: 10 | AY40: - | AZ40: 10 | BA40: - | BB40: 10 | BC40: - | BD40: 10 | BE40: - | BF40: 10 | BG40: - | BH40: 10 | BI40: - | BJ40: 10
A41: IND02203 | B41: IND02203 | C41: International Trade | D41: Photos/Devinder Bagia.jpg | E41: Devinder Bagia | F41: Devinder Bagia at Lakshmikumaran & Sridharan ranks third overall for the RISE international trade rankings. This is one behind V Lakshmikumaran, the founding and managing partner of LKS, whom Bagia acts as second in command to for international trade matters, a position that reflects both seniority and the breadth of his mandate oversight. He scores strongly on the instructions RISE metric, with a client base concentrated in petrochemicals, chemicals, pharmaceuticals, metals, and glass fibre, spanning the globe as well as Saudi Arabian, US, and Chinese clients across India's most active import sectors. A standout recent matter involved a petrochemical company in trade remedy proceedings before the DGTR, where he successfully deployed rarely made arguments for cost adjustments including from start-up and shutdown costs. His technology adoption is at an earlier stage than some peers, using Copilot selectively for research, though the firm is developing a bespoke AI tool for the practice. | G41: Delhi | H41: Partner | I41: Lakshmikumaran & Sridharan | J41: 8 | K41: Ranked 3rd | L41: 3 | M41: 7.5 | N41: 3.35 | O41: Ranked 3rd | P41: 7.6 | Q41: 0 | R41: 6.6 | S41: 7.1 | T41: 7.4 | U41: 7.1 | V41: 8.8 | W41: 8.9 | X41: 9.5 | Y41: 8.6 | Z41: Ranked 3rd | AA41: 9.5 | AB41: 8.6 | AC41: - | AD41: 0 | AE41: 10 | AF41: 8.9 | AG41: 9.3 | AH41: 8.7 | AI41: 5.9 | AJ41: 6.4 | AL41: 4.7 | AM41: 5.3 | AN41: 6 | AO41: 7 | AP41: 7 | AQ41: 7.5 | AR41: 9.2 | AS41: 8.3 | AT41: Ranked 1st | AU41: 10 | AV41: 10 | AW41: 10 | AX41: 10 | AY41: 9 | AZ41: 10 | BA41: 9 | BB41: 10 | BC41: 10 | BD41: 10 | BE41: 9 | BF41: 10 | BG41: 10 | BH41: 10 | BI41: 10 | BJ41: 10
A42: IND01936 | B42: IND01936 | C42: Arbitration | D42: Photos/Dheeraj-Nair-profile-picture-1200x432.jpg | E42: Dheeraj Nair | F42: Dheeraj Nair's RISE instruction metrics reflect high volume across complex mandates, concentrated in private equity shareholders' disputes, and technically complex arbitrations in infrastructure, oil and gas sectors. These span international, domestic, institutional, and ad hoc proceedings alongside white collar and insolvency work. A standout matter involved defending three major PE investors against an emergency SIAC injunction application, where he not only resisted the order but secured one against the counterparty. He focuses on identifying settlement windows early and delivering outcomes quickly, qualities reflected in his strong RISE Experience metrics. | G42: Delhi | H42: Partner | I42: JSA Advocates & Solicitors | J42: 5.9 | L42: 18 | M42: 3.9 | N42: 3.6 | P42: 4.3 | Q42: 1 | R42: 0 | S42: 7.1 | T42: 5.1 | U42: 6.3 | V42: 7.2 | W42: 8.9 | X42: 7.6 | Y42: 7.8 | AA42: 8.9 | AB42: 7.6 | AC42: 6.6 | AD42: 7.5 | AE42: 7.3 | AF42: 7.4 | AG42: 7.9 | AH42: 8.7 | AI42: 6.3 | AJ42: 7.1 | AL42: 4.7 | AM42: 6.7 | AN42: 6 | AO42: 6 | AP42: 8 | AQ42: 7.5 | AR42: 8.5 | AS42: 8.3 | AT42: Top 10 | AU42: 10 | AV42: 10 | AW42: 10 | AX42: 10 | AY42: 10 | AZ42: 10 | BA42: 10 | BB42: 10 | BC42: 10 | BD42: 10 | BE42: 10 | BF42: 10 | BG42: 10 | BH42: 10 | BI42: 10 | BJ42: 10
A43: IND00314 | B43: IND00314 | C43: Competition | D43: Photos/Dhruv-Rajain.png | E43: Dhruv Rajain | F43: Dhruv Rajain at Cyril Amarchand Mangaldas scores most strongly on RISE Instruction metrics, a profile that fits a hands-on merger control practitioner whose value lies in skilled regulatory navigation and technical filing work. His deal exposure spans healthcare, financial services, data centres, paper and pulp, and infrastructure. Notable matters include a data centre transaction, understood to be the first CCI review of that market with conditions imposed, and an ITC-related paper and pulp filing requiring close market analysis in a concentrated sector. A roads and infrastructure matter in which the team persuaded the CCI to extend post-facto treatment to a unit acquisition structure in a novel way adds a first-instance dimension to his instruction profile. His RISE Sophistication metrics are also strong, particularly in pricing, where he adopts a flexible approach combining hourly and fixed-fee models depending on the mandate. He places particular weight on understanding the combinations division’s internal processes and maintaining working relationships with the review team. | G43: Delhi | H43: Partner | I43: Cyril Amarchand Mangaldas | J43: 6.7 | L43: 25 | M43: 5.4 | N43: 5.6 | P43: 4.9 | Q43: 4.1 | R43: 5.1 | S43: 7.5 | T43: 5.9 | U43: 5.9 | V43: 7.5 | W43: 8.3 | X43: 8 | Y43: 8.4 | AA43: 7.8 | AB43: 7.4 | AC43: - | AD43: 0 | AE43: 9.6 | AF43: 9.5 | AG43: 7 | AH43: 8.5 | AI43: 6.7 | AJ43: 6.7 | AL43: 6.7 | AM43: 6.7 | AN43: 8 | AO43: 7 | AP43: 6 | AQ43: 7.5 | AR43: 7.4 | AS43: 8.5 | AU43: 10 | AV43: 10 | AW43: 8 | AX43: 10 | AY43: 8 | AZ43: 10 | BA43: 10 | BB43: 10 | BC43: 8 | BD43: 10 | BE43: 8 | BF43: 10 | BG43: 8 | BH43: 10 | BI43: 8 | BJ43: 10
A44: IND01046 | B44: IND01046 | C44: Capital Markets - Equity | D44: Photos/Vishnu Dutt.jpg | E44: Vishnu Dutt U | F44: Dutt has an integrated securities law practice, and deep understanding of how SEBI and SAT will rule on certain matters, enhancing the quality of her diligence and disclosures for clients. Her highest RISE metric was in Instructions. Key clients include mid-sized investment banks such as Ecmoris, MK Capital, IIFL, Centrum, Dam Capital, and Motilal Oswal, with Motilal Oswal and IIFL gaining a lion's share of medium-sized deals (in the 500–1,000 crore range) over the last 18 months. Dutt’s other high-scoring sub indicator was in the development of junior lawyers. Training extends beyond capital markets, reflecting the firm's philosophy of "holistic lawyering". For example, capital markets lawyers review banking laws and attend sessions on labour codes and the new Securities Market Code. Dutt emphasises that capital markets is a practical discipline with a steep learning curve in the first 12–18 months. The firm consciously ensures that juniors understand the rationale behind templates rather than simply relying on precedent-driven drafting. Significant recent matters included a CNC manufacturer IPO notable for its high-profile client list including Apple, Ferrari, Rolls Royce, Sukhoi, Dassault, and defence manufacturers. | G44: Mumbai | H44: Partner | I44: Bharucha & Partners | J44: 5.7 | L44: 28 | M44: 3 | N44: 4.9 | P44: 0 | Q44: 3.2 | R44: 5.3 | S44: 6 | T44: 7.3 | U44: 6.8 | V44: 8.7 | W44: 8.5 | X44: 7.8 | Y44: 8.2 | AA44: 7.9 | AB44: 7.3 | AC44: 7.6 | AD44: 8.6 | AE44: 8.8 | AF44: 9.4 | AG44: 7.5 | AH44: 8.2 | AI44: 6.6 | AJ44: 7.1 | AL44: 6 | AM44: 7.3 | AN44: 5 | AO44: 7 | AP44: 8 | AQ44: 8 | AR44: 9.5 | AS44: 8.5 | AT44: Top 5 | AU44: 10 | AV44: 10 | AW44: 10 | AX44: 10 | AY44: 10 | AZ44: 10 | BA44: 10 | BB44: 10 | BC44: 10 | BD44: 10 | BE44: 10 | BF44: 10 | BG44: 10 | BH44: 10 | BI44: 10 | BJ44: 10
A45: IND01943 | B45: IND01943 | C45: Competition | D45: Photos/Ela-Bali-profile-picture-1200x432.jpg | E45: Ela Bali | F45: Ela Bali’s achieves an exceptionally high RISE sophistication score that distinguishes her within the cohort. This standing is driven by a prestigious client roster and her involvement in highly complex, contentious mandates. She represents global investors and corporations, including Temasek, EQT, Hyundai, Ford Motor Company, Alpha Wave Global, and IHC Abu Dhabi. A standout example of her high-value work is the Temasek and Alpha Wave investment in Haldiram’s, one of the largest transactions in India’s FMCG sector. Her practice is split evenly between merger control and enforcement, with notable instructions including the MakeMyTrip-Oyo MFN matter and the Hyundai spare parts aftermarket litigation. Bali’s Sophistication score is her second-strongest metric, reflecting her expert use of AI tools for research and document summarization alongside JSA’s internal knowledge management systems. While she remains a high achiever in terms of mandate complexity and volume, her Reputation score reflects a distinctily more moderate public presencm with only some profile across legal directories. | G45: Delhi | H45: Partner | I45: JSA Advocates & Solicitors | J45: 5.6 | L45: 33 | M45: 1.7 | N45: 5.6 | P45: 0 | Q45: 4.1 | R45: 6.8 | S45: 7.5 | T45: 0 | U45: 5.9 | V45: 7.6 | W45: 8.3 | X45: 9.3 | Y45: 8.4 | Z45: Top 5 | AA45: 8.6 | AB45: 7.4 | AC45: - | AD45: 0 | AE45: 9.6 | AF45: 9.5 | AG45: 9.5 | AH45: 8.5 | AI45: 6.1 | AJ45: 6.7 | AL45: 5.3 | AM45: 6.7 | AN45: 6 | AO45: 7 | AP45: 7 | AQ45: 7.5 | AR45: - | AS45: 8.5 | AU45: - | AV45: 10 | AW45: - | AX45: 10 | AY45: - | AZ45: 10 | BA45: - | BB45: 10 | BC45: - | BD45: 10 | BE45: - | BF45: 10 | BG45: - | BH45: 10 | BI45: - | BJ45: 10
A46: IND00929 | B46: IND00929 | C46: Arbitration | D46: Photos/SameerTapia.JPG | E46: Sameer Tapia | F46: Founder and senior partner of ALMT Legal, Sameer Tapia's RISE instruction metrics are his strongest, driven by a client base of European, American, and Far Eastern multinationals alongside large Indian conglomerates, most of whom mandate him directly against Tier 1 Indian firms. Reputation scores follow closely, built less through directory recognition than through an active presence in the business press and a social media profile that keeps him visible well beyond the legal market. The firm's UK roots and seats across London, Singapore, and Dubai reflect a practice that has been cross-border in character from the outset. He uses AI for case law research only, treating it as a probability tool rather than a substitute for commercial judgement. He frames junior development around the distinction between grinders, minders, and finders as a map for career progression. | G46: Mumbai | H46: Founder & Senior Partner | I46: ALMT Legal | J46: 5.7 | L46: 22 | M46: 3.1 | N46: 3.6 | P46: 0 | Q46: 1 | R46: 5.3 | S46: 7.1 | T46: 7.4 | U46: 6.3 | V46: 9.4 | W46: 8.9 | X46: 8.7 | Y46: 7.8 | Z46: Top 5 | AA46: 0 | AB46: 7.6 | AC46: 0 | AD46: 7.5 | AE46: 8.7 | AF46: 7.4 | AG46: 0 | AH46: 8.7 | AI46: 5.1 | AJ46: 7.1 | AL46: 4.7 | AM46: 6.7 | AN46: 6 | AO46: 6 | AP46: 5 | AQ46: 7.5 | AR46: - | AS46: 8.3 | AU46: - | AV46: 10 | AW46: - | AX46: 10 | AY46: - | AZ46: 10 | BA46: - | BB46: 10 | BC46: - | BD46: 10 | BE46: - | BF46: 10 | BG46: - | BH46: 10 | BI46: - | BJ46: 10
A47: IND02909 | B47: IND02909 | C47: Competition | D47: Photos/Gaurav-Desai.png | E47: Gaurav Desai | F47: Gaurav Desai’s highest RISE metrics are in Experience, driven by a practice where clients value his grounded, operational approach to mandates. His Instructions score is equally robust, reflecting a portfolio of work for sovereign wealth funds, leading automotive manufacturers, and major financial institutions, including Fairfax and HDFC Capital Advisors. He also regularly advises global conglomerates such as Johnson & Johnson. Desai splits his practice between corporate M&A and competition law, with a primary focus on merger control. He differentiates himself through his practical analysis of India's deal value thresholds; he notes that while these were designed for digital and asset-light transactions, they are increasingly capturing traditional brick-and-mortar sectors in ways the CCI did not fully anticipate. This sophisticated regulatory reading is shaped by his direct involvement in live filing activity rather than surface-level observation. While his profile remains understated relative to some peers, his work reflects a practitioner deeply embedded in the operational reality of Indian merger control and high-stakes transactional strategy. | G47: Delhi | H47: Partner | I47: Touchstone Partners | J47: 5.3 | L47: 36 | M47: 2.2 | N47: 5.6 | P47: 0 | Q47: 4.1 | R47: 5.1 | S47: 7.5 | T47: 3.6 | U47: 5.9 | V47: 6.9 | W47: 8.3 | X47: 7.6 | Y47: 8.4 | AA47: 6.9 | AB47: 7.4 | AC47: - | AD47: 0 | AE47: 7.7 | AF47: 9.5 | AG47: 7 | AH47: 8.5 | AI47: 6.7 | AJ47: 6.7 | AL47: 6.7 | AM47: 6.7 | AN47: 6 | AO47: 7 | AP47: - | AQ47: 7.5 | AR47: 8.1 | AS47: 8.5 | AU47: 10 | AV47: 10 | AW47: 10 | AX47: 10 | AY47: 8 | AZ47: 10 | BA47: 10 | BB47: 10 | BC47: 10 | BD47: 10 | BE47: 8 | BF47: 10 | BG47: 10 | BH47: 10 | BI47: 10 | BJ47: 10
A48: IND00726 | B48: IND00726 | C48: Competition | D48: Photos/gautam-chawla-1.png | E48: Gautam Chawla | F48: Gautam Chawla at Trilegal is anchored in this RISE competition ranking by the quality and consistency of his client base, with repeat instructions from institutional investors, pension funds, and large asset managers forming the backbone of a practice built on sustained relationships rather than episodic mandates. His practice runs approximately 55 to 60% merger control, with enforcement forming the remainder. He favours concise, decision-oriented guidance over hedged legal analysis. AI and technology usage is notable within his RISE sophistication scores, with structured knowledge management systems, precedent databases, and internal regulatory alerts underpinning a model built for reliable, high-throughput delivery. | G48: Delhi | H48: Partner | I48: Trilegal | J48: 6.9 | L48: 21 | M48: 6.3 | N48: 5.6 | P48: 6.1 | Q48: 4.1 | R48: 5.8 | S48: 7.5 | T48: 6.5 | U48: 5.9 | V48: 7.9 | W48: 8.3 | X48: 7.5 | Y48: 8.4 | AA48: 7.1 | AB48: 7.4 | AC48: - | AD48: 0 | AE48: 9.9 | AF48: 9.5 | AG48: 6 | AH48: 8.5 | AI48: 7.1 | AJ48: 6.7 | AL48: 7.3 | AM48: 6.7 | AN48: 7 | AO48: 7 | AP48: 7 | AQ48: 7.5 | AR48: - | AS48: 8.5 | AU48: - | AV48: 10 | AW48: - | AX48: 10 | AY48: - | AZ48: 10 | BA48: - | BB48: 10 | BC48: - | BD48: 10 | BE48: - | BF48: 10 | BG48: - | BH48: 10 | BI48: - | BJ48: 10
A49: IND00090 | B49: IND00090 | C49: Capital Markets - Equity | D49: Photos/Gautham Srinivas web 2025.png | E49: Gautham Srinivas | F49: Gautham Srinivas runs a pure-play ECM practice, covering IPOs, QIPs, and public offerings exclusively, with relationships built around promoters and management teams over the long term. Instruction scores are his strongest RISE metric, with value and client sub-indicators among the highest in this ECM cohort. Srinivas is comfortable working in deals without precedent. For example, Fractal Analytics, which recently listed as one of the world's first AI companies to go public in India, and Aditya Infotech, a $150mn CCTV technology IPO subscribed approximately 100 times. He is committed to his long-term client relationships and not too concerned at only chasing headline transactions at their expense, and keen to build relationships for the practice. | G49: Delhi | H49: Partner | I49: Khaitan & Co | J49: 6.7 | L49: 19 | M49: 4.9 | N49: 4.9 | P49: 3.7 | Q49: 3.2 | R49: 4.7 | S49: 6 | T49: 6.8 | U49: 6.8 | V49: 8.4 | W49: 8.5 | X49: 8.5 | Y49: 8.2 | AA49: 7.3 | AB49: 7.3 | AC49: 9.3 | AD49: 8.6 | AE49: 8.8 | AF49: 9.4 | AG49: 8.2 | AH49: 8.2 | AI49: 6.7 | AJ49: 7.1 | AL49: - | AM49: 7.3 | AN49: - | AO49: 7 | AP49: - | AQ49: 8 | AR49: 8.5 | AS49: 8.5 | AU49: 10 | AV49: 10 | AW49: 10 | AX49: 10 | AY49: 10 | AZ49: 10 | BA49: 10 | BB49: 10 | BC49: 10 | BD49: 10 | BE49: 10 | BF49: 10 | BG49: 10 | BH49: 10 | BI49: 10 | BJ49: 10
A50: IND00245 | B50: IND00245 | C50: Capital Markets - Equity | D50: Photos/Thomas George.png | E50: Thomas George | F50: George's client list says it all. In the Pine Labs IPO, he advised approximately 17 selling shareholders including Peak XV, Mastercard, and PayPal, and his banking relationships span JM Financial, Kotak, ICICI Securities, Citi, Morgan Stanley, JPMorgan, and Goldman Sachs. His RISE strengths are in his instruction scores, where his client base is a standout sub-indicator and in his sophistication scores. His work on the WeWork India and Indicube listings, reveal a sub-specialism in a pocket of the market that has genuine structural complexity. In terms of the sophistication of his practice, his team uses AI for consent checks across financing contracts, diligence verification, and first-pass document review, allowing senior lawyers to focus on higher-value legal work. | G50: Bengaluru | H50: Partner | I50: Khaitan & Co | J50: 5.6 | L50: 31 | M50: 2.7 | N50: 4.9 | P50: 0 | Q50: 3.2 | R50: 5.8 | S50: 6 | T50: 4.7 | U50: 6.8 | V50: 7.9 | W50: 8.5 | X50: 7.7 | Y50: 8.2 | AA50: 6.1 | AB50: 7.3 | AC50: 7.9 | AD50: 8.6 | AE50: 9.7 | AF50: 9.4 | AG50: 7.5 | AH50: 8.2 | AI50: 7.1 | AJ50: 7.1 | AL50: 7.3 | AM50: 7.3 | AN50: 7 | AO50: 7 | AP50: - | AQ50: 8 | AR50: - | AS50: 8.5 | AU50: - | AV50: 10 | AW50: - | AX50: 10 | AY50: - | AZ50: 10 | BA50: - | BB50: 10 | BC50: - | BD50: 10 | BE50: - | BF50: 10 | BG50: - | BH50: 10 | BI50: - | BJ50: 10
A51: IND00323 | B51: IND00323 | C51: Capital Markets - Equity | D51: Photos/Gokul-Rajan-1.png | E51: Gokul Rajan | F51: Gokul Rajan's highest RISE scores are for instructions and experience. In the latter indicator, he has some of the highest scores in the cohort from a top notch client base. He has worked on some of the largest transactions in the Indian market such as the Hyundai IPO at approximately US$3bn, LG India, Zomato, Swiggy and LIC, with Hyundai and LG executed back-to-back. His time with Linklaters, as well as an in-house lawyer at Citi and his M&A work, gives him a big picture approach to managing transactions. | G51: Delhi | H51: Partner - Regional Head Markets Practice (North) | I51: Cyril Amarchand Mangaldas | J51: 6.6 | L51: 20 | M51: 5.1 | N51: 4.9 | P51: 2.7 | Q51: 3.2 | R51: 8.2 | S51: 6 | T51: 7.6 | U51: 6.8 | V51: 7.7 | W51: 8.5 | X51: 8.3 | Y51: 8.2 | AA51: 6.1 | AB51: 7.3 | AC51: 9.2 | AD51: 8.6 | AE51: 9.8 | AF51: 9.4 | AG51: 8 | AH51: 8.2 | AI51: 6.4 | AJ51: 7.1 | AL51: 6 | AM51: 7.3 | AN51: 6 | AO51: 7 | AP51: 7 | AQ51: 8 | AR51: 9.5 | AS51: 8.5 | AT51: Top 5 | AU51: 10 | AV51: 10 | AW51: 10 | AX51: 10 | AY51: 10 | AZ51: 10 | BA51: 10 | BB51: 10 | BC51: 10 | BD51: 10 | BE51: 10 | BF51: 10 | BG51: 10 | BH51: 10 | BI51: 10 | BJ51: 10
A52: IND02631 | B52: IND02631 | C52: Arbitration | D52: Photos/Gunita_Pahwa.jpg | E52: Gunita Pahwa | F52: Gunita Pahwa's RISE instruction scores are her strongest metric, built on a client base concentrated in national ports and state and regional governments. This produces consistently large-ticket mandates and repeat instructions that few infrastructure practitioners outside the top-tier firms can match. Reputation metrics are supported less by directory recognition than by a strong social media presence and regular news coverage, reflecting a market profile built on visibility as much as peer citation. Her practice spans ports, roads, and airports with a dedicated focus on public sector undertakings and government contracts, extending to international proceedings at SIAC, ICC Paris, and Nepal. | G52: Delhi | H52: Joint Managing Partner | I52: S&A Law Offices | J52: 5.9 | L52: 15 | M52: 3.4 | N52: 3.6 | P52: 0 | Q52: 1 | R52: 6.6 | S52: 7.1 | T52: 8.1 | U52: 6.3 | V52: 8.7 | W52: 8.9 | X52: 8.4 | Y52: 7.8 | Z52: Top 10 | AA52: 9.5 | AB52: 7.6 | AC52: 8.5 | AD52: 7.5 | AE52: 9.8 | AF52: 7.4 | AG52: 7.6 | AH52: 8.7 | AI52: 6 | AJ52: 7.1 | AL52: 6 | AM52: 6.7 | AN52: 6 | AO52: 6 | AP52: 6 | AQ52: 7.5 | AR52: - | AS52: 8.3 | AU52: - | AV52: 10 | AW52: - | AX52: 10 | AY52: - | AZ52: 10 | BA52: - | BB52: 10 | BC52: - | BD52: 10 | BE52: - | BF52: 10 | BG52: - | BH52: 10 | BI52: - | BJ52: 10
A53: IND00454 | B53: IND00454 | C53: Competition | D53: Photos/harman-singh-sandhu.png | E53: Harman Singh Sandhu | F53: Harman Singh Sandhu at Shardul Amarchand Mangaldas is the second-ranked practitioner in this RISE competition ranking and one of the founding figures of India's competition law landscape, having helped build the practice before the regime came into force. His RISE reputation metrics reinforce this, with the highest number of peer recommendations in the cohort and a very strong directory presence. Prior experience at the European Commission and Ofcom gives his approach a deeply institutional character, visible in how he frames regulatory strategy and remedies work. His practice spans large strategic domestic and international transactions, phase-two reviews, and remedies-heavy deals across entertainment, mining, cement, steel, chemicals, and infrastructure, alongside cartel and dominance matters for government bodies, domestic conglomerates, and global multinationals. He has been involved in a significant proportion of India's most complex merger control cases since the regime's inception. His enforcement practice is equally deep, encompassing the successful defence of major domestic and multinational enterprises in high-profile cartel and abuse of dominance proceedings across sectors including cement, coal, paints, tyres, and chemicals sectors. Talent development is standout within his RISE sophistication scores, with deliberate delegation and systematic training underpinning a practice built for institutional continuity rather than individual franchise. | G53: Delhi | H53: Partner | I53: Shardul Amarchand Mangaldas & Co | J53: 9 | K53: Ranked 2nd | L53: 2 | M53: 9.3 | N53: 5.6 | O53: Ranked 2nd | P53: 10 | Q53: 4.1 | R53: 9.9 | S53: 7.5 | T53: 7.9 | U53: 5.9 | V53: 7 | W53: 8.3 | X53: 9.1 | Y53: 8.4 | Z53: Top 10 | AA53: 7.4 | AB53: 7.4 | AC53: - | AD53: 0 | AE53: 10 | AF53: 9.5 | AG53: 9.5 | AH53: 8.5 | AI53: 7.9 | AJ53: 6.7 | AK53: Top 10 | AL53: - | AM53: 6.7 | AN53: - | AO53: 7 | AP53: 10 | AQ53: 7.5 | AR53: 7.6 | AS53: 8.5 | AU53: 10 | AV53: 10 | AW53: 10 | AX53: 10 | AY53: 8 | AZ53: 10 | BA53: 8 | BB53: 10 | BC53: 10 | BD53: 10 | BE53: 8 | BF53: 10 | BG53: 8 | BH53: 10 | BI53: 8 | BJ53: 10
A54: IND00095 | B54: IND00095 | C54: Cyber | D54: Harsh Walia 2023-web.png | E54: Harsh Walia | F54: Harsh Walia spent his early career inside British Telecom and Bharti Airtel before joining Khaitan in 2011, and that in-house background shapes a practice where telecom and technology regulations increasingly overlap. His instruction score is his strongest RISE metric, acting for large Indian and International clients on telecom licensing, AI and privacy governance, cross-border data flows, fintech regulation, and cybersecurity incident response. He has a good understanding of government and regulators having participated in closed-door drafting sessions for the DPDP Act. His high sophistication of practice RISE score draws on advanced use of technology, including the firm's proprietary AI and precedent systems. His most characteristic mandates involve advising on matters involving privacy issues, OTT, cloud telephony and emerging technologies such as digital payments and AI ransomware attacks where the legal problem is not just the breach but the payment, navigating FEMA, RBI, IPC, and CrPC simultaneously while advising clients through high pressure and urgent situations. | G54: Delhi | H54: Partner | I54: Khaitan & Co | J54: 5.9 | L54: 13 | M54: 3.9 | N54: 3.75 | O54: Top 10 | P54: 0 | Q54: 0 | R54: 8.2 | S54: 7.1 | T54: 9.4 | U54: 8 | V54: 8.2 | W54: 8.3 | X54: 7.5 | Y54: 8 | AA54: 7.4 | AB54: 7.6 | AC54: - | AD54: 0 | AE54: 8.5 | AF54: 8.8 | AG54: 7 | AH54: 7.5 | AI54: 6.7 | AJ54: 6.7 | AL54: 7.3 | AM54: 6.7 | AN54: 7 | AO54: 7 | AP54: 6 | AQ54: 6 | AR54: - | AS54: 8.5 | AU54: - | AV54: 10 | AW54: - | AX54: 10 | AY54: - | AZ54: 10 | BA54: - | BB54: 10 | BC54: - | BD54: 10 | BE54: - | BF54: 10 | BG54: - | BH54: 10 | BI54: - | BJ54: 10
A55: IND00455 | B55: IND00455 | C55: Cyber | D55: Hemant Krishna.png | E55: Hemant Krishna | F55: Hemant Krishna joined SAM in 2023, after working in technology practices at other leading law firms and a stint as a legal tech entrepreneur. He receives the second highest score on the RISE sophistication of practice metric, as one of the most tech-savvy practitioners in this list. Krishna was part of the team at SAM which led the evaluation and roll-out of legal AI tool Harvey. He was involved in digital transformation projects at previous firms as well, and says he now "uses AI as regularly as email but always with critical distance and deliberate skepticism." His TMT transactional and regulatory practice has a significant focus on tech sector M&A, and Krishna also handles data and cyber advisory work as part of these larger client mandates. | G55: Bengaluru | H55: Partner | I55: Shardul Amarchand Mangaldas & Co | J55: 5.8 | L55: 15 | M55: 3.1 | N55: 3.75 | P55: 0 | Q55: 0 | R55: 5.3 | S55: 7.1 | T55: 8 | U55: 8 | V55: 8.5 | W55: 8.3 | X55: 6.1 | Y55: 8 | AA55: 5.9 | AB55: 7.6 | AC55: - | AD55: 0 | AE55: 8.7 | AF55: 8.8 | AG55: 5 | AH55: 7.5 | AI55: 8.2 | AJ55: 6.7 | AK55: Ranked 2nd | AL55: 10 | AM55: 6.7 | AN55: 7 | AO55: 7 | AP55: - | AQ55: 6 | AR55: - | AS55: 8.5 | AU55: - | AV55: 10 | AW55: - | AX55: 10 | AY55: - | AZ55: 10 | BA55: - | BB55: 10 | BC55: - | BD55: 10 | BE55: - | BF55: 10 | BG55: - | BH55: 10 | BI55: - | BJ55: 10
A56: IND00456 | B56: IND00456 | C56: Arbitration | D56: Photos/ila-kapur.png | E56: Ila Kapoor | F56: Ila Kapoor’s RISE Reputation metric places her among the leading practitioners in this cohort, with strong Instruction scores reflecting her consistent role on high-value disputes. Her practice is increasingly focused on private equity matters, where she advises foreign PE firms and Indian promoters on exit and post-acquisition claims, alongside a steady flow of hospitality arbitrations. She also handles construction disputes with international counterparties and multi-jurisdictional commercial arbitrations. She trained in the US and conducts her own advocacy rather than routinely briefing senior counsel, supporting her cross-border approach. | G56: Delhi | H56: Partner | I56: Shardul Amarchand Mangaldas & Co | J56: 7.6 | K56: Top 10 | L56: 7 | M56: 7.4 | N56: 3.6 | O56: Top 10 | P56: 6.4 | Q56: 1 | R56: 9.2 | S56: 7.1 | T56: 7.8 | U56: 6.3 | V56: 8.4 | W56: 8.9 | X56: 8.3 | Y56: 7.8 | Z56: Top 10 | AA56: 8.7 | AB56: 7.6 | AC56: 5.9 | AD56: 7.5 | AE56: 9.4 | AF56: 7.4 | AG56: 9.2 | AH56: 8.7 | AI56: 6.7 | AJ56: 7.1 | AL56: 5.3 | AM56: 6.7 | AN56: 7 | AO56: 6 | AP56: 8 | AQ56: 7.5 | AR56: - | AS56: 8.3 | AU56: - | AV56: 10 | AW56: - | AX56: 10 | AY56: - | AZ56: 10 | BA56: - | BB56: 10 | BC56: - | BD56: 10 | BE56: - | BF56: 10 | BG56: - | BH56: 10 | BI56: - | BJ56: 10
A57: IND00271 | B57: IND00271 | C57: Capital Markets - Equity | D57: Photos/abhinav-2.png | E57: Abhinav Kumar | F57: In 2024, Abhinav Kumar moved with a senior member team from Cyril Amarchand Mangaldas to build a high quality ECM practice at TT&A. His RISE instruction scores reflect what he has built. Client and deal value scores are particularly strong, showing he has kept a foothold at the upper end of the market with a leaner team. Having watched the deleterious impact of a busy market on lawyers, he keeps a deliberate cap on the number of transactions per associate and invests more heavily in supervision than most of his peers. His standout recent matter is Singtel's sale of shares in Bharti Airtel, acting as the only counsel across two transactions totalling approximately US$2.5bn | G57: Mumbai | H57: Partner | I57: TT&A | J57: 7.8 | K57: Top 10 | L57: 10 | M57: 7.2 | N57: 4.9 | O57: Top 10 | P57: 6.7 | Q57: 3.2 | R57: 8.1 | S57: 6 | T57: 6.7 | U57: 6.8 | V57: 9.3 | W57: 8.5 | X57: 9.1 | Y57: 8.2 | Z57: Top 5 | AA57: 8.4 | AB57: 7.3 | AC57: 9.6 | AD57: 8.6 | AE57: 9.6 | AF57: 9.4 | AG57: 8.8 | AH57: 8.2 | AI57: 6.1 | AJ57: 7.1 | AL57: 5.3 | AM57: 7.3 | AN57: 6 | AO57: 7 | AP57: 7 | AQ57: 8 | AR57: - | AS57: 8.5 | AU57: - | AV57: 10 | AW57: - | AX57: 10 | AY57: - | AZ57: 10 | BA57: - | BB57: 10 | BC57: - | BD57: 10 | BE57: - | BF57: 10 | BG57: - | BH57: 10 | BI57: - | BJ57: 10
A58: IND02635 | B58: IND02635 | C58: Capital Markets - Equity | D58: Photos/Jabarati-Chandra-GS.jpeg | E58: Jabarati Chandra | F58: India's first insurance company IPO, large-scale QIPs, and tech listings including that of Pine Labs are in Jabarati Chandra's bag. This run of transactions gives her high scores for client base and mandate value in this RISE cohort of ECM lawyers. However, her highest RISE metric comes from her Experience scores: her clients really enjoy working with her. She is strong in the tech sector, and feels it is a sector that requires more than execution prowess and one in which she can exert her fairly unique judgement. Chandra is deliberate about building a team that mirrors her approach: one that can both digest regulatory updates, provide practical context and then properly advise clients on what actions to take. | G58: Mumbai | H58: Partner | I58: S&R Associates | J58: 7.4 | L58: 12 | M58: 6 | N58: 4.9 | P58: 4.5 | Q58: 3.2 | R58: 8.1 | S58: 6 | T58: 7 | U58: 6.8 | V58: 8.5 | W58: 8.5 | X58: 8.7 | Y58: 8.2 | AA58: 6.5 | AB58: 7.3 | AC58: 9.5 | AD58: 8.6 | AE58: 10 | AF58: 9.4 | AG58: 8.5 | AH58: 8.2 | AI58: 7.5 | AJ58: 7.1 | AK58: Top 10 | AL58: 7.3 | AM58: 7.3 | AN58: 7 | AO58: 7 | AP58: 8 | AQ58: 8 | AR58: - | AS58: 8.5 | AU58: - | AV58: 10 | AW58: - | AX58: 10 | AY58: - | AZ58: 10 | BA58: - | BB58: 10 | BC58: - | BD58: 10 | BE58: - | BF58: 10 | BG58: - | BH58: 10 | BI58: - | BJ58: 10
A59: IND01705 | B59: IND01705 | C59: Capital Markets - Equity | D59: Photos/Abhiroop-Lahiri-.png | E59: Abhiroop Lahiri | F59: Instruction and experience scores are Abhiroop Lahiri's strongest RISE metrics. He joined CAM from IndusLaw in 2024, with a client base that spans small finance banks including Ujjivan and Jana, PE and VC houses exiting through IPOs, and new-age technology companies. Lahiri'ssocial media presence is a notable sub-indicator, reflecting a market profile that extends beyond transactions. His practice is deliberately broad across issuer, bank, and selling shareholder mandates, and his healthcare work, including the Doctor Agrawal IPO and Niva Bupa representing Bupa UK's exit, illustrates his range. Everstone Capital is a particularly valued client, where he acts as promoter counsel across multiple listings in pharma, QSR, and industrial parks. | G59: Delhi | H59: Partner | I59: Cyril Amarchand Mangaldas | J59: 5.6 | L59: 30 | M59: 2.9 | N59: 4.9 | P59: 0 | Q59: 3.2 | R59: 4.7 | S59: 6 | T59: 6.8 | U59: 6.8 | V59: 9.2 | W59: 8.5 | X59: 7.7 | Y59: 8.2 | AA59: 6.9 | AB59: 7.3 | AC59: 8 | AD59: 8.6 | AE59: 9.4 | AF59: 9.4 | AG59: 7 | AH59: 8.2 | AI59: 6.7 | AJ59: 7.1 | AL59: 6.7 | AM59: 7.3 | AN59: 6 | AO59: 7 | AP59: 7 | AQ59: 8 | AR59: 8.5 | AS59: 8.5 | AU59: 10 | AV59: 10 | AW59: 10 | AX59: 10 | AY59: 10 | AZ59: 10 | BA59: 10 | BB59: 10 | BC59: 10 | BD59: 10 | BE59: 10 | BF59: 10 | BG59: 10 | BH59: 10 | BI59: 10 | BJ59: 10
A60: IND00723 | B60: IND00723 | C60: International Trade | D60: Photos/dhruv-gupta-.png | E60: Dhruv Gupta | F60: International trade experts are rare, and rarer still in India's largest five firms. Dhruv Gupta is an exception to this rule, ranking fourth overall in the RISE ratings and third for the sophistication of his practice. He scores highly in these sophistication RISE metrics for his advanced use of AI tools for data analysis, and a holistic approach to training junior lawyers, which factors in commercial, political and technical training in structured and unstructured sessions. His focus on the steel industry, one of the most litigated and politically sensitive areas of international trade law, gives his practice a distinct sectoral depth. Gupta acts for these clients both at home and abroad, working on cases in the EU and in Brazil since the beginning of 2024, in addition to cases held before domestic forums. | G60: Delhi | H60: Partner | I60: Trilegal | J60: 7.6 | K60: Top 5 | L60: 4 | M60: 6.4 | N60: 3.35 | O60: Top 5 | P60: 5.5 | Q60: 0 | R60: 7.5 | S60: 7.1 | T60: 6.7 | U60: 7.1 | V60: 8.8 | W60: 8.9 | X60: 8.9 | Y60: 8.6 | Z60: Top 10 | AA60: 9.5 | AB60: 8.6 | AC60: - | AD60: 0 | AE60: 8.9 | AF60: 8.9 | AG60: 8.7 | AH60: 8.7 | AI60: 7.5 | AJ60: 6.4 | AK60: Ranked 3rd | AL60: 7.3 | AM60: 5.3 | AN60: 7 | AO60: 7 | AP60: 8 | AQ60: 7.5 | AR60: 7.2 | AS60: 8.3 | AU60: 10 | AV60: 10 | AW60: 6 | AX60: 10 | AY60: 8 | AZ60: 10 | BA60: 8 | BB60: 10 | BC60: 10 | BD60: 10 | BE60: 6 | BF60: 10 | BG60: 8 | BH60: 10 | BI60: 10 | BJ60: 10
A61: IND00732 | B61: IND00732 | C61: Cyber | D61: jaideep-reddy-4.png | E61: Jaideep Reddy | F61: Jaideep Reddy ranks eleventh in the 2026 RISE Cyber rating with strong scores for instructions and on the client experience metrics. His instruction score reflects a practice servicing top-tier clients for legally complex and high stakes work. It includes advising companies and investors on cybersecurity matters, including breach response and crisis management, regulatory reporting, cyber due diligence in transactions, and ongoing compliance and governance. Reddy also scores well within the reputation RISE rating for his strong media profile in news and social media, where he is frequently cited as an expert on crypto. Reddy describes his practice as having a special situations focus, where he often guides clients through regulatory proceedings and crises such as hacking, data breaches and ransom demands. | G61: Bengaluru | H61: Partner | I61: Trilegal | J61: 6.2 | L61: 11 | M61: 3.5 | N61: 3.75 | P61: 0 | Q61: 0 | R61: 7.1 | S61: 7.1 | T61: 8 | U61: 8 | V61: 8.7 | W61: 8.3 | X61: 8.3 | Y61: 8 | Z61: Top 10 | AA61: 7 | AB61: 7.6 | AC61: - | AD61: 0 | AE61: 9.3 | AF61: 8.8 | AG61: 8.5 | AH61: 7.5 | AI61: 7.5 | AJ61: 6.7 | AK61: Top 5 | AL61: 7.3 | AM61: 6.7 | AN61: 9 | AO61: 7 | AP61: - | AQ61: 6 | AR61: 8.5 | AS61: 8.5 | AT61: Top 10 | AU61: 10 | AV61: 10 | AW61: 10 | AX61: 10 | AY61: 10 | AZ61: 10 | BA61: 10 | BB61: 10 | BC61: 10 | BD61: 10 | BE61: 10 | BF61: 10 | BG61: 10 | BH61: 10 | BI61: 10 | BJ61: 10
A62: IND00734 | B62: IND00734 | C62: Cyber | D62: Jyotsna-Web-1-1-1.png | E62: Jyotsna Jayaram | F62: Jyotsna Jayaram ranks fourth in the 2026 RISE Cyber rating, with the equal highest score for the RISE instructions metric. As part of the most often recommended team for cyber advice in India, she has built a strong client bases which spans global technology companies, fintech, banking and financial services, telecom, e-commerce, and manufacturing. She handled a high volume of incident management, regulatory compliance, and DPDP readiness mandates in the past year. Jayaram is particularly tuned into the technical aspects of her clients' products, and gets involved at the very early stages to assist with project development and strategy. Jayaram also scores well on the RISE sophistication metric, and regularly uses a range of advanced technology and AI tools in her work. | G62: Bengaluru | H62: Partner | I62: Trilegal | J62: 7.6 | K62: Top 5 | L62: 4 | M62: 6.9 | N62: 3.75 | O62: Top 10 | P62: 6 | Q62: 0 | R62: 7.8 | S62: 7.1 | T62: 7.7 | U62: 8 | V62: 8.2 | W62: 8.3 | X62: 8.7 | Y62: 8 | Z62: Top 5 | AA62: 9.5 | AB62: 7.6 | AC62: - | AD62: 0 | AE62: 10 | AF62: 8.8 | AG62: 8 | AH62: 7.5 | AI62: 7 | AJ62: 6.7 | AK62: Top 10 | AL62: 8 | AM62: 6.7 | AN62: 7 | AO62: 7 | AP62: 6 | AQ62: 6 | AR62: 8.5 | AS62: 8.5 | AT62: Top 10 | AU62: 10 | AV62: 10 | AW62: 10 | AX62: 10 | AY62: 10 | AZ62: 10 | BA62: 10 | BB62: 10 | BC62: 10 | BD62: 10 | BE62: 10 | BF62: 10 | BG62: 10 | BH62: 10 | BI62: 10 | BJ62: 10
A63: IND00337 | B63: IND00337 | C63: Arbitration | D63: Photos/Kapil Arora - Arb.png | E63: Kapil Arora | F63: Kapil Arora's RISE instruction metrics are built on a concentrated book of repeat international clients in construction and infrastructure arbitration. Clients include Larsen & Toubro, Sembcorp Green Infra and Hellmann Worldwide Logistics, placing him at the higher end of the market for cross-border engineering disputes. Fifteen years of accumulated technical fluency allows him to explain turbine and boiler mechanics to tribunals himself. His Talent Development sub-indiciator is also strong as he gives junior lawyers early exposure to high-stakes advocacy, producing a top-heavy team with negligible attrition. All advocacy and cross-examination is conducted in-house rather than briefing external counsel. | G63: Delhi | H63: Partner | I63: Cyril Amarchand Mangaldas | J63: 6.2 | L63: 13 | M63: 3.6 | N63: 3.6 | P63: 0 | Q63: 1 | R63: 8.7 | S63: 7.1 | T63: 5.8 | U63: 6.3 | V63: 9.7 | W63: 8.9 | X63: 8.2 | Y63: 7.8 | AA63: 6.1 | AB63: 7.6 | AC63: 7 | AD63: 7.5 | AE63: 9.7 | AF63: 7.4 | AG63: 9 | AH63: 8.7 | AI63: 7.6 | AJ63: 7.1 | AK63: Top 10 | AL63: 6.7 | AM63: 6.7 | AN63: - | AO63: 6 | AP63: 9 | AQ63: 7.5 | AR63: - | AS63: 8.3 | AU63: - | AV63: 10 | AW63: - | AX63: 10 | AY63: - | AZ63: 10 | BA63: - | BB63: 10 | BC63: - | BD63: 10 | BE63: - | BF63: 10 | BG63: - | BH63: 10 | BI63: - | BJ63: 10
A64: IND00739 | B64: IND00739 | C64: Arbitration | D64: Photos/Ketan-Gaur.png | E64: Ketan Gaur | F64: Ketan Gaur holds rights of audience before the Singapore International Commercial Court and Court of Appeal, a practical credential that reflects the genuine shape of his practice. His mandates span Singapore, London, Germany, and India, and he routinely handles arbitration alongside the simultaneous enforcement, set-aside, and interim relief proceedings that follow. His RISE instruction score is his strongest metric, with a near-perfect complexity rating, built on a client base that includes sovereign-linked entities alongside multinationals. His RISE experience score is equally notable. He is appointed as arbitrator by Indian constitutional courts in ad hoc proceedings, and he regularly advises general counsel on operational and strategic questions beyond the formal mandate, giving him unusual commercial depth for a partner at his stage. | G64: Delhi | H64: Partner | I64: Trilegal | J64: 5.2 | L64: 27 | M64: 2.6 | N64: 3.6 | P64: 1 | Q64: 1 | R64: 3.2 | S64: 7.1 | T64: 6.6 | U64: 6.3 | V64: 4.4 | W64: 8.9 | X64: 7.5 | Y64: 7.8 | AA64: 7.6 | AB64: 7.6 | AC64: 7.9 | AD64: 7.5 | AE64: 0 | AF64: 7.4 | AG64: 9.8 | AH64: 8.7 | AI64: 5.9 | AJ64: 7.1 | AL64: 6.7 | AM64: 6.7 | AN64: 6 | AO64: 6 | AP64: 5 | AQ64: 7.5 | AR64: 7.9 | AS64: 8.3 | AU64: 10 | AV64: 10 | AW64: 8 | AX64: 10 | AY64: 10 | AZ64: 10 | BA64: 10 | BB64: 10 | BC64: 8 | BD64: 10 | BE64: 8 | BF64: 10 | BG64: 10 | BH64: 10 | BI64: 10 | BJ64: 10
A65: IND00112 | B65: IND00112 | C65: Arbitration | D65: Photos/Kingshuk.png | E65: Kingshuk Banerjee | F65: Kingshuk Banerjee concentrates almost exclusively on arbitration, with 90% of his billable work in the practice. His focus is M&A and shareholder disputes, cross-border private equity investment claims, and a small number of construction, maritime, and defence matters. His RISE instruction score reflects high volume and legal complexity, with a client base that includes a major mining company, Tarini Prasad Mohanty, and Maxis Communications Berhad. His RISE reputation score is built through consistent directory recognition and a strong social media presence rather than purely through peer citation. He handles advocacy in-house rather than briefing external senior counsel, giving clients continuity between strategy and courtroom presentation. What distinguishes him is a tendency toward deep over-preparation, a discipline he credits for consistently producing results rather than treating as inefficiency. | G65: Mumbai | H65: Partner | I65: Khaitan & Co | J65: 6.8 | K65: Top 10 | L65: 9 | M65: 6.1 | N65: 3.6 | O65: Top 10 | P65: 5.2 | Q65: 1 | R65: 7.8 | S65: 7.1 | T65: 5.1 | U65: 6.3 | V65: 9 | W65: 8.9 | X65: 7.8 | Y65: 7.8 | AA65: 8.4 | AB65: 7.6 | AC65: 6.4 | AD65: 7.5 | AE65: 5.9 | AF65: 7.4 | AG65: 9 | AH65: 8.7 | AI65: 6.5 | AJ65: 7.1 | AL65: 7.3 | AM65: 6.7 | AN65: 6 | AO65: 6 | AP65: 6 | AQ65: 7.5 | AR65: 8.3 | AS65: 8.3 | AT65: Top 10 | AU65: 10 | AV65: 10 | AW65: 10 | AX65: 10 | AY65: 10 | AZ65: 10 | BA65: 10 | BB65: 10 | BC65: 10 | BD65: 10 | BE65: 10 | BF65: 10 | BG65: 8 | BH65: 10 | BI65: 10 | BJ65: 10
A66: IND00579 | B66: IND00579 | C66: Capital Markets - Equity | D66: Photos/Lionel-D_Almeida_5789015_1.jpg | E66: Lionel D'Almeida | F66: Lionel D'Almeida has strong market share, as evinced by his instruction scores and a media profile that reflects his role on transactions with public market significance. His client base leans toward private equity and promoter-backed companies, and he advises across the full stakeholder spectrum, acting for issuers, promoters, banks, and PE investors. This breadth allows him nuanced understanding of where transactional tensions are likely to be. Alongside the International Financial Services Authority, he helped shape the regulatory framework for India's GIFT City IFSC. His work at the intersection of practice and policy is useful in a jurisdiction that is still defining its rules. | G66: Mumbai | H66: Senior Partner | I66: AZB & Partners | J66: 6.8 | L66: 18 | M66: 5 | N66: 4.9 | P66: 2.7 | Q66: 3.2 | R66: 7.9 | S66: 6 | T66: 6.7 | U66: 6.8 | V66: 9.1 | W66: 8.5 | X66: 8.7 | Y66: 8.2 | AA66: 7.3 | AB66: 7.3 | AC66: 9.2 | AD66: 8.6 | AE66: 9.8 | AF66: 9.4 | AG66: 8.5 | AH66: 8.2 | AI66: 6.9 | AJ66: 7.1 | AL66: 6.7 | AM66: 7.3 | AN66: 7 | AO66: 7 | AP66: 7 | AQ66: 8 | AR66: - | AS66: 8.5 | AU66: - | AV66: 10 | AW66: - | AX66: 10 | AY66: - | AZ66: 10 | BA66: - | BB66: 10 | BC66: - | BD66: 10 | BE66: - | BF66: 10 | BG66: - | BH66: 10 | BI66: - | BJ66: 10
A67: IND01975 | B67: IND01975 | C67: Capital Markets - Equity | D67: Photos/Madhurima-Mukherjee-profile-picture.jpg | E67: Madhurima Mukherjee (Saha) | F67: Madhurima Mukherjee's reputation score is among the strongest in this RISE cohort, reflecting a career spent building capital markets practices across several of India's leading firms including Amarchand Mangaldas, Luthra and Luthra and AZB. Now at JSA, she is one of India's most experienced practitioners. Naturally, her RISE Instruction score is high, and she handles both a large volume of work that is high in value. Recent work with Google and Microsoft is reflective of her quality practice: both engagements required her team to go well beyond standard legal counsel scope, guiding global corporates through the mechanics of the Indian capital markets process in a way that was closer to a banking advisory role than a legal one. | G67: Delhi | H67: Partner | I67: JSA Advocates & Solicitors | J67: 7 | L67: 15 | M67: 6.9 | N67: 4.9 | P67: 5.9 | Q67: 3.2 | R67: 8.7 | S67: 6 | T67: 7.2 | U67: 6.8 | V67: 9 | W67: 8.5 | X67: 7.7 | Y67: 8.2 | AA67: 9.3 | AB67: 7.3 | AC67: 9.5 | AD67: 8.6 | AE67: 0 | AF67: 9.4 | AG67: 8.2 | AH67: 8.2 | AI67: 5.6 | AJ67: 7.1 | AL67: 4 | AM67: 7.3 | AN67: 6 | AO67: 7 | AP67: - | AQ67: 8 | AR67: - | AS67: 8.5 | AU67: - | AV67: 10 | AW67: - | AX67: 10 | AY67: - | AZ67: 10 | BA67: - | BB67: 10 | BC67: - | BD67: 10 | BE67: - | BF67: 10 | BG67: - | BH67: 10 | BI67: - | BJ67: 10
A68: IND01732 | B68: IND01732 | C68: Capital Markets - Equity | D68: Photos/Manan-Lahoty.jpg | E68: Manan Lahoty | F68: Manan Lahoty heads India's largest capital markets teams by headcount and receives high numbers of peer recognitions. What distinguishes his practice is a combination of pioneering transaction work and a team that handles demanding mandates without the attrition that afflicts comparable practices. Lahoty led India's first reverse flip IPOs, including PhonePe and Groww, alongside Swiggy, Hella Infra, and Vishal Mega Mart, navigating structural challenges with little precedent. His track record for novel transactions, paired with strong reputation and instruction scores, sets him clearly apart. | G68: Mumbai | H68: Partner | I68: Cyril Amarchand Mangaldas | J68: 8.7 | K68: Ranked 2nd | L68: 2 | M68: 9.2 | N68: 4.9 | O68: Ranked 2nd | P68: 9 | Q68: 3.2 | R68: 9.7 | S68: 6 | T68: 8.5 | U68: 6.8 | V68: 10 | W68: 8.5 | X68: 9 | Y68: 8.2 | Z68: Top 10 | AA68: 7.9 | AB68: 7.3 | AC68: 9.8 | AD68: 8.6 | AE68: 7.9 | AF68: 9.4 | AG68: 9.5 | AH68: 8.2 | AI68: 7.2 | AJ68: 7.1 | AL68: 6 | AM68: 7.3 | AN68: 8 | AO68: 7 | AP68: 8 | AQ68: 8 | AR68: 8.5 | AS68: 8.5 | AT68: Top 10 | AU68: 10 | AV68: 10 | AW68: 10 | AX68: 10 | AY68: 10 | AZ68: 10 | BA68: 10 | BB68: 10 | BC68: 10 | BD68: 10 | BE68: 10 | BF68: 10 | BG68: 10 | BH68: 10 | BI68: 10 | BJ68: 10
A69: IND00120 | B69: IND00120 | C69: Capital Markets - Debt | D69: Photos/Manisha Shroff.png | E69: Manisha Shroff | F69: Manisha Shroff at Khaitan & Co receives more peer recommendations than any other practitioner in the DCM list and her RISE Reputation scores are among the strongest in this year's rating. Alongside, her RISE reputation score is reinforced by a media presence and social media following that reflect a market profile built over consistent years at the top end of the market. She leads one of the few purely DCM focused practices in India, a specialism that is genuinely rare given the ECM orientation of most Indian capital markets work. Her instruction record is market leading on volume and value of corporate bond issuances, spanning multiple Vedanta bonds, JSW Steel, airport and infrastructure bonds, and NBFC offshore debt, a sector that has grown significantly as companies seek cheaper international funding. Axis Bank programme updates and recurring infrastructure mandates round out a practice that operates across the full range of Indian corporate debt. | G69: Mumbai | H69: Partner | I69: Khaitan & Co | J69: 8.8 | K69: Ranked 1st | L69: 1 | M69: 9.3 | N69: 4 | O69: Ranked 1st | P69: 10 | Q69: 2.9 | R69: 8.2 | S69: 5.8 | T69: 7.9 | U69: 7.5 | V69: 9.6 | W69: 9.3 | X69: 9.2 | Y69: 8.4 | Z69: Ranked 2nd | AA69: 10 | AB69: 8.5 | AC69: 10 | AD69: 7.9 | AE69: 8.8 | AF69: 8.8 | AG69: 8.8 | AH69: 8.7 | AI69: 7.1 | AJ69: 6.6 | AK69: Top 5 | AL69: 7.3 | AM69: 6.7 | AN69: - | AO69: 6 | AP69: - | AQ69: 7 | AR69: 9.4 | AS69: 8.7 | AT69: Ranked 2nd | AU69: 8.6 | AV69: 9.6 | AW69: 9.4 | AX69: 10 | AY69: 9.4 | AZ69: 10 | BA69: 10 | BB69: 10 | BC69: 10 | BD69: 10 | BE69: 8.6 | BF69: 10 | BG69: 8.6 | BH69: 10 | BI69: 9.4 | BJ69: 9.6
A70: IND02739 | B70: IND02739 | C70: Arbitration | D70: Photos/Manmeet Singh.png | E70: Manmeet Singh | F70: Manmeet Singh joined Cyril Amarchand Mangaldas in December 2024 from Saraf and Partners, bringing a practice concentrated in high-value infrastructure and construction disputes for Indian conglomerates, private equity platforms, and energy companies. His RISE instruction scores reflect a preference for complex, high-ticket matters over volume, with six to seven arbitrations a year each typically involving multiple expert workstreams across delay, quantum, and technical disciplines. His RISE sophistication score is equally strong, underpinned by two habits that are more systematic than most. His team uses AI daily for document review, bundle summarisation, and cross-examination preparation, and he tracks court judgements closely to monitor the evolution of arbitration and contract law in India, feeding that analysis directly into how he builds legal arguments. What sets him apart is the investment he makes in anticipatory strategy, modelling how opposing counsel will frame a set of facts and how a tribunal is likely to read them before a hearing stage is reached. | G70: Delhi | H70: Partner | I70: Cyril Amarchand Mangaldas | J70: 5.8 | L70: 19 | M70: 2.7 | N70: 3.6 | P70: 1 | Q70: 1 | R70: 6 | S70: 7.1 | T70: 0 | U70: 6.3 | V70: 9.7 | W70: 8.9 | X70: 8.1 | Y70: 7.8 | AA70: 5.5 | AB70: 7.6 | AC70: 9 | AD70: 7.5 | AE70: 8.7 | AF70: 7.4 | AG70: 8.2 | AH70: 8.7 | AI70: 7.5 | AJ70: 7.1 | AK70: Top 10 | AL70: 7.3 | AM70: 6.7 | AN70: 7 | AO70: 6 | AP70: 8 | AQ70: 7.5 | AR70: 8.5 | AS70: 8.3 | AT70: Top 10 | AU70: 10 | AV70: 10 | AW70: 10 | AX70: 10 | AY70: 10 | AZ70: 10 | BA70: 10 | BB70: 10 | BC70: 10 | BD70: 10 | BE70: 10 | BF70: 10 | BG70: 10 | BH70: 10 | BI70: 10 | BJ70: 10
A71: IND03226 | B71: IND03226 | C71: Cyber | D71: Mathew Chacko.jpg | E71: Mathew Chacko | F71: Mathew Chacko receives the second highest reputation score in this RISE cyber cohort, and leads one of the busiest data protection practices in Asia. His boutique firm advises around 100 Nasdaq companies. He was the second most mentioned lawyer by peers, and receives a top score for his social media presence, alongside high scores for profile in directories and news media. His instruction score follows closely, built a client base spanning international and domestic banks, global insurers, and technology multinationals. While his team handled 59 cyber incidents in 2025, it is the complexity of the high-stakes regulatory and strategic mandates he personally leads that makes his practice stand out. | G71: Bengaluru | H71: Founding Partner | I71: Spice Route Legal | J71: 8 | K71: Ranked 2nd | L71: 2 | M71: 8.1 | N71: 3.75 | O71: Ranked 2nd | P71: 7.5 | Q71: 0 | R71: 9.2 | S71: 7.1 | T71: 7.9 | U71: 8 | V71: 10 | W71: 8.3 | X71: 8.7 | Y71: 8 | Z71: Top 5 | AA71: 7.5 | AB71: 7.6 | AC71: - | AD71: 0 | AE71: 10 | AF71: 8.8 | AG71: 8.5 | AH71: 7.5 | AI71: 6.3 | AJ71: 6.7 | AL71: 4.7 | AM71: 6.7 | AN71: 8 | AO71: 7 | AP71: - | AQ71: 6 | AR71: - | AS71: 8.5 | AU71: - | AV71: 10 | AW71: - | AX71: 10 | AY71: - | AZ71: 10 | BA71: - | BB71: 10 | BC71: - | BD71: 10 | BE71: - | BF71: 10 | BG71: - | BH71: 10 | BI71: - | BJ71: 10
A72: IND00121 | B72: IND00121 | C72: International Trade | D72: Photos/Mayank Jain.png | E72: Mayank Jain | F72: Mayank Jain at Khaitan & Co leads a trade practice anchored in customs work across a range of industry sectors, supplemented by trade remedy matters and a developing policy advocacy capability, having joined from trade and tax specialists Lakshmikumaran & Sridharan. His closest client relationship is with steel giant Jindal Stainless, and a recent standout matter saw him secure a zero duty margin for a Chinese steel exporter in an anti-dumping investigation before the DGTR, the only exporter in the proceedings to achieve that outcome. Jain provided comments to multiple articles in business publications in 2025 on trade matters, and scores highly in the RISE news media metric for his public profile. | G72: Mumbai | H72: Partner | I72: Khaitan & Co | J72: 5.3 | L72: 12 | M72: 2.2 | N72: 3.35 | P72: 0 | Q72: 0 | R72: 0 | S72: 7.1 | T72: 9 | U72: 7.1 | V72: 8.2 | W72: 8.9 | X72: 7.8 | Y72: 8.6 | AA72: 7.9 | AB72: 8.6 | AC72: - | AD72: 0 | AE72: 8.8 | AF72: 8.9 | AG72: 7.5 | AH72: 8.7 | AI72: 6.6 | AJ72: 6.4 | AK72: Top 10 | AL72: 6 | AM72: 5.3 | AN72: 7 | AO72: 7 | AP72: - | AQ72: 7.5 | AR72: 8.5 | AS72: 8.3 | AT72: Top 5 | AU72: 10 | AV72: 10 | AW72: 10 | AX72: 10 | AY72: 10 | AZ72: 10 | BA72: 10 | BB72: 10 | BC72: 10 | BD72: 10 | BE72: 10 | BF72: 10 | BG72: 10 | BH72: 10 | BI72: 10 | BJ72: 10
A73: IND00229 | B73: IND00229 | C73: Capital Markets - Equity | D73: Photos/Sudghir Bassi.png | E73: Sudhir Bassi | F73: Membership of SEBI's Primary Market Advisory Committee gives Sudhir Bassi a direct line into regulatory policy. His work on ESOP grandfathering rules for founders reclassified as promoters is a concrete example of that influence translating into outcomes for clients. Instruction and experience scores are his strongest RISE metrics, with client base and complexity the standout sub-indicators. His practice focuses on multinational subsidiaries seeking Indian listings and mature PE-backed companies, a client profile that tends to generate structurally demanding work. Blackstone is a named repeat client, which gives his team a rounded experience and Bassi has a steady pipeline of deals in the $300mn to $800mn range. | G73: Mumbai | H73: Executive Director | I73: Khaitan & Co | J73: 6.9 | L73: 17 | M73: 5.1 | N73: 4.9 | P73: 5.9 | Q73: 3.2 | R73: 5.3 | S73: 6 | T73: 0 | U73: 6.8 | V73: 8.2 | W73: 8.5 | X73: 8.4 | Y73: 8.2 | AA73: 7.5 | AB73: 7.3 | AC73: 8.4 | AD73: 8.6 | AE73: 8.7 | AF73: 9.4 | AG73: 9 | AH73: 8.2 | AI73: 7.3 | AJ73: 7.1 | AL73: 7.3 | AM73: 7.3 | AN73: 8 | AO73: 7 | AP73: 7 | AQ73: 8 | AR73: 8.5 | AS73: 8.5 | AU73: 10 | AV73: 10 | AW73: 10 | AX73: 10 | AY73: 10 | AZ73: 10 | BA73: 10 | BB73: 10 | BC73: 10 | BD73: 10 | BE73: 10 | BF73: 10 | BG73: 10 | BH73: 10 | BI73: 10 | BJ73: 10
A74: IND01738 | B74: IND01738 | C74: Cyber | D74: Namita Viswanathan.webp | E74: Namita Viswanath | F74: Namita Viswanath's sophistication score is her strongest RISE metric, reflecting a technology-driven practice where she has access to leading legal AI tools and works on flexible and data-driven pricing models. Viswanath also advises clients on using legal AI tools within their in-house legal teams, ensuring compliant and safe storage and sharing of data. Her RISE instruction score reflects a high-volume, cross-sector practice spanning global technology companies, financial services, insurance, healthcare, and crypto clients. Recent work includes DPDP readiness programmes that require rebuilding privacy frameworks from the ground up. She describes her differentiating quality as positioning: sophisticated clients will have already read the law, and so the value she adds is increasingly strategic. She trains the junior members of her team to also think as business enablers not just legal advisers. | G74: Bengaluru | H74: Partner | I74: CMS INDUSLAW | J74: 5.1 | L74: 18 | M74: 3.6 | N74: 3.75 | P74: 0 | Q74: 0 | R74: 8.7 | S74: 7.1 | T74: 7.1 | U74: 8 | V74: 8 | W74: 8.3 | X74: 5.9 | Y74: 8 | AA74: 8 | AB74: 7.6 | AC74: - | AD74: 0 | AE74: 4.8 | AF74: 8.8 | AG74: 5.5 | AH74: 7.5 | AI74: 6.5 | AJ74: 6.7 | AL74: 7.3 | AM74: 6.7 | AN74: 8 | AO74: 7 | AP74: 5 | AQ74: 6 | AR74: - | AS74: 8.5 | AU74: - | AV74: 10 | AW74: - | AX74: 10 | AY74: - | AZ74: 10 | BA74: - | BB74: 10 | BC74: - | BD74: 10 | BE74: - | BF74: 10 | BG74: - | BH74: 10 | BI74: - | BJ74: 10
A75: IND01508 | B75: IND01508 | C75: Arbitration | D75: Photos/Naresh Thacker.jpg | E75: Naresh Thacker | F75: Naresh Thacker established his own chambers in 2025 after 17 years in arbitration, most of them at Economic Laws Practice where he built the disputes practice from a base in regulatory and tax work. His RISE instruction score is his strongest metric, running 11 to 12 matters a year at the higher end of ticket size, weighted toward technically demanding construction, dredging, and freight corridor disputes alongside shareholder work. His client base spans both direct corporate instructions and law firms that brief him as counsel. What distinguishes him for instructing firms is a fluency in translating legal strategy into communication that reaches client management directly, something he attributes to having spent over a decade operating inside a law firm before moving to independent practice. | G75: Mumbai | H75: Counsel | I75: Chambers of Naresh Thacker | J75: 6.4 | L75: 12 | M75: 6 | N75: 3.6 | O75: Top 10 | P75: 4.3 | Q75: 1 | R75: 7.5 | S75: 7.1 | T75: 8 | U75: 6.3 | V75: 9.1 | W75: 8.9 | X75: 7 | Y75: 7.8 | AA75: 6.9 | AB75: 7.6 | AC75: 8.3 | AD75: 7.5 | AE75: 4.7 | AF75: 7.4 | AG75: 7 | AH75: 8.7 | AI75: 5.9 | AJ75: 7.1 | AL75: 5.3 | AM75: 6.7 | AN75: 7 | AO75: 6 | AP75: 6 | AQ75: 7.5 | AR75: 8.3 | AS75: 8.3 | AT75: Top 10 | AU75: 10 | AV75: 10 | AW75: 8 | AX75: 10 | AY75: 10 | AZ75: 10 | BA75: 10 | BB75: 10 | BC75: 10 | BD75: 10 | BE75: 10 | BF75: 10 | BG75: 10 | BH75: 10 | BI75: 10 | BJ75: 10
A76: IND00490 | B76: IND00490 | C76: Competition | D76: Photos/naval-chopra.png | E76: Naval Satarawala Chopra | F76: Naval Satarawala Chopra at Shardul Amarchand Mangaldas scores most strongly on RISE sophistication metrics. He has shaped one of the most deliberately architected competition practices in India, with shared leadership, practice-wide revenue targets, and capacity-based staffing reflecting a deliberate choice to build a durable institution rather than a personal franchise. AI usage is a standout within those scores, extending beyond summarisation into stress-testing theories of harm, custom workflow-building, and integrated knowledge management. His practice covers merger control, cartel investigations, and abuse of dominance, with a recent uptick in cartel matters alongside consistent merger control and behavioural work. Instructions skew international and cross-border, benchmarked against elite global competition teams rather than purely domestic peers. He estimates roughly half his time now goes to practice and firm management, a split that reinforces the institutional character of his profile. | G76: Delhi | H76: Partner | I76: Shardul Amarchand Mangaldas & Co | J76: 7.7 | L76: 11 | M76: 6.9 | N76: 5.6 | P76: 6.1 | Q76: 4.1 | R76: 8.3 | S76: 7.5 | T76: 6.9 | U76: 5.9 | V76: 8.7 | W76: 8.3 | X76: 8.2 | Y76: 8.4 | AA76: 7.4 | AB76: 7.4 | AC76: - | AD76: 0 | AE76: 8.3 | AF76: 9.5 | AG76: 8.5 | AH76: 8.5 | AI76: 8.3 | AJ76: 6.7 | AK76: Top 5 | AL76: 9.3 | AM76: 6.7 | AN76: 7 | AO76: 7 | AP76: 8 | AQ76: 7.5 | AR76: - | AS76: 8.5 | AU76: - | AV76: 10 | AW76: - | AX76: 10 | AY76: - | AZ76: 10 | BA76: - | BB76: 10 | BC76: - | BD76: 10 | BE76: - | BF76: 10 | BG76: - | BH76: 10 | BI76: - | BJ76: 10
A77: IND02231 | B77: IND02231 | C77: Competition | D77: Photos/Neelambera Sandeepan.jpg | E77: Neelambera Sandeepan | F77: Neelambera Sandeepan at Lakshmikumaran & Sridharan scores most notably on RISE instruction metrics, with clients and complexity the standout indicators. Her mandates reflect increasing complexity driven by procedural challenges, multi-forum litigation, and cross-border coordination, often producing outcomes with broader implications for regulatory process and enforcement. Her work is focused on regulated and technology-driven sectors, where competition issues arise across both transactions and ongoing enforcement and compliance matters. Talent development is notable within her RISE sophistication scores. Associates spend time across practice areas, supported by internal knowledge sharing and input from economists and international practitioners, with conference attendance and certifications actively encouraged. She takes a holistic view of client mandates, understanding how the overall business operates rather than advising on the law alone, and focuses on finding solutions that are workable across the entire business rather than creating regulatory roadblocks. | G77: Delhi | H77: Partner | I77: Lakshmikumaran & Sridharan | J77: 5.3 | L77: 35 | M77: 2.6 | N77: 5.6 | P77: 0 | Q77: 4.1 | R77: 4.2 | S77: 7.5 | T77: 6 | U77: 5.9 | V77: 8.2 | W77: 8.3 | X77: 7.6 | Y77: 8.4 | AA77: 5.8 | AB77: 7.4 | AC77: - | AD77: 0 | AE77: 9.1 | AF77: 9.5 | AG77: 7.5 | AH77: 8.5 | AI77: 6.3 | AJ77: 6.7 | AL77: 4.7 | AM77: 6.7 | AN77: 6 | AO77: 7 | AP77: 8 | AQ77: 7.5 | AR77: - | AS77: 8.5 | AU77: - | AV77: 10 | AW77: - | AX77: 10 | AY77: - | AZ77: 10 | BA77: - | BB77: 10 | BC77: - | BD77: 10 | BE77: - | BF77: 10 | BG77: - | BH77: 10 | BI77: - | BJ77: 10
A78: IND07527 | B78: IND08614 | C78: Cyber | D78: Photos/Nehaa-Chaudhari.webp | E78: Nehaa Chaudhari | F78: Nehaa Chaudhari has achieved a strong RISE reputation score, and was recommended by peers as a leading expert in data protection and technology policy and regulation. Her practice at Ikigai Law spans public policy, data protection compliance, AI governance, intermediary liability, telecom regulation, and cross-border data transfers alongside other commercial and transactional work. Clients include large US technology companies and foreign firms requiring India-specific advisory, and Indian startups across the full growth lifecycle. She receives a high score on the RISE sophistication of practice metric, based largely on a tech-savvy practice where she activities experiments with a range of new AI tools. | G78: Bengaluru | H78: Partner | I78: Ikigai Law | J78: 7.1 | K78: Top 10 | L78: 6 | M78: 6.3 | N78: 3.75 | O78: Top 10 | P78: 5 | Q78: 0 | R78: 8.7 | S78: 7.1 | T78: 6.9 | U78: 8 | V78: 7.9 | W78: 8.3 | X78: 7.9 | Y78: 8 | AA78: 6.2 | AB78: 7.6 | AC78: - | AD78: 0 | AE78: 9 | AF78: 8.8 | AG78: 7.5 | AH78: 7.5 | AI78: 6.8 | AJ78: 6.7 | AK78: Top 10 | AL78: 6 | AM78: 6.7 | AN78: 8 | AO78: 7 | AP78: - | AQ78: 6 | AR78: - | AS78: 8.5 | AU78: - | AV78: 10 | AW78: - | AX78: 10 | AY78: - | AZ78: 10 | BA78: - | BB78: 10 | BC78: - | BD78: 10 | BE78: - | BF78: 10 | BG78: - | BH78: 10 | BI78: - | BJ78: 10
A79: IND00494 | B79: IND00494 | C79: Capital Markets - Equity | D79: Photos/nikhil-naredi.png | E79: Nikhil Naredi | F79: Nikhil Naredi at Shardul Amarchand Mangaldas & Co. leads the firm's Mumbai capital markets team alongside Prashant Gupta in Delhi. His reputation scores are his strongest RISE metric. Highly regarded by peers, he draws repeat mandates from investment banks and PE houses, including Blackstone and Warburg Pincus portfolio companies. Marquee transactions include the Hyundai Motors IPO and the ICICI Prudential Mutual Fund IPO, notable for coordinating one of India's largest syndicates with 18 underwriters. His team holds mandates on two large REIT and InvIT transactions, including a circa $500mn Blackstone portfolio deal currently in progress. | G79: Mumbai | H79: Partner | I79: Shardul Amarchand Mangaldas & Co | J79: 8.1 | K79: Top 10 | L79: 6 | M79: 8.6 | N79: 4.9 | O79: Top 5 | P79: 9 | Q79: 3.2 | R79: 8.6 | S79: 6 | T79: 7 | U79: 6.8 | V79: 8.7 | W79: 8.5 | X79: 8.3 | Y79: 8.2 | AA79: 7.6 | AB79: 7.3 | AC79: 9 | AD79: 8.6 | AE79: 9.8 | AF79: 9.4 | AG79: 7.3 | AH79: 8.2 | AI79: 6.5 | AJ79: 7.1 | AL79: 6.7 | AM79: 7.3 | AN79: 7 | AO79: 7 | AP79: 6 | AQ79: 8 | AR79: - | AS79: 8.5 | AU79: - | AV79: 10 | AW79: - | AX79: 10 | AY79: - | AZ79: 10 | BA79: - | BB79: 10 | BC79: - | BD79: 10 | BE79: - | BF79: 10 | BG79: - | BH79: 10 | BI79: - | BJ79: 10
A80: IND00757 | B80: IND00757 | C80: Cyber | D80: Nikhil-Narendran-Partner-Trilegal.png | E80: Nikhil Narendran | F80: Nikhil Narendran ranks first in the 2026 RISE Cyber rating. He was the most mentioned practitioner in the market survey by a significant margin and receives the top reputation score. Cyber advice is part of Narendran's broad TMT sector practice and includes breach response, data protection implementation, AI regulatory strategy, and free speech litigation. His high instructions score draws on a client base that includes a number of global tech giants. A recent standout matter was securing a Supreme Court order reinstating a Wikimedia page taken down by Delhi High Court directive, a landmark free speech outcome in a politically challenging environment. Narendran also advises on AI policy and recently contributed to a Trilegal white paper on generative AI regulation used by the Indian government. | G80: Bengaluru | H80: Partner | I80: Trilegal | J80: 9 | K80: Ranked 1st | L80: 1 | M80: 9.8 | N80: 3.75 | O80: Ranked 1st | P80: 10 | Q80: 0 | R80: 9.6 | S80: 7.1 | T80: 9.7 | U80: 8 | V80: 9.7 | W80: 8.3 | X80: 9.3 | Y80: 8 | Z80: Ranked 2nd | AA80: 9.6 | AB80: 7.6 | AC80: - | AD80: 0 | AE80: 10 | AF80: 8.8 | AG80: 9 | AH80: 7.5 | AI80: 6.7 | AJ80: 6.7 | AK80: Top 10 | AL80: - | AM80: 6.7 | AN80: 7 | AO80: 7 | AP80: - | AQ80: 6 | AR80: 8.5 | AS80: 8.5 | AT80: Top 5 | AU80: 10 | AV80: 10 | AW80: 10 | AX80: 10 | AY80: 10 | AZ80: 10 | BA80: 10 | BB80: 10 | BC80: 10 | BD80: 10 | BE80: 10 | BF80: 10 | BG80: 10 | BH80: 10 | BI80: 10 | BJ80: 10
A81: IND00759 | B81: IND00759 | C81: Competition | D81: Photos/Nisha-Kaur-Uberoi-profile-picture.jpg | E81: Nisha Kaur Uberoi | F81: Nisha Kaur Uberoi at JSA is the highest-ranked practitioner in this RISE competition ranking, achieving the highest instruction score in the cohort and a reputation score that places her among the most visible competition lawyers in the Indian market. Clients select her specifically for the competition piece on major transactions, often independently of the firm handling the broader deal, and bring difficult matters to her team. Her matters include Apple's challenge to the CCI's penalty regime, major cartel defence work and multibillion-dollar merger control mandates for clients including Schneider, GIC and Nippon Steel. Complexity is a consistent feature: securing behavioural rather than divestment remedies, clearing difficult transactions without phase-two review, and working across the intersection of law, economics and commercial strategy. She has built a large specialist competition team and trains juniors to think as regulators as well as advisers, a deliberate investment in institutional depth which prevails over technology-led efficiency. | G81: Mumbai | H81: Partner | I81: JSA Advocates & Solicitors | J81: 9 | K81: Ranked 1st | L81: 1 | M81: 9.6 | N81: 5.6 | O81: Ranked 1st | P81: 9.9 | Q81: 4.1 | R81: 10 | S81: 7.5 | T81: 8 | U81: 5.9 | V81: 10 | W81: 8.3 | X81: 10 | Y81: 8.4 | Z81: Ranked 1st | AA81: 10 | AB81: 7.4 | AC81: - | AD81: 0 | AE81: 10 | AF81: 9.5 | AG81: 10 | AH81: 8.5 | AI81: 5.7 | AJ81: 6.7 | AL81: 3.3 | AM81: 6.7 | AN81: 6 | AO81: 7 | AP81: 8 | AQ81: 7.5 | AR81: 8.1 | AS81: 8.5 | AU81: 10 | AV81: 10 | AW81: 10 | AX81: 10 | AY81: 8 | AZ81: 10 | BA81: 10 | BB81: 10 | BC81: 10 | BD81: 10 | BE81: 10 | BF81: 10 | BG81: 10 | BH81: 10 | BI81: 8 | BJ81: 10
A82: IND00761 | B82: IND00761 | C82: Arbitration | D82: Photos/Nitesh Jain.png | E82: Nitesh Jain | F82: Nitesh Jain joined Trilegal in 2021 to strengthen the disputes practice. His RISE instruction score is his strongest metric, built on high-value cross-border mandates for clients including Blackstone, Mitsui and Zee Entertainment across seats in Singapore, London, and New York. A standout matter involved winning a SIAC arbitration, and successfully enforcing and implementing a foreign emergency order through to the Indian Court using an indirect mechanism. His RISE sophistication score reflects deliberate investment in talent. He divides cross-examination responsibilities between partners and team members, organised a mock cross-examination trial attended by around 100 general counsel and lawyers, and sends team members to conduct their own advocacy in domestic proceedings to build the instincts that complex international arbitrations require. | G82: Mumbai | H82: Partner | I82: Trilegal | J82: 8 | K82: Top 5 | L82: 5 | M82: 7 | N82: 3.6 | O82: Top 10 | P82: 7.2 | Q82: 1 | R82: 5.3 | S82: 7.1 | T82: 7.4 | U82: 6.3 | V82: 8.8 | W82: 8.9 | X82: 9.2 | Y82: 7.8 | Z82: Ranked 2nd | AA82: 7.5 | AB82: 7.6 | AC82: 9.4 | AD82: 7.5 | AE82: 9.2 | AF82: 7.4 | AG82: 9.8 | AH82: 8.7 | AI82: 7.3 | AJ82: 7.1 | AL82: 7.3 | AM82: 6.7 | AN82: 4 | AO82: 6 | AP82: 9 | AQ82: 7.5 | AR82: - | AS82: 8.3 | AU82: - | AV82: 10 | AW82: - | AX82: 10 | AY82: - | AZ82: 10 | BA82: - | BB82: 10 | BC82: - | BD82: 10 | BE82: - | BF82: 10 | BG82: - | BH82: 10 | BI82: - | BJ82: 10
A83: IND00140 | B83: IND00140 | C83: Capital Markets - Equity | D83: Photos/Oishik Bagchi_0.png | E83: Oishik Bagchi | F83: Oishik Bagchi scores most strongly on instructions and sophistication in the RISE metrics, with talent development and client base his standout sub-indicators. Bagchi starts his junior training programme each June with new hires, running weekly sessions on drafting and capital markets processes, supplemented by a course with Gujarat National Law University. It blends online and offline teaching and functions as a recruitment pipeline. His client base spans Morgan Stanley, Citi, Goldman Sachs, and ICICI Securities on the banking side and Vikram Solar and Force Cry on the company side, with clients often retained post-IPO for follow-on work. The Vikram Solar IPO, executed in a nascent renewable energy sector with limited precedent and disputes managed in court late in the timeline, illustrates the complexity of his practice. | G83: Mumbai | H83: Partner | I83: Khaitan & Co | J83: 5.4 | L83: 34 | M83: 2 | N83: 4.9 | P83: 0 | Q83: 3.2 | R83: 0 | S83: 6 | T83: 7.2 | U83: 6.8 | V83: 8.8 | W83: 8.5 | X83: 7.9 | Y83: 8.2 | AA83: 7.1 | AB83: 7.3 | AC83: 7.9 | AD83: 8.6 | AE83: 9.4 | AF83: 9.4 | AG83: 7.5 | AH83: 8.2 | AI83: 7.5 | AJ83: 7.1 | AL83: 7.3 | AM83: 7.3 | AN83: 7 | AO83: 7 | AP83: 8 | AQ83: 8 | AR83: 9.4 | AS83: 8.5 | AT83: Top 10 | AU83: 9.4 | AV83: 10 | AW83: 9.4 | AX83: 10 | AY83: 9.4 | AZ83: 10 | BA83: 9.4 | BB83: 10 | BC83: 9.4 | BD83: 10 | BE83: 8.6 | BF83: 10 | BG83: 9.4 | BH83: 10 | BI83: 9.4 | BJ83: 10
A84: IND00777 | B84: IND00777 | C84: Capital Markets - Equity | D84: Photos/Richa Choudhary.png | E84: Richa Choudhary | F84: One of the younger practitioners near the top of the RISE rankings, Richa Choudhary at Trilegal has notable instruction scores, with a client base score that reflects the blue chip quality of her clients. She works across both equity and debt capital markets and scores highest overall for volume of matters while maintaining strong deal quality. One of her most distinctive transactions is the first listing on India's Social Stock Exchange, advising SGBS Unnati Foundation on a Zero Coupon Zero Principal instrument IPO with no prior template. The structure attracted enough international attention that the Malaysian Stock Exchange approached her team for guidance on setting up a comparable framework. | G84: Mumbai | H84: Partner | I84: Trilegal | J84: 8.2 | K84: Top 5 | L84: 5 | M84: 6.6 | N84: 4.9 | P84: 5 | Q84: 3.2 | R84: 9 | S84: 6 | T84: 7 | U84: 6.8 | V84: 9.7 | W84: 8.5 | X84: 9.8 | Y84: 8.2 | Z84: Ranked 1st | AA84: 10 | AB84: 7.3 | AC84: 9.9 | AD84: 8.6 | AE84: 10 | AF84: 9.4 | AG84: 9.5 | AH84: 8.2 | AI84: 8.3 | AJ84: 7.1 | AK84: Ranked 3rd | AL84: 8.7 | AM84: 7.3 | AN84: 6 | AO84: 7 | AP84: 9 | AQ84: 8 | AR84: 8.8 | AS84: 8.5 | AT84: Top 10 | AU84: 10 | AV84: 10 | AW84: 9 | AX84: 10 | AY84: 9 | AZ84: 10 | BA84: 9 | BB84: 10 | BC84: 8 | BD84: 10 | BE84: 9 | BF84: 10 | BG84: 9 | BH84: 10 | BI84: 9 | BJ84: 10
A85: IND01511 | B85: IND01511 | C85: Competition | D85: Photos/Parthsarathi Jha.jpg | E85: Parthsarathi Jha | F85: Parthsarathi Jha at Economic Laws Practice appears in both the international trade and competition RISE rating, a dual recognition that reflects the quality of mandate his practice attracts in both. He scores most strongly on the reputation and instructions RISE metrics for international trade, with the third-highest number of peer recommendations and a client base that includes the Government of India, whom he is currently advising on an ongoing WTO dispute with China concerning production incentive schemes in the EV sector. Jha also scores strongly on instructions for his competition work. Overall, his practice sits at the intersection of trade and technology, advising major technology companies and large e-commerce platforms on trade policy issues where cloud infrastructure and digital commerce create novel regulatory questions. | G85: Delhi | H85: Partner | I85: Economic Laws Practice | J85: 5.9 | L85: 30 | M85: 3.6 | N85: 5.6 | P85: 3 | Q85: 4.1 | R85: 5.8 | S85: 7.5 | T85: 0 | U85: 5.9 | V85: 8.6 | W85: 8.3 | X85: 8 | Y85: 8.4 | AA85: 5.9 | AB85: 7.4 | AC85: - | AD85: 0 | AE85: 9.8 | AF85: 9.5 | AG85: 8 | AH85: 8.5 | AI85: 6.3 | AJ85: 6.7 | AL85: 5.3 | AM85: 6.7 | AN85: 7 | AO85: 7 | AP85: 7 | AQ85: 7.5 | AR85: 7.9 | AS85: 8.5 | AU85: 8 | AV85: 10 | AW85: 10 | AX85: 10 | AY85: 8 | AZ85: 10 | BA85: 10 | BB85: 10 | BC85: 8 | BD85: 10 | BE85: 10 | BF85: 10 | BG85: 10 | BH85: 10 | BI85: 10 | BJ85: 10
A86: IND01511 | B86: IND01511 | C86: International Trade | D86: Photos/Parthsarathi Jha.jpg | E86: Parthsarathi Jha | F86: Parthsarathi Jha at Economic Laws Practice appears in both the international trade and competition RISE rating, a dual recognition that reflects the quality of mandate his practice attracts in both. He scores most strongly on the reputation and instructions RISE metrics for international trade, with the third-highest number of peer recommendations and a client base that includes the Government of India, whom he is currently advising on an ongoing WTO dispute with China concerning production incentive schemes in the EV sector. Jha also scores strongly on instructions for his competition work. Overall, his practice sits at the intersection of trade and technology, advising major technology companies and large e-commerce platforms on trade policy issues where cloud infrastructure and digital commerce create novel regulatory questions. | G86: Delhi | H86: Partner | I86: Economic Laws Practice | J86: 7.5 | K86: Top 5 | L86: 5 | M86: 7 | N86: 3.35 | O86: Top 5 | P86: 8.3 | Q86: 0 | R86: 7.1 | S86: 7.1 | T86: 0 | U86: 7.1 | V86: 9.8 | W86: 8.9 | X86: 8.5 | Y86: 8.6 | AA86: 6.7 | AB86: 8.6 | AC86: - | AD86: 0 | AE86: 9.6 | AF86: 8.9 | AG86: 8.8 | AH86: 8.7 | AI86: 6.3 | AJ86: 6.4 | AK86: Top 10 | AL86: 5.3 | AM86: 5.3 | AN86: 7 | AO86: 7 | AP86: 7 | AQ86: 7.5 | AR86: 7.9 | AS86: 8.3 | AU86: 8 | AV86: 10 | AW86: 10 | AX86: 10 | AY86: 8 | AZ86: 10 | BA86: 10 | BB86: 10 | BC86: 8 | BD86: 10 | BE86: 10 | BF86: 10 | BG86: 10 | BH86: 10 | BI86: 10 | BJ86: 10
A87: IND00033 | B87: IND00033 | C87: Competition | D87: Photos/Anisha Chand.jpg | E87: Anisha Chand | F87: Placed 15th in the 2026 RISE Competition list, Anisha Chand has high sophistication and experience scores. Within the Sophisitcation score, Chand's attention to talent development and approach to pricing reflect a practice with little attritition rate and encouragement to junior lawyers to experiment AI within upskilling courses. Chand's Instruction scores with client quality and mandate value as the leading contributing metrics. This reflects a practice built on sustained throughput in substantial merger control work rather than mere high-profile visibility. Her instructions profile points to consistent flow from large strategic and sponsor-led transactions, with the team among the most active in Indian merger control by filing volume and particularly prominent in long-form notifications. The practice is notable for sitting where scale and complexity meet — form-two filings, borderline-modification matters and transactions where the work centres on data-heavy advocacy to avoid remedies rather than reacting to a clearance problem already in motion. Beyond merger control, Chand maintains a full-spectrum competition practice spanning cartel matters, leniency work, complainant-side mandates and compliance programmes for global platforms, with a developing strand of advisory at the competition-privacy intersection. The firm is investing in technology infrastructure across the practice, including internal AI tools and external platforms. | G87: Mumbai | H87: Partner | I87: Khaitan & Co | J87: 7.2 | L87: 15 | M87: 6.8 | N87: 5.6 | P87: 6.5 | Q87: 4.1 | R87: 7.5 | S87: 7.5 | T87: 5.9 | U87: 5.9 | V87: 8.4 | W87: 8.3 | X87: 7.2 | Y87: 8.4 | AA87: 8.2 | AB87: 7.4 | AC87: - | AD87: 0 | AE87: 7.4 | AF87: 9.5 | AG87: 6.5 | AH87: 8.5 | AI87: 8.1 | AJ87: 6.7 | AK87: Top 5 | AL87: 6.7 | AM87: 6.7 | AN87: 9 | AO87: 7 | AP87: 9 | AQ87: 7.5 | AR87: 8.3 | AS87: 8.5 | AU87: 10 | AV87: 10 | AW87: 10 | AX87: 10 | AY87: 10 | AZ87: 10 | BA87: 8 | BB87: 10 | BC87: 10 | BD87: 10 | BE87: 10 | BF87: 10 | BG87: 10 | BH87: 10 | BI87: 10 | BJ87: 10
A88: IND04763 | B88: IND04763 | C88: Capital Markets - Debt | D88: Photos/Pranav Sharma - CAM.jpg | E88: Pranav Sharma | F88: Placed fourth in the 2026 RISE Debt Capital Market rating, Pranav Sharma's practice stands out for RISE instruction and experience metrics. Across all the RISE metrics, Sharma scores particularly well for a strong client base, social media profile, and interesting approach to pricing. His practice is focused on debt capital markets, covering onshore INR bonds, securitisations, derivatives, and offshore euro bonds, with clients including Kotak, IFC, Blackstone and other leading institutional investors and lenders. His pricing approach involves an internal cost estimation tool applied once key deal parameters are known, part of a broader effort to standardise DCM work by borrowing process discipline from equity teams. Sharma describes his practice as having two defining characteristics: a directness in client communication, including a willingness to deliver difficult messages and a client-first philosophy. | G88: Mumbai | H88: Partner | I88: Cyril Amarchand Mangaldas | J88: 7 | K88: Top 5 | L88: 4 | M88: 6.2 | N88: 4 | O88: Top 5 | P88: 5.5 | Q88: 2.9 | R88: 6 | S88: 5.8 | T88: 6.4 | U88: 7.5 | V88: 10 | W88: 9.3 | X88: 8.3 | Y88: 8.4 | Z88: Top 10 | AA88: 7.7 | AB88: 8.5 | AC88: 7.3 | AD88: 7.9 | AE88: 9.8 | AF88: 8.8 | AG88: 8.2 | AH88: 8.7 | AI88: 6 | AJ88: 6.6 | AK88: Top 10 | AL88: 6 | AM88: 6.7 | AN88: 8 | AO88: 6 | AP88: 5 | AQ88: 7 | AR88: 8.7 | AS88: 8.7 | AT88: Ranked 3rd | AU88: 9 | AV88: 9.6 | AW88: 10 | AX88: 10 | AY88: 10 | AZ88: 10 | BA88: 10 | BB88: 10 | BC88: 8 | BD88: 10 | BE88: 10 | BF88: 10 | BG88: 7 | BH88: 10 | BI88: 7 | BJ88: 9.6
A89: IND01030 | B89: IND01030 | C89: Competition | D89: Photos/Samir Gandhi.png | E89: Samir R Gandhi | F89: Placed in the top 5 RISE Competition rating, Samir Gandhi's highest scores are in his instruction and experience scores. Although Gandhi performs remarkably well across all the RISE reputation metrics, including for peer mentions and directories, his Instruction metrics reflect a busy practice of complex work for top-tier, sophisticated and typically global clients. From his performance within the experience score, clients appear to trust and enjoy working with Gandhi and award him top or near-top marks across the board. His practice spans merger control, enforcement and competition litigation, with a distinctively commercial style of advice that centres on outcomes: knowing when to negotiate, when to litigate and how to preserve credibility before the CCI. Particularly strong on matters sitting at the intersection of competition law, including merger remedies in insolvency contexts and the overlap between antitrust, privacy, data and IP. That breadth of analytical framing, rather than narrow doctrinal specialism, appears to be a consistent feature of the more complex instructions he describes. Gandhi also appears comparatively advanced among Indian competition practitioners in deploying technology within the practice, using AI-assisted workflows and internal knowledge systems to handle large volumes of client data and filing trends, while keeping partner judgement central to the advice. | G89: Delhi | H89: Partner | I89: Axiom5 | J89: 8.6 | K89: Top 5 | L89: 4 | M89: 8.3 | N89: 5.6 | O89: Top 5 | P89: 8.5 | Q89: 4.1 | R89: 9 | S89: 7.5 | T89: 6.4 | U89: 5.9 | V89: 8.3 | W89: 8.3 | X89: 9.1 | Y89: 8.4 | Z89: Top 10 | AA89: 8.3 | AB89: 7.4 | AC89: - | AD89: 0 | AE89: 9.9 | AF89: 9.5 | AG89: 9 | AH89: 8.5 | AI89: 8.4 | AJ89: 6.7 | AK89: Ranked 3rd | AL89: 8 | AM89: 6.7 | AN89: 8 | AO89: 7 | AP89: 9 | AQ89: 7.5 | AR89: 9.8 | AS89: 8.5 | AT89: Ranked 1st | AU89: 10 | AV89: 10 | AW89: 10 | AX89: 10 | AY89: 10 | AZ89: 10 | BA89: 10 | BB89: 10 | BC89: 10 | BD89: 10 | BE89: 10 | BF89: 10 | BG89: 7.6 | BH89: 10 | BI89: 10 | BJ89: 10
A90: IND02009 | B90: IND02009 | C90: Capital Markets - Equity | D90: Photos/Pracheta-Bhattacharya-profile-picture.jpg | E90: Pracheta Bhattacharya | F90: Pracheta Bhattacharya's instruction scores are his strongest RISE metric at JSA, with client base and deal value among the strongest sub-indicators, built on relationships with IIFL, Axis, Kotak, and other domestic and international merchant banks. Bhattacharya's practice spans equity capital markets with InvITs and REITs as a core specialism, an unusual combination that few practitioners in this cohort have developed to the same depth. What distinguishes his current client profile is a deliberate concentration on government-linked infrastructure mandates, including the Ministry of Coal and Ministry of Roads, at a moment when disinvestment targets are becoming more aggressive. The NHAI fundraise at approximately US$560mn illustrates that positioning. | G90: Mumbai | H90: Partner | I90: JSA Advocates & Solicitors | J90: 5.6 | L90: 32 | M90: 2.2 | N90: 4.9 | P90: 0 | Q90: 3.2 | R90: 4.7 | S90: 6 | T90: 3.3 | U90: 6.8 | V90: 7.7 | W90: 8.5 | X90: 8.5 | Y90: 8.2 | AA90: 8.3 | AB90: 7.3 | AC90: 8.8 | AD90: 8.6 | AE90: 9.8 | AF90: 9.4 | AG90: 7.8 | AH90: 8.2 | AI90: 6.3 | AJ90: 7.1 | AL90: 5.3 | AM90: 7.3 | AN90: - | AO90: 7 | AP90: - | AQ90: 8 | AR90: 7.2 | AS90: 8.5 | AU90: 8 | AV90: 10 | AW90: 10 | AX90: 10 | AY90: 8 | AZ90: 10 | BA90: 8 | BB90: 10 | BC90: 8 | BD90: 10 | BE90: 8 | BF90: 10 | BG90: 8 | BH90: 10 | BI90: 8 | BJ90: 10
A91: IND00153 | B91: IND00153 | C91: Competition | D91: Photos/Pranjal Prateek_0.png | E91: Pranjal Prateek | F91: Pranjal Prateek at Khaitan & Co scores most notably on RISE instruction and sophistication metrics, with Clients and Complexity the standout sub-indicators. His mandates reflect increasing complexity driven by prolonged regulator engagement, evolving enforcement scenarios, and the need to coordinate strategy across multiple stakeholders. AI usage is notable within his RISE sophistication scores. He uses the firm's KAI platform to analyse regulator decisions, identify trends, and support internal knowledge sharing, with automation applied to routine workflows such as document templates and chronologies, and a human-in-the-loop approach maintained for judgement-led work. His practice is concentrated in pharma, technology, consumer, and infrastructure, where competition scrutiny is closely linked to transactional and enforcement activity. He grounds opinions in first principles and takes a measured, non-sales-led approach to client work. | G91: Delhi | H91: Partner | I91: Khaitan & Co | J91: 6.7 | L91: 23 | M91: 4.7 | N91: 5.6 | P91: 3 | Q91: 4.1 | R91: 7.5 | S91: 7.5 | T91: 5.2 | U91: 5.9 | V91: 8.2 | W91: 8.3 | X91: 8.1 | Y91: 8.4 | AA91: 6.6 | AB91: 7.4 | AC91: - | AD91: 0 | AE91: 9.2 | AF91: 9.5 | AG91: 8 | AH91: 8.5 | AI91: 7.9 | AJ91: 6.7 | AK91: Top 10 | AL91: 8.7 | AM91: 6.7 | AN91: 6 | AO91: 7 | AP91: 8 | AQ91: 7.5 | AR91: 8.5 | AS91: 8.5 | AU91: 10 | AV91: 10 | AW91: 10 | AX91: 10 | AY91: 10 | AZ91: 10 | BA91: 10 | BB91: 10 | BC91: 10 | BD91: 10 | BE91: 10 | BF91: 10 | BG91: 10 | BH91: 10 | BI91: 10 | BJ91: 10
A92: IND00502 | B92: IND00502 | C92: Capital Markets - Equity | D92: Photos/prashant-Gupta.png | E92: Prashant Gupta | F92: Prashant Gupta is the number one ranked equity capital markets RISE lawyer in this year's cohort. He received more peer recommendations than any other practitioner. The majority (80%) of his book of work is on deals above US$250mn, and he acts as issuer counsel on large marquee technology and internet transactions, as well as for global multinationals. The complexity on these technology and internet mandates tends to come from regulator scepticism toward loss-making companies, fragmented cap tables, and shareholders who all want different things. His issuer counsel role on one of India's largest IPOs for Hyundai at approximately US$3 billion illustrates the level at which he operates. | G92: Delhi | H92: National Practice Head of Capital Markets | I92: Shardul Amarchand Mangaldas & Co | J92: 9.3 | K92: Ranked 1st | L92: 1 | M92: 9.7 | N92: 4.9 | O92: Ranked 1st | P92: 10 | Q92: 3.2 | R92: 9.8 | S92: 6 | T92: 8.9 | U92: 6.8 | V92: 9.5 | W92: 8.5 | X92: 9.2 | Y92: 8.2 | Z92: Ranked 2nd | AA92: 7.3 | AB92: 7.3 | AC92: 9.9 | AD92: 8.6 | AE92: 9.9 | AF92: 9.4 | AG92: 9.2 | AH92: 8.2 | AI92: 8.7 | AJ92: 7.1 | AK92: Ranked 1st | AL92: 7.3 | AM92: 7.3 | AN92: 9 | AO92: 7 | AP92: 10 | AQ92: 8 | AR92: 10 | AS92: 8.5 | AT92: Ranked 1st | AU92: 10 | AV92: 10 | AW92: 10 | AX92: 10 | AY92: 10 | AZ92: 10 | BA92: 10 | BB92: 10 | BC92: 10 | BD92: 10 | BE92: 10 | BF92: 10 | BG92: 10 | BH92: 10 | BI92: 10 | BJ92: 10
